Workbook

Sheet Sheet2
A1: OT
A2: OT-50811 | B2: 45870 | C2: 45870 | D2: 45873 | E2: 45871 | F2: 2266 | G2: Jose Ruben Hernandez Ruiz | H2: 7247XC | I2: USIMECA | J2: Sis Cd Hidalgo
A3: OT-50812 | B3: 45870 | C3: 45870 | D3: 45873 | E3: 45871 | F3: 2045 | G3: Ariel Ines Simbron Avila | H3: 5000XC | I3: USIMECA | J3: Sis Cd Hidalgo
A4: OT-50813 | B4: 45870 | C4: 45870 | D4: 45873 | E4: 45871 | F4: 1867 | G4: Jose Juan Olvera Marquez | H4: 2619XC | I4: USIMECA | J4: Sis Cd Hidalgo
A5: OT-50814 | B5: 45870 | C5: 45870 | D5: 45873 | E5: 45871 | F5: 2379 | G5: Enrique Cruz Hernandez | H5: 4544XC | I5: USIMECA | J5: Sis Cd Hidalgo
A6: OT-50815 | B6: 45870 | C6: 45870 | D6: 45873 | E6: 45871 | F6: 2344 | G6: Luis Alberto Perez Rendon | H6: 5510XC | I6: USIMECA | J6: Sis Cd Hidalgo
A7: OT-50816 | B7: 45870 | C7: 45870 | D7: 45873 | E7: 45871 | F7: 2260 | G7: Jesus Manuel Villalpa Islas | H7: 4659XC | I7: USIMECA | J7: Sis Cd Hidalgo
A11: 2266 | B11: Jose Ruben Hernandez Ruiz
A12: 2045 | B12: Ariel Ines Simbron Avila
A13: 1867 | B13: Jose Juan Olvera Marquez
A14: 2379 | B14: Enrique Cruz Hernandez
A15: 2344 | B15: Luis Alberto Perez Rendon
A16: 2260 | B16: Jesus Manuel Villalpa Islas

Sheet Guia de tarjetas
B2: Matricula | C2: Nombre | D2: Fecha de Nacimiento | E2: Nombres | F2: Apellidos | G2: Número de tarjeta | H2: Vencimiento | I2: CVV | J2: Reserva | K2: Número de Reserva | L2: Costo | M2: Costo por cambio | N2: Suma con cambio | O2: COMENTARIOS | P2: OT
B3: =INDEX(TUSA!$A:$A,MATCH($C3,TUSA!$BK:$BK,0),1) -> 2219 | C3: Francisco Gabriel Lopez Vertis | D3: =INDEX(TUSA!F:$F,MATCH($C3,TUSA!$BK:$BK,0),1) -> 32454 | E3: =INDEX(TUSA!D:D,MATCH($C3,TUSA!$BK:$BK,0),1) -> Francisco Gabriel | F3: {=INDEX(TUSA!B:B&" "&TUSA!C:C,MATCH($C3,TUSA!$BK:$BK,0),1)} -> Lopez Vertis | G3: =+VLOOKUP(B3,Tarjetas!$B:$K,3,FALSE()) -> 5227940202759980 | H3: =+VLOOKUP(B3,Tarjetas!$B:$K,10,FALSE()) -> 45836 | I3: =+VLOOKUP(B3,Tarjetas!$B:$K,9,FALSE()) -> 463 | J3: Martes 12:33 | K3: RY2CKY | L3: 2389 | M3: 422 | N3: =+Table4[[#This Row],[Costo]]+Table4[[#This Row],[Costo por cambio]] -> 2811 | O3: YA VOLÓ | P3: OT-5081166
B4: =INDEX(TUSA!$A:$A,MATCH($C4,TUSA!$BK:$BK,0),1) -> 2358 | C4: Angel Abraham Lopez Romero | D4: =INDEX(TUSA!F:$F,MATCH($C4,TUSA!$BK:$BK,0),1) -> 37288 | E4: =INDEX(TUSA!D:D,MATCH($C4,TUSA!$BK:$BK,0),1) -> Angel Abraham | F4: {=INDEX(TUSA!B:B&" "&TUSA!C:C,MATCH($C4,TUSA!$BK:$BK,0),1)} -> Lopez Romero | G4: =+VLOOKUP(B4,Tarjetas!$B:$K,3,FALSE()) -> 5227940202997270 | H4: =+VLOOKUP(B4,Tarjetas!$B:$K,10,FALSE()) -> 46019 | I4: =+VLOOKUP(B4,Tarjetas!$B:$K,9,FALSE()) -> 634 | J4: Martes 12:33 | K4: LYVRFF | L4: 2386 | M4: 464 | N4: =+Table4[[#This Row],[Costo]]+Table4[[#This Row],[Costo por cambio]] -> 2850 | O4: YA VOLÓ | P4: OT-5081164
B5: =INDEX(TUSA!$A:$A,MATCH($C5,TUSA!$BK:$BK,0),1) -> 2378 | C5: Guillermo Hernandez Abundiz | D5: =INDEX(TUSA!F:$F,MATCH($C5,TUSA!$BK:$BK,0),1) -> 32714 | E5: =INDEX(TUSA!D:D,MATCH($C5,TUSA!$BK:$BK,0),1) -> Guillermo | F5: {=INDEX(TUSA!B:B&" "&TUSA!C:C,MATCH($C5,TUSA!$BK:$BK,0),1)} -> Hernandez Abundiz | G5: =+VLOOKUP(B5,Tarjetas!$B:$K,3,FALSE()) -> 5227940203167610 | H5: =+VLOOKUP(B5,Tarjetas!$B:$K,10,FALSE()) -> 47150 | I5: =+VLOOKUP(B5,Tarjetas!$B:$K,9,FALSE()) -> 474 | J5: Martes 12:33 | K5: BGL7NQ | L5: 2399 | M5: 422 | N5: =+Table4[[#This Row],[Costo]]+Table4[[#This Row],[Costo por cambio]] -> 2821 | O5: YA VOLÓ | P5: OT-5081167
B6: =INDEX(TUSA!$A:$A,MATCH($C6,TUSA!$BK:$BK,0),1) -> 2386 | C6: Gabriel Fuentes Sibaja | D6: =INDEX(TUSA!F:$F,MATCH($C6,TUSA!$BK:$BK,0),1) -> 25629 | E6: =INDEX(TUSA!D:D,MATCH($C6,TUSA!$BK:$BK,0),1) -> Gabriel | F6: {=INDEX(TUSA!B:B&" "&TUSA!C:C,MATCH($C6,TUSA!$BK:$BK,0),1)} -> Fuentes Sibaja | G6: =+VLOOKUP(B6,Tarjetas!$B:$K,3,FALSE()) -> 5227940203167560 | H6: =+VLOOKUP(B6,Tarjetas!$B:$K,10,FALSE()) -> 47150 | I6: =+VLOOKUP(B6,Tarjetas!$B:$K,9,FALSE()) -> 534 | J6: Martes 12:33 | K6: A933TY | L6: 2551 | M6: 270 | N6: =+Table4[[#This Row],[Costo]]+Table4[[#This Row],[Costo por cambio]] -> 2821 | O6: YA VOLÓ | P6: OT-5081165
B8: =INDEX(TUSA!$A:$A,MATCH($C8,TUSA!$BK:$BK,0),1) -> 1818 | C8: Leonardo Moreno Lopez | D8: =INDEX(TUSA!F:$F,MATCH($C8,TUSA!$BK:$BK,0),1) -> 28621 | E8: =INDEX(TUSA!D:D,MATCH($C8,TUSA!$BK:$BK,0),1) -> Leonardo | F8: {=INDEX(TUSA!B:B&" "&TUSA!C:C,MATCH($C8,TUSA!$BK:$BK,0),1)} -> Moreno Lopez | G8: =+VLOOKUP(B8,Tarjetas!$B:$K,3,FALSE()) -> 5227940203167630 | H8: =+VLOOKUP(B8,Tarjetas!$B:$K,10,FALSE()) -> 47150 | I8: =+VLOOKUP(B8,Tarjetas!$B:$K,9,FALSE()) -> 608 | J8: Miercoles 12:33 | K8: P9D7JL | L8: 2252 | M8: 807 | N8: =+Table4[[#This Row],[Costo]]+Table4[[#This Row],[Costo por cambio]] -> 3059 | O8: CAMBIO HECHO facturado | P8: =+VLOOKUP(Table4[[#This Row],[Matricula]],OTS!A:C,3,FALSE) -> OT-5081170
B9: =INDEX(TUSA!$A:$A,MATCH($C9,TUSA!$BK:$BK,0),1) -> 2162 | C9: Jorge Brindis Juarez | D9: =INDEX(TUSA!F:$F,MATCH($C9,TUSA!$BK:$BK,0),1) -> 27208 | E9: =INDEX(TUSA!D:D,MATCH($C9,TUSA!$BK:$BK,0),1) -> Jorge | F9: {=INDEX(TUSA!B:B&" "&TUSA!C:C,MATCH($C9,TUSA!$BK:$BK,0),1)} -> Brindis Juarez | G9: =+VLOOKUP(B9,Tarjetas!$B:$K,3,FALSE()) -> 5227940202760600 | H9: =+VLOOKUP(B9,Tarjetas!$B:$K,10,FALSE()) -> 45836 | I9: =+VLOOKUP(B9,Tarjetas!$B:$K,9,FALSE()) -> 923 | J9: Miercoles 12:33 | K9: P9D7JL | L9: 2252 | M9: 807 | N9: =+Table4[[#This Row],[Costo]]+Table4[[#This Row],[Costo por cambio]] -> 3059 | O9: CAMBIO HECHO facturado | P9: =+VLOOKUP(Table4[[#This Row],[Matricula]],OTS!A:C,3,FALSE) -> OT-5081178
B11: =INDEX(TUSA!$A:$A,MATCH($C11,TUSA!$BK:$BK,0),1) -> 2370 | C11: Oscar Carmona Rocha | D11: =INDEX(TUSA!F:$F,MATCH($C11,TUSA!$BK:$BK,0),1) -> 35807 | E11: =INDEX(TUSA!D:D,MATCH($C11,TUSA!$BK:$BK,0),1) -> Oscar | F11: {=INDEX(TUSA!B:B&" "&TUSA!C:C,MATCH($C11,TUSA!$BK:$BK,0),1)} -> Carmona Rocha | G11: 5227940202997287 | H11: 12/28 | I11: =+VLOOKUP(B11,Tarjetas!$B:$K,9,FALSE()) -> 933 | J11: Miercoles 12:33 | K11: FDJC2J | L11: 2609 | M11: 426 | N11: =+Table4[[#This Row],[Costo]]+Table4[[#This Row],[Costo por cambio]] -> 3035 | O11: CAMBIO HECHO | P11: =+VLOOKUP(Table4[[#This Row],[Matricula]],OTS!A:C,3,FALSE) -> OT-5081174
B12: =INDEX(TUSA!$A:$A,MATCH($C12,TUSA!$BK:$BK,0),1) -> 2275 | C12: Salvador Vazquez Tlapalamatl | D12: =INDEX(TUSA!F:$F,MATCH($C12,TUSA!$BK:$BK,0),1) -> 38257 | E12: =INDEX(TUSA!D:D,MATCH($C12,TUSA!$BK:$BK,0),1) -> Salvador | F12: {=INDEX(TUSA!B:B&" "&TUSA!C:C,MATCH($C12,TUSA!$BK:$BK,0),1)} -> Vazquez Tlapalamatl | G12: 5227940202714179 | H12: 05/28 | I12: =+VLOOKUP(B12,Tarjetas!$B:$K,9,FALSE()) -> 75 | J12: Miercoles 12:33 | K12: VKGYPX | L12: 2609 | M12: 402 | N12: =+Table4[[#This Row],[Costo]]+Table4[[#This Row],[Costo por cambio]] -> 3011 | O12: CAMBIO HECHO | P12: =+VLOOKUP(Table4[[#This Row],[Matricula]],OTS!A:C,3,FALSE) -> OT-5081176
B13: =INDEX(TUSA!$A:$A,MATCH($C13,TUSA!$BK:$BK,0),1) -> 2218 | C13: Luis Uribe Quintero | D13: =INDEX(TUSA!F:$F,MATCH($C13,TUSA!$BK:$BK,0),1) -> 32777 | E13: =INDEX(TUSA!D:D,MATCH($C13,TUSA!$BK:$BK,0),1) -> Luis | F13: {=INDEX(TUSA!B:B&" "&TUSA!C:C,MATCH($C13,TUSA!$BK:$BK,0),1)} -> Uribe Quintero | G13: 5227940202193630 | H13: 04/27 | I13: =+VLOOKUP(B13,Tarjetas!$B:$K,9,FALSE()) -> 769 | J13: Miercoles 12:33 | K13: MK5HGH | L13: 2609 | M13: 392 | N13: =+Table4[[#This Row],[Costo]]+Table4[[#This Row],[Costo por cambio]] -> 3001 | O13: CAMBIO HECHO | P13: =+VLOOKUP(Table4[[#This Row],[Matricula]],OTS!A:C,3,FALSE) -> OT-5081177
B14: =INDEX(TUSA!$A:$A,MATCH($C14,TUSA!$BK:$BK,0),1) -> 2211 | C14: Jonathan Uribe Quintero | D14: =INDEX(TUSA!F:$F,MATCH($C14,TUSA!$BK:$BK,0),1) -> 35956 | E14: =INDEX(TUSA!D:D,MATCH($C14,TUSA!$BK:$BK,0),1) -> Jonathan | F14: {=INDEX(TUSA!B:B&" "&TUSA!C:C,MATCH($C14,TUSA!$BK:$BK,0),1)} -> Uribe Quintero | G14: 5227940202193036 | H14: 04/27 | I14: =+VLOOKUP(B14,Tarjetas!$B:$K,9,FALSE()) -> 454 | J14: Miercoles 12:33 | K14: ZJ6KWA | L14: 2609 | M14: 627 | N14: =+Table4[[#This Row],[Costo]]+Table4[[#This Row],[Costo por cambio]] -> 3236 | O14: CAMBIO HECHO | P14: =+VLOOKUP(Table4[[#This Row],[Matricula]],OTS!A:C,3,FALSE) -> OT-5081172
B15: =INDEX(TUSA!$A:$A,MATCH($C15,TUSA!$BK:$BK,0),1) -> 2195 | C15: Aurelio Jaime Perez Martinez | D15: =INDEX(TUSA!F:$F,MATCH($C15,TUSA!$BK:$BK,0),1) -> 27663 | E15: =INDEX(TUSA!D:D,MATCH($C15,TUSA!$BK:$BK,0),1) -> Aurelio Jaime | F15: {=INDEX(TUSA!B:B&" "&TUSA!C:C,MATCH($C15,TUSA!$BK:$BK,0),1)} -> Perez Martinez | G15: 5227940202714237 | H15: 05/28 | I15: =+VLOOKUP(B15,Tarjetas!$B:$K,9,FALSE()) -> 124 | J15: Miercoles 12:33 | K15: F8MCJL | L15: 2609 | M15: 617 | N15: =+Table4[[#This Row],[Costo]]+Table4[[#This Row],[Costo por cambio]] -> 3226 | O15: CAMBIO HECHO | P15: =+VLOOKUP(Table4[[#This Row],[Matricula]],OTS!A:C,3,FALSE) -> OT-5081171
B16: =INDEX(TUSA!$A:$A,MATCH($C16,TUSA!$BK:$BK,0),1) -> 2133 | C16: Martin Cuellar Campos | D16: =INDEX(TUSA!F:$F,MATCH($C16,TUSA!$BK:$BK,0),1) -> 27212 | E16: =INDEX(TUSA!D:D,MATCH($C16,TUSA!$BK:$BK,0),1) -> Martin | F16: {=INDEX(TUSA!B:B&" "&TUSA!C:C,MATCH($C16,TUSA!$BK:$BK,0),1)} -> Cuellar Campos | G16: 5227940202759943 | H16: 06/28 | I16: =+VLOOKUP(B16,Tarjetas!$B:$K,9,FALSE()) -> 538 | J16: Miercoles 12:33 | K16: XL33NH | L16: 2570 | M16: 656 | N16: =+Table4[[#This Row],[Costo]]+Table4[[#This Row],[Costo por cambio]] -> 3226 | O16: CAMBIO HECHO | P16: =+VLOOKUP(Table4[[#This Row],[Matricula]],OTS!A:C,3,FALSE) -> OT-5081169
B17: =INDEX(TUSA!$A:$A,MATCH($C17,TUSA!$BK:$BK,0),1) -> 912 | C17: Ramon Mario Hernandez Lagos | D17: =INDEX(TUSA!F:$F,MATCH($C17,TUSA!$BK:$BK,0),1) -> 23985 | E17: =INDEX(TUSA!D:D,MATCH($C17,TUSA!$BK:$BK,0),1) -> Ramon Mario | F17: {=INDEX(TUSA!B:B&" "&TUSA!C:C,MATCH($C17,TUSA!$BK:$BK,0),1)} -> Hernandez Lagos | G17: 5227940202760636 | H17: 06/28 | I17: =+VLOOKUP(B17,Tarjetas!$B:$K,9,FALSE()) -> 919 | J17: Miercoles 12:33 | K17: RYKNNI | L17: 2850 | M17: 376 | N17: =+Table4[[#This Row],[Costo]]+Table4[[#This Row],[Costo por cambio]] -> 3226 | O17: CAMBIO HECHO | P17: =+VLOOKUP(Table4[[#This Row],[Matricula]],OTS!A:C,3,FALSE) -> OT-5081179
B18: =INDEX(TUSA!$A:$A,MATCH($C18,TUSA!$BK:$BK,0),1) -> 2262 | C18: Javier Islas Valdez | D18: =INDEX(TUSA!F:$F,MATCH($C18,TUSA!$BK:$BK,0),1) -> 30892 | E18: =INDEX(TUSA!D:D,MATCH($C18,TUSA!$BK:$BK,0),1) -> Javier | F18: {=INDEX(TUSA!B:B&" "&TUSA!C:C,MATCH($C18,TUSA!$BK:$BK,0),1)} -> Islas Valdez | G18: D7156G0KGZES | H18: =+VLOOKUP(B18,Tarjetas!$B:$K,10,FALSE()) -> 45836 | I18: =+VLOOKUP(B18,Tarjetas!$B:$K,9,FALSE()) -> 578 | J18: Miercoles 12:33 | K18: OBMZ4C | L18: 2609 | M18: 440 | N18: =+Table4[[#This Row],[Costo]]+Table4[[#This Row],[Costo por cambio]] -> 3049 | O18: CAMBIO HECHO facturado | P18: =+VLOOKUP(Table4[[#This Row],[Matricula]],OTS!A:C,3,FALSE) -> OT-5081173
B19: =INDEX(TUSA!$A:$A,MATCH($C19,TUSA!$BK:$BK,0),1) -> 1990 | C19: Luis Lazcano Cuatepotzo | D19: =INDEX(TUSA!F:$F,MATCH($C19,TUSA!$BK:$BK,0),1) -> 30906 | E19: =INDEX(TUSA!D:D,MATCH($C19,TUSA!$BK:$BK,0),1) -> Luis | F19: {=INDEX(TUSA!B:B&" "&TUSA!C:C,MATCH($C19,TUSA!$BK:$BK,0),1)} -> Lazcano Cuatepotzo | G19: D7156G0KGZF9 | H19: =+VLOOKUP(B19,Tarjetas!$B:$K,10,FALSE()) -> 45836 | I19: =+VLOOKUP(B19,Tarjetas!$B:$K,9,FALSE()) -> 817 | J19: Miercoles 12:33 | K19: OBMZ4C | L19: 2609 | M19: 440 | N19: =+Table4[[#This Row],[Costo]]+Table4[[#This Row],[Costo por cambio]] -> 3049 | O19: CAMBIO HECHO facturado | P19: =+VLOOKUP(Table4[[#This Row],[Matricula]],OTS!A:C,3,FALSE) -> OT-5081175
C28: Lopez Vertis | D28: RY2CKY
C29: Lopez Romero | D29: LYVRFF
C30: Hernandez Abundiz | D30: BGL7NQ
C31: Fuentes Sibaja | D31: A933TY
C33: Moreno Lopez | D33: P9D7JL
C34: Brindis Juarez | D34: P9D7JL
C36: Carmona Rocha | D36: FDJC2J
C37: Vazquez Tlapalamatl | D37: VKGYPX
C38: Uribe Quintero | D38: MK5HGH
C39: Uribe Quintero | D39: ZJ6KWA
C40: Perez Martinez | D40: F8MCJL
C41: Cuellar Campos | D41: XL33NH
... C44: Lazcano Cuatepotzo | D44: OBMZ4C

Sheet Tarjetas
A1: id_control_tags_Up | B1: id_matricula | C1: Operador | D1: Dispositivo | E1: Fecha_alta | F1: Observaciones | G1: Usuario | H1: NIP | I1: IUT | J1: Num_Confidencial | K1: Num_Vigencia
A2: 1109 | B2: 216 | C2: Javier Carpio Segundo | D2: 5227940202047110 | E2: 45145 | F2: No-cargado | G2: Karina | H2: 6125 | I2: D0154G0IKBFA | J2: 313 | K2: 45684
A3: 1669 | B3: 283 | C3: Victorino Dominguez Olvera | D3: 5227940203167600 | E3: 45888 | F3: No-cargado | G3: AnahiL | H3: 1323 | I3: D1156G0LFGC8 | J3: 218 | K3: 47150
A4: 813 | B4: 352 | C4: Andres Hernandez Sanchez | D4: 5227940200393580 | E4: 44418 | F4: No-cargado | G4: Ariadna | H4: 3954 | I4: D3159G0FX4VH | J4: 653 | K4: 45773
A5: 1587 | B5: 623 | C5: Oswaldo Padilla Oropeza | D5: 5227940202997990 | E5: 45853 | F5: No-cargado | G5: AnahiL | H5: 4840 | I5: D9159G0L61OR | J5: 666 | K5: 46019
A6: 1492 | B6: 912 | C6: Ramon Mario Hernandez Lagos | D6: 5227940202760630 | E6: 45692 | F6: No-cargado | G6: AntonioL | H6: 5121 | I6: D7156G0KGZFE | J6: 919 | K6: 45836
A7: 1672 | B7: 1818 | C7: Leonardo Moreno Lopez | D7: 5227940203167630 | E7: 45891 | F7: No-cargado | G7: AnahiL | H7: 2761 | I7: D1156G0LFGCB | J7: 608 | K7: 47150
A8: 1562 | B8: 1867 | C8: Jose Juan Olvera Marquez | D8: 5227940202759970 | E8: 45700 | F8: No-cargado | G8: AntonioL | H8: 2464 | I8: D7155G0KGZDK | J8: 514 | K8: 45836
A9: 818 | B9: 1902 | C9: Luis Jesus Cortez Lopez | D9: 5227940200393530 | E9: 44419 | G9: Antonio | H9: 83087 | I9: D3159G0FX4VC | J9: 478 | K9: 45773
A10: 1569 | B10: 1982 | C10: Humberto Daniel Salazar Arguello | D10: 5227940202997810 | E10: 45776 | F10: No-cargado | G10: Ariadna | H10: 490 | I10: D9159G0L61O9 | J10: 673 | K10: 46019
A11: 1446 | B11: 1990 | C11: Luis Lazcano Cuatepotzo | D11: D7156G0KGZF9 | E11: 45577 | F11: No-cargado | G11: AnaJM | H11: 5544 | I11: D7156G0KGZF9 | J11: 817 | K11: 45836
A12: 961 | B12: 2039 | C12: Adrian Rodrigo Salazar Gutierrez | D12: 5227940200603850 | E12: 44795 | F12: No-cargado | G12: Antonio | H12: 6544 | I12: D6150G0G7R2P | J12: 856 | K12: 45834
A13: 1002 | B13: 2045 | C13: Ariel Ines Simbron Avila | D13: 5227940201705110 | E13: 44956 | F13: No-cargado | G13: Ariadna | H13: 917 | I13: D7150G0HORTZ | J13: 587 | K13: 45803
A14: 1571 | B14: 2050 | C14: Jose Armando Ochoa Gonzalez | D14: 5227940202997830 | E14: 45792 | F14: No-cargado | G14: AntonioL | H14: 3659 | I14: D9159G0L61OB | J14: 998 | K14: 46019
A15: 1203 | B15: 2077 | C15: Alberto Trujillo Luna | D15: 5227940202193200 | E15: 45336 | G15: Antonio | H15: 472 | I15: D1159G0IW879 | J15: 364 | K15: 45774
A16: 1014 | B16: 2083 | C16: Jose Guadalupe Escamilla Carbajal | D16: 5227940201705230 | E16: 44838 | F16: No-cargado | G16: Ariadna | H16: 9255 | I16: D7150G0HORUB | J16: 130 | K16: 45803
A17: 1381 | B17: 2105 | C17: Gabriel Flores Garrido | D17: 5227940202714100 | E17: 45664 | F17: No-cargado | G17: AnaJM | H17: 69 | I17: D7151G0KAKZO | J17: 261 | K17: 45805
A18: 1570 | B18: 2125 | C18: German Santos Lozano Lopez | D18: 5227940202997820 | E18: 45786 | F18: No-cargado | G18: AntonioL | H18: 2200 | I18: D9159G0L61OA | J18: 659 | K18: 46019
A19: 1553 | B19: 2133 | C19: Martin Cuellar Campos | D19: 5227940202759940 | E19: 45719 | F19: No-cargado | G19: AntonioL | H19: 6233 | I19: D7155G0KGZDH | J19: 538 | K19: 45836
A20: 1148 | B20: 2139 | C20: Waldo Amhed Dominguez Lopez | D20: 5227940202047570 | E20: 45044 | F20: No-cargado | G20: Vanessa | H20: 8610 | I20: D0154G0IKBGK | J20: 964 | K20: 45684
A21: 1462 | B21: 2151 | C21: Hugo Ramirez Linares | D21: D7156G0KGZEG | E21: 45699 | F21: No-cargado | G21: TaniaTC | H21: 5506 | I21: D7156G0KGZEG | J21: 400 | K21: 45836
A22: 1547 | B22: 2162 | C22: Jorge Brindis Juarez | D22: 5227940202760600 | E22: 45734 | F22: No-cargado | G22: Ariadna | H22: 7474 | I22: D7156G0KGZFB | J22: 923 | K22: 45836
A23: 1123 | B23: 2170 | C23: Luis Daniel Monroy Garduño | D23: 5227940202047250 | E23: 45100 | F23: No-cargado | G23: Karina | H23: 5137 | I23: D0154G0IKBFO | J23: 643 | K23: 45684
A24: 1103 | B24: 2172 | C24: Luis Alfonso Hernandez Huerta | D24: 5227940202047050 | E24: 45107 | F24: No-cargado | G24: Karina | H24: 5326 | I24: D0154G0IKBF4 | J24: 952 | K24: 45684
A25: 1116 | B25: 2176 | C25: Edwin Ruben Silva Rodriguez | D25: 5227940202047180 | E25: 45421 | F25: No-cargado | G25: Patricia | H25: 8503 | I25: D0154G0IKBFH | J25: 90 | K25: 45684
A26: 1146 | B26: 2184 | C26: Edgar Jesus Franco Gonzalez | D26: 5227940202047030 | E26: 45155 | F26: No-cargado | G26: Antonio | H26: 2443 | I26: D0154G0IKBF2 | J26: 619 | K26: 45684
A27: 1394 | B27: 2195 | C27: Aurelio Jaime Perez Martinez | D27: 5227940202714230 | E27: 45456 | F27: No-cargado | G27: Patricia | H27: 1839 | I27: D7151G0KAL01 | J27: 124 | K27: 45805
... A29: 1210 | B29: 2206 | C29: Rafael Vargas Garcia | D29: 5227940202193110 | E29: 45202 | F29: No-cargado | G29: AnahiM | H29: 5523 | I29: D1159G0IW870 | J29: 221 | K29: 45774
A30: 1145 | B30: 2209 | C30: Jose Rafael Ontiveros Osnaya | D30: 5227940202047020 | E30: 45217 | G30: Antonio | H30: 2353 | I30: D0154G0IKBF1 | J30: 187 | K30: 45684
A31: 1214 | B31: 2210 | C31: Julio Cesar Islas Alcantara | D31: 5227940202193070 | E31: 45222 | F31: No-cargado | G31: Patricia | H31: 0 | I31: D1159G0IW86W
A32: 1218 | B32: 2211 | C32: Jonathan Uribe Quintero | D32: 5227940202193030 | E32: 45251 | G32: Patricia | H32: 6070 | I32: D1159G0IW86S | J32: 454 | K32: 45774
A33: 1664 | B33: 2214 | C33: Adolfo Julio Cesar Romero Garcia | D33: 5227940203167550 | E33: 45874 | F33: No-cargado | G33: AnahiL | H33: 6204 | I33: D1156G0LFGC3 | J33: 107 | K33: 47150
A34: 1273 | B34: 2218 | C34: Luis Uribe Quintero | D34: 5227940202193630 | E34: 45286 | F34: No-cargado | G34: Patricia | H34: 1076 | I34: D1159G0IW88G | J34: 769 | K34: 45774
A35: 1561 | B35: 2219 | C35: Francisco Gabriel Lopez Vertis | D35: 5227940202759980 | E35: 45703 | F35: No-cargado | G35: AntonioL | H35: 941 | I35: D7155G0KGZDL | J35: 463 | K35: 45836
A36: 1470 | B36: 2225 | C36: Efren Gustavo Pineda Avila | D36: 5227940202760200 | E36: 45636 | F36: No-cargado | G36: AnaJM | H36: 3820 | I36: D7156G0KGZE7 | J36: 741 | K36: 45836
A37: 1282 | B37: 2228 | C37: Efrain Juncal Sosa | D37: 5227940202193540 | E37: 45359 | F37: No-cargado | G37: Patricia | H37: 7513 | I37: D1159G0IW887 | J37: 565 | K37: 45774
A38: 1284 | B38: 2230 | C38: Javier Peralta Ortiz | D38: 5227940202193520 | E38: 45328 | F38: No-cargado | G38: Patricia | H38: 69 | I38: D1159G0IW885 | J38: 643 | K38: 45774
A39: 1294 | B39: 2240 | C39: Marcos Hernandez Flores | D39: 5227940202193890 | E39: 45359 | F39: No-cargado | G39: Patricia | H39: 5243 | I39: D1159G0IW896 | J39: 61 | K39: 45774
A40: 1297 | B40: 2244 | C40: Oscar Romo Jimenez | D40: 5227940202193860 | E40: 45370 | F40: No-cargado | G40: Patricia | H40: 5532 | I40: D1159G0IW893 | J40: 432 | K40: 45774
A41: 1356 | B41: 2254 | C41: David Juarez Juarez | D41: 5227940202193910 | E41: 45415 | F41: No-cargado | G41: Patricia | H41: 1619 | I41: D1159G0IW898 | J41: 945 | K41: 45774
A42: 1390 | B42: 2260 | C42: Jesus Manuel Villalpa Islas | D42: 5227940202714190 | E42: 45477 | F42: No-cargado | G42: Ariadna | H42: 1653 | I42: D7151G0KAKZX | J42: 13 | K42: 45805
A43: 1450 | B43: 2262 | C43: Javier Islas Valdez | D43: D7156G0KGZES | E43: 45616 | F43: No-cargado | G43: TaniaTC | H43: 4220 | I43: D7156G0KGZES | J43: 578 | K43: 45836
A44: 1375 | B44: 2266 | C44: Jose Ruben Hernandez Ruiz | D44: 5227940202714440 | E44: 45436 | F44: No-cargado | G44: DenniMV | H44: 3537 | I44: D7151G0KAL0M | J44: 149 | K44: 45805
... A84: 1671 | B84: 2390 | C84: Wilibaldo Hernandez Angeles | D84: 5227940203167620 | E84: 45891 | F84: No-cargado | G84: AnahiL | H84: 6494 | I84: D1156G0LFGCA | J84: 677 | K84: 47150

Sheet sheet1
A1: ID_matricula | B1: Ap_paterno | C1: Ap_materno | D1: Nombres | E1: Fecha_nacimto | F1: Lugar_nacimto | G1: Reg_fed_causantes | H1: Direccion | I1: Colonia | J1: Ciudad | K1: Estado | L1: Codigo_postal | M1: Pais | N1: Titulo | O1: Estado_estudios | P1: Cedula_profesional | Q1: Puesto | R1: Actividad | S1: Area | T1: Telefono | U1: ID_no_poliza | V1: No_cartilla | W1: Fecha_ingreso_poliza | X1: No_IMSS | Y1: Nacionalidad | Z1: No_CURP | AA1: ID_empleado | AB1: Contrato_eventual | AC1: Fecha_ingreso | AD1: Fecha_alta_IMSS | AE1: Fecha_planta | AF1: Fecha_de_baja | AG1: Sexo | AH1: Estado_civil | AI1: Pension_alimenticia | AJ1: No_oficio | AK1: Disp_para_viajar | AL1: Disp_cambio_residencia | AM1: Observaciones | AN1: Habilidades_especificas | AO1: Areas_de_experiencia | AP1: Areas_de_interes | AQ1: Correo_electronico | AR1: Fecha_baja_IMSS | AS1: No_credito_infonavit | AT1: No_credito_fonacot | AU1: No_cta_bancaria | AV1: Institucion_bancaria | AW1: Camisa | AX1: Pantalon | AY1: Zapatos | AZ1: Chamarra | BA1: ID_empresa | BB1: Sueldo_promedio | BC1: No_bimestre | BD1: Contacto | BE1: No_celular | BF1: Fecha_captura | BG1: Movto | BH1: Tarjeta_combustible | BI1: No_celular2 | BJ1: No_cred_elector | BK1: Folio_cred_elector | BL1: Observaciones2 | BM1: TiempoRastreo | BN1: tel | BO1: Id_Escolaridad | BP1: Tipo_Nomina | BQ1: Playera | BR1: Rueda_5 | BS1: Telefono2 | BT1: Mpio_nac | BU1: FechaCursoOrganizacion | BV1: FechaCemex | BW1: Login_app | BX1: Referido_por | BY1: OpLocal | BZ1: Tipo_sangre | CA1: No_Domicilio | CB1: Entre_calle1 | CC1: Entre_calle2 | CD1: Nombre
A2: 1760 | B2: Sanchez | C2: Garcia | D2: Ricardo | E2: 33743 | F2: Hidalgo | G2: SAGR920519F27 | H2: Jose Maria Pino Suarez 11 | I2: Jose Maria Pino Suarez | J2: Tepeapulco | K2: Hidalgo | L2: 43992 | M2: México | O2: TRUE | Q2: O | S2: Operativo | T2: 6677979058 | U2: 004-0000384386-00 | W2: 43890 | X2: 1312923737-9 | Y2: Mexicana | Z2: SAGR920519HHGNRC00 | AA2: 1 | AB2: TRUE | AC2: 43878 | AD2: 43878 | AF2: 44583 | AG2: M | AH2: U | AI2: FALSE | AK2: TRUE | AL2: TRUE | AN2: Manejo | AO2: Manejo de unidades torton, rabon y tractocamion | AP2: Manejo | AQ2: r.1760tusa@gmail.com | AR2: 44583 | AU2: 5256783255765290 | AV2: Banamex | AW2: 0 | AX2: 0 | AY2: 0.0 | BA2: 0 | BB2: 393.89 | BC2: 1 | BD2: FALSE | BE2: 7712405453 | BF2: 44585 | BG2: M | BJ2: 1942925497 | BK2: 1193087866327 | BM2: 10 | BO2: 2 | BP2: N | BR2: FALSE | BS2: 7752057898 | BT2: Tepeapulco | BW2: FALSE | BY2: FALSE | CD2: =+Table1[[#This Row],[Nombres]]&" "&Table1[[#This Row],[Ap_paterno]]&" "&Table1[[#This Row],[Ap_materno]] -> Ricardo Sanchez Garcia
A3: 1762 | B3: Lazcano | C3: Valencia | D3: Jessica | E3: 32997 | F3: Hidalgo | G3: LAVJ900504UZ5 | H3: Cda. Emiliano Zapata Nte SN | I3: Centro | J3: Tlanalapa | K3: Hidalgo | L3: 43930 | M3: México | N3: Licenciatura en contaduría | O3: TRUE | Q3: A | S3: Administrativo | T3: 7751537242 | U3: 53603-01 12322474 | W3: 44829 | X3: 0220905655-1 | Y3: Mexicana | Z3: LAVJ900504MHGZLS06 | AA3: 2 | AB3: TRUE | AC3: 43899 | AD3: 43899 | AE3: 45292 | AG3: F | AH3: S | AI3: FALSE | AK3: TRUE | AL3: FALSE | AN3: Contabilidad | AO3: Contabilidad general | AP3: Impuestos | AQ3: j.1762tusa@gmail.com | AU3: 5256783282383893 | AV3: Banamex | AW3: 34 | AX3: 0 | AY3: 0 | AZ3: 34 | BA3: 0 | BB3: 613.31 | BC3: 0 | BD3: FALSE | BE3: 7711896851 | BF3: 44110 | BG3: M | BJ3: 1898342092 | BK3: 1395082418806 | BM3: 10 | BN3: 7751531778 | BO3: 5 | BP3: N | BQ3: M | BR3: FALSE | BS3: 7751490555 | BT3: Tepeapulco | BW3: FALSE | BY3: FALSE | CD3: =+Table1[[#This Row],[Nombres]]&" "&Table1[[#This Row],[Ap_paterno]]&" "&Table1[[#This Row],[Ap_materno]] -> Jessica Lazcano Valencia
A4: 1764 | B4: Castro | C4: Islas | D4: Juan Carlos | E4: 31690 | F4: Hidalgo | G4: CAIJ8610059E3 | H4: Atitalaquia No. 749 | I4: Rojo Gomez | J4: Sahagun | K4: Hidalgo | L4: 43996 | M4: Mexico | N4: Ingeniería en Sistemas Computacionales | O4: TRUE | Q4: A | S4: Administrativo | U4: 0000505-0000001 | X4: 13128603050 | Y4: Mexicana | Z4: CAIJ861005HHGSSN03 | AA4: 2 | AB4: TRUE | AC4: 43913 | AD4: 43913 | AF4: 43974 | AG4: M | AH4: U | AI4: FALSE | AK4: FALSE | AL4: FALSE | AN4: Desarrollo de software | AO4: Desarrollo en Sistemas | AQ4: juan.castro@trasladosuniversales.com.mx | AR4: 43974 | AU4: 5256783056131098 | AV4: Banamex | AW4: 0 | AX4: 0 | AY4: 0.0 | BA4: 0 | BB4: 424.78 | BC4: 0 | BD4: FALSE | BF4: 44047 | BG4: M | BJ4: 1219099464368 | BK4: 1147525511 | BM4: 10 | BO4: 5 | BP4: N | BR4: FALSE | BT4: Tepeapulco | BW4: FALSE | BY4: FALSE | CD4: =+Table1[[#This Row],[Nombres]]&" "&Table1[[#This Row],[Ap_paterno]]&" "&Table1[[#This Row],[Ap_materno]] -> Juan Carlos Castro Islas
A5: 1905 | B5: Lozada | C5: Martinez | D5: Marco Antonio | E5: 32347 | F5: Puebla | G5: LOMM8807238G7 | H5: Calle Miguel Hidalgo | I5: El Paredon | J5: El Paredon | K5: Puebla | L5: 73302 | M5: Mexico | O5: TRUE | Q5: O | S5: Operativo | T5: 7751558502 | X5: 0220883833-0 | Y5: Mexicana | Z5: LOMM880723HPLZRR05 | AA5: 1 | AB5: TRUE | AC5: 44392 | AD5: 44392 | AF5: 44487 | AG5: M | AH5: U | AI5: FALSE | AK5: TRUE | AL5: FALSE | AQ5: m.1905tusa@gmail.com | AR5: 44487 | AU5: 5256783585532196 | AV5: Banamex | AW5: 36 | AX5: 32 | AY5: 26.0 | AZ5: G | BA5: 0 | BB5: 206.49 | BC5: 0 | BD5: FALSE | BF5: 44488 | BG5: M | BJ5: 0484076270539 | BM5: 10 | BO5: 2 | BP5: N | BQ5: G | BR5: FALSE | BS5: 7751393525 | BT5: Chignahuapan | BW5: FALSE | BY5: FALSE | CD5: =+Table1[[#This Row],[Nombres]]&" "&Table1[[#This Row],[Ap_paterno]]&" "&Table1[[#This Row],[Ap_materno]] -> Marco Antonio Lozada Martinez
A6: 1899 | B6: Aguilera | C6: Hernandez | D6: Hipolito | E6: 24557 | F6: Nuevo León | G6: AUHH670326G84 | H6: Montes Dolomiticos | I6: Las Puentes | J6: San Nicolas de los Garza | K6: Monterrey | L6: 66460 | M6: Mexico | O6: TRUE | Q6: A | S6: Administrativo | T6: 8127553322 | X6: 4385678683-5 | Y6: Mexicana | Z6: AUHH670326HNLGRP01 | AA6: 2 | AB6: FALSE | AC6: 44382 | AD6: 44382 | AF6: 44782 | AG6: M | AH6: C | AI6: FALSE | AK6: FALSE | AL6: FALSE | AQ6: h.1899tusa@gmail.com | AU6: 5256783290819094 | AV6: Banamex | AW6: 42 | AX6: 38 | AY6: 28.0 | AZ6: XG | BA6: 0 | BB6: 403.95 | BC6: 0 | BD6: FALSE | BF6: 44789 | BG6: M | BJ6: 1817048222282 | BM6: 10 | BO6: 1 | BP6: N | BQ6: XG | BR6: FALSE | BS6: 8126583512 | BT6: Garcia | BW6: FALSE | BY6: FALSE | CD6: =+Table1[[#This Row],[Nombres]]&" "&Table1[[#This Row],[Ap_paterno]]&" "&Table1[[#This Row],[Ap_materno]] -> Hipolito Aguilera Hernandez
A7: 1766 | B7: Vivar | C7: Ramirez | D7: Marco Antonio | E7: 35691 | F7: México | G7: VIRM9709188S4 | H7: Achali Int A Mz 1, Lt 19 | I7: Artesanos | J7: Chimalhuacan | K7: México | L7: 56334 | M7: México | O7: FALSE | Q7: O | S7: Operativo | U7: 0000505-0000001 | X7: 1715977841-8 | Y7: Mexicana | Z7: VIRM970918HMCVMR08 | AA7: 1 | AB7: TRUE | AC7: 43948 | AD7: 43948 | AF7: 44022 | AG7: M | AH7: U | AI7: FALSE | AK7: TRUE | AL7: FALSE | AN7: Manejo | AO7: Rabon, torton | AP7: Manejo | AQ7: marco1997fde@gmail.com | AR7: 44022 | AU7: 5256783303422092 | AV7: Banamex | AW7: 0 | AX7: 0 | AY7: 0.0 | BA7: 0 | BB7: 247.99 | BC7: 0 | BD7: FALSE | BF7: 44100 | BG7: M | BJ7: 1953716026 | BK7: 1175104378486 | BM7: 10 | BO7: 1 | BP7: N | BR7: FALSE | BT7: Nezahualcoyotl | BW7: FALSE | BY7: FALSE | CD7: =+Table1[[#This Row],[Nombres]]&" "&Table1[[#This Row],[Ap_paterno]]&" "&Table1[[#This Row],[Ap_materno]] -> Marco Antonio Vivar Ramirez
A8: 1769 | B8: Rodriguez | C8: Gonzalez | D8: Daniel Israel | E8: 28244 | F8: Nuevo León | G8: ROGD770429G11 | H8: San Ignacio #211 | I8: Valle del Jarcel | J8: Monterrey | K8: Nuevo Leon | L8: 64000 | M8: Mexico | O8: TRUE | Q8: A | S8: Administrativo | T8: 8132482286 | U8: 0000505-0000001 | X8: 4394777648-0 | Y8: Mexicana | Z8: ROGD770429HNLDNN07 | AA8: 3 | AB8: TRUE | AC8: 43976 | AD8: 43976 | AF8: 44025 | AG8: M | AH8: C | AI8: FALSE | AK8: FALSE | AL8: FALSE | AN8: Vigilancia | AO8: Vigilancia | AP8: Vigilancia | AQ8: rodriguezgonzalezd77@gmail.com | AR8: 44025 | AU8: 5256783197081897 | AV8: Banamex | AW8: 0 | AX8: 32 | AY8: 0.0 | BA8: 0 | BB8: 242 | BC8: 0 | BD8: TRUE | BF8: 44028 | BG8: M | BJ8: 0441098727937 | BK8: 1658881762 | BM8: 10 | BO8: 2 | BP8: N | BR8: FALSE | BT8: Monterrey | BW8: FALSE | BY8: FALSE | CD8: =+Table1[[#This Row],[Nombres]]&" "&Table1[[#This Row],[Ap_paterno]]&" "&Table1[[#This Row],[Ap_materno]] -> Daniel Israel Rodriguez Gonzalez
A9: 1770 | B9: Cañas | C9: Hernandez | D9: Marco Antonio | E9: 32691 | F9: Chiapas | G9: CAHM890702D24 | H9: Primera Ave. 321 | I9: Satelite del Norte | J9: Monterrey | K9: Nuevo Leon | L9: 64000 | M9: México | O9: TRUE | Q9: A | S9: Administrativo | U9: 53603-01 14508255 | W9: 44829 | X9: 0518890860-1 | Y9: Mexicana | Z9: CAHM890702HCSXRR08 | AA9: 2 | AB9: TRUE | AC9: 43976 | AD9: 43976 | AG9: M | AH9: C | AI9: FALSE | AK9: FALSE | AL9: FALSE | AN9: Vigilancia | AO9: Vigilancia | AP9: Vigilancia | AQ9: canasmarco97@gmail.com | AU9: 5256784082658393 | AV9: Banamex | AW9: 36 | AX9: 36 | AY9: 6 | AZ9: 36 | BA9: 0 | BB9: 517.98 | BC9: 0 | BD9: TRUE | BF9: 44827 | BG9: M | BJ9: 1760081144961 | BK9: 1962741305 | BM9: 10 | BO9: 3 | BP9: N | BQ9: G | BR9: FALSE | BT9: Chiapa de Corzo | BW9: FALSE | BY9: FALSE | CD9: =+Table1[[#This Row],[Nombres]]&" "&Table1[[#This Row],[Ap_paterno]]&" "&Table1[[#This Row],[Ap_materno]] -> Marco Antonio Cañas Hernandez
A10: 1771 | B10: Mota | C10: Delgadillo | D10: Lorena | E10: 35000 | F10: Puebla | G10: MODL9510288W0 | H10: Granada No 2 | I10: Lomas del pedregal | J10: Apan | K10: Hidalgo | L10: 43917 | M10: México | N10: Ingenieria en Logistica | O10: TRUE | Q10: A | S10: Administrativo | T10: 7751572801 | U10: 0000505-0000001 | W10: 44012 | X10: 1516958884-3 | Y10: Mexicana | Z10: MODL951028MPLTLR09 | AA10: 2 | AB10: TRUE | AC10: 44001 | AD10: 44001 | AF10: 44026 | AG10: F | AH10: S | AI10: FALSE | AK10: TRUE | AL10: FALSE | AN10: Trafico y Rastreo | AO10: Trafico, Rastreo, servicio al cliente | AP10: Trafico | AQ10: lore28.il10@gmail.com | AR10: 44026 | AU10: 5256783340091298 | AV10: Banamex | AW10: CH | AX10: 0 | AY10: 0.0 | BA10: 0 | BB10: 445.24 | BC10: 3 | BD10: FALSE | BF10: 44048 | BG10: M | BJ10: 1892883214 | BK10: 0143096437935 | BM10: 10 | BO10: 5 | BP10: N | BR10: FALSE | BT10: Chignahuapan | BW10: FALSE | BY10: FALSE | CD10: =+Table1[[#This Row],[Nombres]]&" "&Table1[[#This Row],[Ap_paterno]]&" "&Table1[[#This Row],[Ap_materno]] -> Lorena Mota Delgadillo
A11: 1909 | B11: Hernandez | C11: Gomez | D11: Jose | E11: 25678 | F11: Hidalgo | G11: HEGJ700420MR5 | H11: Pachuca | I11: Pueblo Nuevo Barrio | J11: Pachuca de Soto | K11: Hidalgo | L11: 42181 | M11: Mexico | O11: TRUE | Q11: O | S11: Operativo | T11: 7711257753 | X11: 2089705298-9 | Y11: Mexicana | Z11: HEGJ700420HHGRMS07 | AA11: 1 | AB11: TRUE | AC11: 44392 | AD11: 44392 | AF11: 44504 | AG11: M | AH11: C | AI11: FALSE | AK11: TRUE | AL11: FALSE | AQ11: j.1909tusa@gmail.com | AR11: 44504 | AU11: 5256783591282893 | AV11: Banamex | AW11: 40 | AX11: 38 | AY11: 27.0 | AZ11: G | BA11: 0 | BB11: 545.07 | BC11: 0 | BD11: FALSE | BE11: 8112442233 | BF11: 44519 | BG11: M | BJ11: 0727008169396 | BM11: 10 | BO11: 2 | BP11: N | BQ11: XG | BR11: FALSE | BS11: 7712936258 | BT11: Huejutla de Reyes | BW11: FALSE | BY11: FALSE | CD11: =+Table1[[#This Row],[Nombres]]&" "&Table1[[#This Row],[Ap_paterno]]&" "&Table1[[#This Row],[Ap_materno]] -> Jose Hernandez Gomez
A12: 1767 | B12: Moreno | C12: Perez | D12: Aldo Alexis BAJA | E12: 34465 | F12: Tlaxcala | G12: MOPA940511CY2 | H12: Apizaco SN | I12: San Miguel Xolco | J12: Otumba | K12: México | L12: 55900 | M12: México | O12: TRUE | Q12: O | S12: Operativo | X12: 9413948592-7 | Y12: Mexicana | Z12: MOPA940511HTLRRL04 | AA12: 1 | AB12: TRUE | AC12: 43948 | AD12: 43948 | AF12: 43950 | AG12: M | AH12: U | AI12: FALSE | AK12: FALSE | AL12: FALSE | AR12: 43950 | AU12: 5256783292521599 | AV12: Banamex | AW12: 0 | AX12: 0 | AY12: 0.0 | BA12: 0 | BB12: 130.48 | BC12: 0 | BD12: FALSE | BF12: 44264 | BG12: M | BJ12: 3891132358263 | BK12: 1315052100107 | BM12: 10 | BO12: 3 | BP12: N | BR12: FALSE | BT12: Calpulalpan | BW12: FALSE | BY12: FALSE | CD12: =+Table1[[#This Row],[Nombres]]&" "&Table1[[#This Row],[Ap_paterno]]&" "&Table1[[#This Row],[Ap_materno]] -> Aldo Alexis BAJA Moreno Perez
A13: 1773 | B13: Espejel | C13: Alonso | D13: Emigdio | E13: 26959 | F13: Tlaxcala | G13: EEAE731022DU1 | H13: Av. Netzahualcoyotl Sur No 6 | I13: El Mirador | J13: Calpulalpan | K13: Tlaxcala | L13: 90204 | M13: México | O13: TRUE | Q13: O | S13: Operativo | T13: 7491010492 | U13: 12322506 | W13: 44829 | X13: 6191731192-2 | Y13: Mexicana | Z13: EEAE731022HTLSLM06 | AA13: 1 | AB13: TRUE | AC13: 44005 | AD13: 44005 | AF13: 45428 | AG13: M | AH13: U | AI13: FALSE | AK13: FALSE | AL13: FALSE | AM13: Marisol Aguirre Conyuge 2411101703 Luis Espejel Hno 5531503931 Monserrat Espejel hija 7491142177 | AN13: Manejo | AO13: Tractocamion | AP13: Manejo | AQ13: espejelalonsoemigdio@gmail.com | AU13: 5256784052415998 | AV13: Banamex | AW13: 44 | AX13: 38 | AY13: 26.0 | AZ13: 0 | BA13: 0 | BB13: 345.97 | BC13: 3 | BD13: FALSE | BF13: 45593 | BG13: M | BJ13: 1571339469 | BK13: 0088014061996 | BM13: 10 | BO13: 2 | BP13: N | BQ13: CH | BR13: TRUE | BS13: 74911142177 | BT13: Calpulalpan | BU13: 44852 | BV13: 45410 | BW13: FALSE | BY13: FALSE | CD13: =+Table1[[#This Row],[Nombres]]&" "&Table1[[#This Row],[Ap_paterno]]&" "&Table1[[#This Row],[Ap_materno]] -> Emigdio Espejel Alonso
A14: 1772 | B14: Barrios | C14: Gonzalez | D14: Gerardo | E14: 27296 | F14: Puebla | G14: BAGG740924244 | H14: Luis Donaldo Colosio 4 | I14: San Juan | J14: Huauchinango | K14: Puebla | L14: 73160 | M14: Mexico | O14: TRUE | Q14: O | S14: Operativo | U14: 004-0000384386-00 | X14: 0316740149-0 | Y14: Mexicana | Z14: BAGG740924HPLRNR01 | AA14: 1 | AB14: TRUE | AC14: 44005 | AD14: 44005 | AF14: 44280 | AG14: M | AH14: C | AI14: FALSE | AK14: TRUE | AL14: FALSE | AN14: Manejo | AO14: Manejo | AP14: Manejo | AQ14: gerabarrios995@gmail.com | AR14: 44280 | AU14: 5579070119195256 | AV14: Banamex | AW14: 0 | AX14: 0 | AY14: 0.0 | BA14: 0 | BB14: 308.3 | BC14: 3 | BD14: TRUE | BE14: 7711278215 | BF14: 44284 | BG14: M | BJ14: 0605056916281 | BK14: 1877236260 | BM14: 10 | BO14: 1 | BP14: N | BR14: FALSE | BT14: Puebla | BW14: FALSE | BY14: FALSE | CD14: =+Table1[[#This Row],[Nombres]]&" "&Table1[[#This Row],[Ap_paterno]]&" "&Table1[[#This Row],[Ap_materno]] -> Gerardo Barrios Gonzalez
A15: 1774 | B15: Romo | C15: Alonso | D15: Abraham | E15: 33226 | F15: Hidalgo | G15: ROAA901219SC7 | H15: Centeno No 117 | I15: Lomas de Nopalapa | J15: Pachuca | K15: Hidalgo | L15: 42186 | M15: México | O15: TRUE | Q15: O | S15: Operativo | T15: 7711850966 | U15: 0000505-0000001 | X15: 1310901967-2 | Y15: Mexicana | Z15: ROAA901219HHGMLB02 | AA15: 1 | AB15: TRUE | AC15: 44005 | AD15: 44005 | AF15: 44022 | AG15: M | AH15: U | AI15: FALSE | AK15: FALSE | AL15: FALSE | AN15: Manejo | AO15: Revolvedoras, tractos | AP15: Manejo | AQ15: romofernando875@gmail.com | AR15: 44022 | AU15: 5256783094097897 | AV15: Banamex | AW15: 0 | AX15: 0 | AY15: 0.0 | BA15: 0 | BB15: 130.48 | BC15: 0 | BD15: FALSE | BF15: 44028 | BG15: M | BJ15: 1813046076 | BK15: 0740084007977 | BM15: 10 | BO15: 2 | BP15: N | BR15: FALSE | BT15: Pachuca de Soto | BW15: FALSE | BY15: FALSE | CD15: =+Table1[[#This Row],[Nombres]]&" "&Table1[[#This Row],[Ap_paterno]]&" "&Table1[[#This Row],[Ap_materno]] -> Abraham Romo Alonso
A16: 1775 | B16: Morales | C16: Hernandez | D16: Juan Jose | E16: 33202 | F16: Veracruz | G16: MOHJ9011254M1 | H16: Independencia No. 2 | I16: Centro | J16: Acajete | K16: Veracruz | L16: 45180 | M16: Mexico | O16: FALSE | Q16: O | S16: Operativo | U16: 0000505-0000001 | X16: 6509902983-0 | Y16: Mexicana | Z16: MOHJ901125HVZRRN01 | AA16: 1 | AB16: TRUE | AC16: 44005 | AD16: 44005 | AF16: 44027 | AG16: M | AH16: U | AI16: FALSE | AK16: TRUE | AL16: FALSE | AN16: Manejar | AO16: Manejar | AP16: Manejar | AQ16: fahrenheit.morales@gmail.com | AR16: 44027 | AU16: 5256783340091199 | AV16: Banamex | AW16: 0 | AX16: 0 | AY16: 0.0 | BA16: 0 | BB16: 130.48 | BC16: 3 | BD16: TRUE | BF16: 44028 | BG16: M | BJ16: 2993083217806 | BK16: 1509943889 | BM16: 10 | BO16: 3 | BP16: N | BR16: FALSE | BT16: Xalapa | BW16: FALSE | BY16: FALSE | CD16: =+Table1[[#This Row],[Nombres]]&" "&Table1[[#This Row],[Ap_paterno]]&" "&Table1[[#This Row],[Ap_materno]] -> Juan Jose Morales Hernandez
A17: 1776 | B17: Arellano | C17: Ramirez | D17: Francisco | E17: 29770 | F17: Puebla | G17: AERF810703L98 | H17: Sonora #16B | I17: La Conchita | J17: Apan | K17: Hidalgo | L17: 43900 | M17: Mexico | O17: TRUE | Q17: O | S17: Operativo | U17: 0000505-0000001 | X17: 7201810717-6 | Y17: Mexicana | Z17: AERF810703HPLRMR04 | AA17: 1 | AB17: TRUE | AC17: 44021 | AD17: 44021 | AF17: 44096 | AG17: M | AH17: C | AI17: FALSE | AK17: FALSE | AL17: FALSE | AN17: Menejo | AO17: Mnejo | AP17: Manejo | AQ17: f.1776tusa@gmail.com | AR17: 44096 | AU17: 5256783273291691 | AV17: Banamex | AW17: 0 | AX17: 0 | AY17: 0.0 | BA17: 0 | BB17: 302.2 | BC17: 3 | BD17: FALSE | BF17: 44102 | BG17: M | BJ17: 0128010273166 | BK17: 1833800191 | BM17: 10 | BO17: 3 | BP17: N | BR17: FALSE | BT17: Puebla | BW17: FALSE | BY17: FALSE | CD17: =+Table1[[#This Row],[Nombres]]&" "&Table1[[#This Row],[Ap_paterno]]&" "&Table1[[#This Row],[Ap_materno]] -> Francisco Arellano Ramirez
A18: 1777 | B18: Santillan | C18: Montes | D18: Evaristo | E18: 28059 | G18: SAME7610267E9 | H18: Simon Bolivar S/N | I18: Barrio los Laureles | J18: Hueypoxtla | K18: México | L18: 55670 | M18: México | O18: FALSE | Q18: O | S18: Operativo | U18: 0000505-0000001 | W18: 44027 | X18: 9499760642-4 | Y18: Mexicana | Z18: SAME761026HMCNNV09 | AA18: 1 | AB18: TRUE | AC18: 44021 | AD18: 44021 | AF18: 44096 | AG18: M | AH18: C | AI18: FALSE | AK18: FALSE | AL18: FALSE | AQ18: e.1777tusa@gmail.com | AR18: 44096 | AU18: 5256783340625491 | AV18: Banamex | AW18: 0 | AX18: 0 | AY18: 0.0 | BA18: 0 | BB18: 280.12 | BC18: 3 | BD18: FALSE | BF18: 44102 | BG18: M | BJ18: 1981047215807 | BK18: 0000065522494 | BM18: 10 | BO18: 2 | BP18: N | BR18: FALSE | BW18: FALSE | BY18: FALSE | CD18: =+Table1[[#This Row],[Nombres]]&" "&Table1[[#This Row],[Ap_paterno]]&" "&Table1[[#This Row],[Ap_materno]] -> Evaristo Santillan Montes
A19: 1778 | B19: Lopantzi | C19: Flores | D19: Brigido | E19: 26580 | F19: Tlaxcala | G19: LOFB721008GD5 | H19: San Jose #22 | I19: Aztatla | J19: Aztatla | K19: Tlaxcala | L19: 90670 | M19: Mexico | O19: TRUE | Q19: O | S19: Operativo | U19: 004-0000384386-00 | X19: 0216720171-0 | Y19: Mexicana | Z19: LOFB721008HTLPLR04 | AA19: 1 | AB19: TRUE | AC19: 44021 | AD19: 44021 | AF19: 44293 | AG19: M | AH19: C | AI19: FALSE | AK19: TRUE | AL19: FALSE | AM19: Numero personal 2461229788 | AN19: Manejo | AO19: Manejo | AP19: Manejo | AQ19: b.1778tusa@gmail.com | AR19: 44293 | AU19: 5256783340109199 | AV19: Banamex | AW19: 0 | AX19: 0 | AY19: 0.0 | BA19: 0 | BB19: 365.07 | BC19: 3 | BD19: FALSE | BE19: 7711895521 | BF19: 44293 | BG19: M | BJ19: 0281010070631 | BK19: 1418242550 | BM19: 10 | BO19: 2 | BP19: N | BR19: FALSE | BT19: Tlaxcala | BW19: FALSE | BY19: FALSE | CD19: =+Table1[[#This Row],[Nombres]]&" "&Table1[[#This Row],[Ap_paterno]]&" "&Table1[[#This Row],[Ap_materno]] -> Brigido Lopantzi Flores
A20: 1780 | B20: Avelar | C20: Sandoval | D20: Pedro | E20: 28637 | F20: México | G20: AESP780527421 | H20: Cda. 2da. de Rosendo Arnaiz 4 | I20: Rosendo Arnaiz | J20: San Martin de las Piramides | K20: Estado de México | L20: 55850 | M20: Mexico | N20: na | O20: TRUE | Q20: O | S20: Operativo | U20: 004-0000384386-00 | X20: 9400780681-6 | Y20: Mexicana | Z20: AESP780527HMCVND05 | AA20: 1 | AB20: TRUE | AC20: 44025 | AD20: 44025 | AF20: 44249 | AG20: M | AH20: U | AI20: FALSE | AK20: TRUE | AL20: FALSE | AN20: Manejar | AO20: Conduccion | AP20: Mecanica | AQ20: avelarpedro53@gmail.com | AR20: 44249 | AU20: 5256783396126196 | AV20: Banamex | AW20: 42 | AX20: 42 | AY20: 0.0 | AZ20: 42 | BA20: 0 | BB20: 320.71 | BC20: 4 | BD20: FALSE | BE20: 7714036618 | BF20: 44250 | BG20: M | BJ20: 4108015579652 | BK20: 1488984361 | BM20: 10 | BO20: 2 | BP20: N | BQ20: XG | BR20: FALSE | BT20: San Martin de las Piramides | BW20: FALSE | BY20: FALSE | CD20: =+Table1[[#This Row],[Nombres]]&" "&Table1[[#This Row],[Ap_paterno]]&" "&Table1[[#This Row],[Ap_materno]] -> Pedro Avelar Sandoval
A21: 1783 | B21: Dominguez | C21: Olvera | D21: Martin | E21: 21580 | F21: Hidalgo | G21: DOOM590130MM9 | H21: Letra O Nº 9 | I21: Abecedario | J21: Sahagun | K21: Hidalgo | L21: 43990 | M21: México | O21: TRUE | Q21: A | S21: Administrativo | T21: 8112445652 | U21: 004-0000384386-00 | X21: 1378590571-5 | Y21: Mexicana | Z21: DOOM590130HHGMLR04 | AA21: 2 | AB21: FALSE | AC21: 44037 | AD21: 44037 | AF21: 44225 | AG21: M | AH21: C | AI21: FALSE | AK21: FALSE | AL21: FALSE | AQ21: martin56dominguezz@gmail.com | AR21: 44225 | AU21: 5256782591837094 | AV21: Banamex | AW21: 0 | AX21: 0 | AY21: 0.0 | BA21: 0 | BB21: 333.29 | BC21: 4 | BD21: FALSE | BE21: 8115387710 | BF21: 44265 | BG21: M | BI21: 7711895511 | BJ21: 1478024644 | BK21: 1211018459541 | BM21: 10 | BO21: 1 | BP21: N | BR21: FALSE | BT21: Tepeapulco | BW21: FALSE | BY21: FALSE | CD21: =+Table1[[#This Row],[Nombres]]&" "&Table1[[#This Row],[Ap_paterno]]&" "&Table1[[#This Row],[Ap_materno]] -> Martin Dominguez Olvera
A22: 1768 | B22: Rosas | C22: Esteban | D22: Martin Eduardo | E22: 32559 | F22: Hidalgo | G22: ROEM890220AF1 | H22: Av. Mexico | I22: Benito Juarez | J22: Sahagun | K22: Hidalgo | L22: 43994 | M22: Mexico | O22: FALSE | Q22: O | S22: Operativo | U22: 0000505-0000001 | X22: 1307893400-0 | Y22: Mexicana | Z22: ROEM890220HHGSSR00 | AA22: 1 | AB22: TRUE | AC22: 43949 | AD22: 43949 | AF22: 44102 | AG22: M | AH22: C | AI22: FALSE | AK22: TRUE | AL22: FALSE | AQ22: m.1768tusa@gmail.com | AR22: 44102 | AU22: 5256782097794997 | AV22: Banamex | AW22: 0 | AX22: 0 | AY22: 0.0 | BA22: 0 | BB22: 311.82 | BC22: 0 | BD22: FALSE | BF22: 44110 | BG22: M | BJ22: 1814780560 | BK22: 1221078045139 | BM22: 10 | BO22: 1 | BP22: N | BR22: FALSE | BT22: Tepeapulco | BW22: FALSE | BY22: FALSE | CD22: =+Table1[[#This Row],[Nombres]]&" "&Table1[[#This Row],[Ap_paterno]]&" "&Table1[[#This Row],[Ap_materno]] -> Martin Eduardo Rosas Esteban
A23: 1779 | B23: Lopez | C23: Islas | D23: Amado | E23: 25208 | F23: México | G23: LOIA690105GH6 | H23: Lirios No 131 | I23: La Rosa | J23: El Susto, Singuilucan | K23: Hidalgo | L23: 43790 | M23: Mexico | O23: TRUE | Q23: O | S23: Operativo | W23: 44027 | X23: 0186691822-8 | Y23: Mexicana | Z23: LOIA690105HDFPSM03 | AA23: 1 | AB23: TRUE | AC23: 44022 | AF23: 44023 | AG23: M | AH23: C | AI23: FALSE | AK23: TRUE | AL23: FALSE | AN23: Manejo | AO23: Manejo | AP23: Manejo | AW23: 0 | AX23: 0 | AY23: 0.0 | BA23: 0 | BB23: 130.48 | BC23: 0 | BD23: FALSE | BF23: 44047 | BG23: M | BJ23: 1123035160674 | BK23: 1479318407 | BM23: 10 | BO23: 1 | BP23: N | BR23: FALSE | BT23: Chapultepec | BW23: FALSE | BY23: FALSE | CD23: =+Table1[[#This Row],[Nombres]]&" "&Table1[[#This Row],[Ap_paterno]]&" "&Table1[[#This Row],[Ap_materno]] -> Amado Lopez Islas
A24: 1785 | B24: Zarate | C24: De Lucio | D24: Agustin | E24: 28638 | F24: Hidalgo | G24: ZALA780528HM8 | H24: Belizario Dominguez No 6 | I24: Jaltepec | J24: Axapusco | K24: México | L24: 55965 | M24: México | O24: TRUE | Q24: O | S24: Operativo | U24: 0000505-0000001 | W24: 44042 | X24: 1396782571-5 | Y24: Mexicana | Z24: ZALA780528HHGRCG00 | AA24: 1 | AB24: TRUE | AC24: 44042 | AD24: 44042 | AF24: 44114 | AG24: M | AH24: C | AI24: FALSE | AK24: FALSE | AL24: FALSE | AQ24: a.1785tus@gmail.com | AR24: 44114 | AU24: 5256783340106492 | AV24: Banamex | AW24: 34 | AX24: 32 | AY24: 0.0 | BA24: 0 | BB24: 171.27 | BC24: 4 | BD24: FALSE | BF24: 44126 | BG24: M | BJ24: 1867915249 | BK24: 0485052700288 | BM24: 10 | BO24: 2 | BP24: N | BQ24: M | BR24: FALSE | BT24: Tepeapulco | BW24: FALSE | BY24: FALSE | CD24: =+Table1[[#This Row],[Nombres]]&" "&Table1[[#This Row],[Ap_paterno]]&" "&Table1[[#This Row],[Ap_materno]] -> Agustin Zarate De Lucio
A25: 1787 | B25: Lopez | C25: Pastrana | D25: Jorge | E25: 29446 | F25: Hidalgo | G25: LOPJ800813CJ5 | H25: Rosendo Flores No 54 | I25: Centro | J25: Emiliano Zapata | K25: Hidalo | L25: 43960 | M25: México | O25: TRUE | Q25: O | S25: Operativo | U25: 0000505-0000001 | W25: 44042 | X25: 1399801646-6 | Y25: Mexicana | Z25: LOPJ800813HHGPSR08 | AA25: 1 | AB25: TRUE | AC25: 44042 | AD25: 44042 | AF25: 44081 | AG25: M | AH25: C | AI25: FALSE | AK25: TRUE | AL25: FALSE | AQ25: j.1787tusa@gmail.com | AR25: 44081 | AU25: 5256782646441496 | AV25: Banamex | AW25: 40 | AX25: 32 | AY25: 0.0 | BA25: 0 | BB25: 208.47 | BC25: 4 | BD25: FALSE | BF25: 44088 | BG25: M | BJ25: 1143369313 | BK25: 0352071577098 | BM25: 10 | BO25: 3 | BP25: N | BQ25: G | BR25: FALSE | BT25: Tepeapulco | BW25: FALSE | BY25: FALSE | CD25: =+Table1[[#This Row],[Nombres]]&" "&Table1[[#This Row],[Ap_paterno]]&" "&Table1[[#This Row],[Ap_materno]] -> Jorge Lopez Pastrana
A26: 1788 | B26: Ortiz | C26: Urbina | D26: Jose Saul | E26: 34927 | F26: Nuevo León | G26: OIUS950816HNLRRL02 | H26: Alvaro Obregon No 324 | I26: La Loma, Zona Centro | J26: Mina | K26: Nuevo Leon | L26: 65100 | M26: México | N26: Tecnico en informatica | O26: FALSE | Q26: A | S26: Administrativo | U26: 0000505-0000001 | W26: 44043 | X26: 4313951591-0 | Y26: Mexicana | Z26: OIUS950816SS3 | AA26: 2 | AB26: TRUE | AC26: 44043 | AD26: 44043 | AF26: 44050 | AG26: M | AH26: C | AI26: FALSE | AK26: FALSE | AL26: FALSE | AO26: Control de patio | AR26: 44050 | AU26: 5256783352741095 | AV26: Banamex | AW26: 0 | AX26: 0 | AY26: 0.0 | BA26: 0 | BB26: 350.14 | BC26: 4 | BD26: FALSE | BF26: 44125 | BG26: M | BJ26: 2408135009391 | BK26: 1319122606533 | BM26: 10 | BO26: 3 | BP26: N | BR26: FALSE | BT26: San Nicolas de los Garza | BW26: FALSE | BY26: FALSE | CD26: =+Table1[[#This Row],[Nombres]]&" "&Table1[[#This Row],[Ap_paterno]]&" "&Table1[[#This Row],[Ap_materno]] -> Jose Saul Ortiz Urbina
A27: 1793 | B27: Beltran | C27: Nolasco | D27: Jose Pedro | E27: 33175 | F27: Hidalgo | G27: BENP901029ND3 | H27: Allende 14B | I27: Santa Barbara | J27: Santa Barbara | K27: Hidalgo | L27: 43961 | M27: México | O27: TRUE | Q27: O | S27: Operativo | T27: 7751892546 | X27: 1310902883-0 | Y27: Mexicana | Z27: BENP901029HHGLLD16 | AA27: 1 | AB27: TRUE | AC27: 44053 | AD27: 44053 | AF27: 44095 | AG27: M | AH27: U | AI27: FALSE | AK27: TRUE | AL27: FALSE | AN27: Manejo | AO27: Manejo | AP27: Manejo | AQ27: pedro291090@gmail.com | AR27: 44095 | AU27: 5256783037004398 | AV27: Banamex | AW27: 32 | AX27: 38 | AY27: 0.0 | BA27: 0 | BB27: 257.58 | BC27: 4 | BD27: FALSE | BF27: 44102 | BG27: M | BJ27: 0357082701881 | BK27: 2012343542 | BM27: 10 | BO27: 2 | BP27: N | BQ27: M | BR27: FALSE | BT27: Apan | BW27: FALSE | BY27: FALSE | CD27: =+Table1[[#This Row],[Nombres]]&" "&Table1[[#This Row],[Ap_paterno]]&" "&Table1[[#This Row],[Ap_materno]] -> Jose Pedro Beltran Nolasco
A28: 1790 | B28: Villalpa | C28: Islas | D28: Jesus Manuel BAJA 2 | E28: 30578 | F28: Hidalgo | G28: VIIJ830919K72 | H28: Calle 1 M24 L29 | I28: Palmillas | J28: Sahagún | K28: Hidalgo | L28: 43998 | M28: México | O28: FALSE | Q28: O | S28: Operativo | T28: 5532051626 | U28: 53 | W28: 44829 | X28: 0217838917-3 | Y28: Mexicana | Z28: VIIJ830919HHGLSS05 | AA28: 1 | AB28: TRUE | AC28: 44053 | AD28: 44053 | AF28: 45124 | AG28: M | AH28: C | AI28: FALSE | AK28: FALSE | AL28: FALSE | AM28: 7713471060 telefono personal | AO28: Autobus, tactos | AQ28: villalpaislasjesus@gmail.com | AR28: 45124 | AU28: 5579100241407798 | AV28: Banamex | AW28: 40 | AX28: 34 | AY28: 0.0 | BA28: 0 | BB28: 396.15 | BC28: 4 | BD28: FALSE | BF28: 45430 | BG28: M | BJ28: 1470200046 | BK28: 1209030916099 | BM28: 10 | BO28: 2 | BP28: N | BR28: TRUE | BS28: 7757068741 | BT28: Tepeapulco | BU28: 44856 | BW28: FALSE | BY28: FALSE | CD28: =+Table1[[#This Row],[Nombres]]&" "&Table1[[#This Row],[Ap_paterno]]&" "&Table1[[#This Row],[Ap_materno]] -> Jesus Manuel BAJA 2 Villalpa Islas
A29: 1791 | B29: Bermudez | C29: Merida | D29: Efrain | E29: 31300 | F29: Hidalgo | G29: BEME850910VC6 | H29: Josefa Ortiz de Dominguez No 16 A | I29: Irolo | J29: Irolo | K29: Hidalgo | L29: 43991 | M29: México | O29: TRUE | Q29: O | S29: Operativo | T29: 7919136203 | W29: 44058 | X29: 1302850426-7 | Y29: Mexicana | Z29: BEME850910HHGRRF08 | AA29: 1 | AB29: TRUE | AC29: 44053 | AD29: 44053 | AF29: 44105 | AG29: M | AH29: U | AI29: FALSE | AK29: FALSE | AL29: FALSE | AN29: Manejo | AO29: Conduccion de unidades en general | AP29: Manejo | AQ29: e.1791tusa@gmail.com | AR29: 44105 | AU29: 5256783377479499 | AV29: Banamex | AW29: 0 | AX29: 0 | AY29: 0.0 | BA29: 0 | BB29: 293.4 | BC29: 4 | BD29: FALSE | BF29: 44125 | BG29: M | BJ29: 1586481227 | BK29: 1228066151383 | BM29: 10 | BO29: 2 | BP29: N | BR29: FALSE | BT29: Tepeapulco | BW29: FALSE | BY29: FALSE | CD29: =+Table1[[#This Row],[Nombres]]&" "&Table1[[#This Row],[Ap_paterno]]&" "&Table1[[#This Row],[Ap_materno]] -> Efrain Bermudez Merida
A30: 1796 | B30: Galindo | C30: Calderon | D30: Carlos | E30: 27837 | F30: México | G30: GACC760318I11 | H30: Jenufa Mz 102 L22 | I30: Miguel Hidalgo | J30: Tlahuac | K30: D.F. | L30: 13200 | M30: México | O30: TRUE | Q30: O | S30: Operativo | T30: 5570324890 | W30: 44058 | X30: 4296761627-9 | Y30: Mexicana | Z30: GACC760318HDFLLR09 | AA30: 1 | AB30: FALSE | AC30: 44053 | AD30: 44053 | AF30: 44088 | AG30: M | AH30: C | AI30: FALSE | AK30: FALSE | AL30: FALSE | AO30: tricuerna | AQ30: charlie187641@gmail.com | AR30: 44088 | AU30: 5256783345237193 | AV30: Banamex | AW30: 0 | AX30: 0 | AY30: 0.0 | BA30: 0 | BB30: 287.93 | BC30: 0 | BD30: FALSE | BF30: 44095 | BG30: M | BJ30: 1740545224 | BK30: 3678041209624 | BM30: 10 | BO30: 2 | BP30: N | BR30: TRUE | BT30: Aculco | BW30: FALSE | BY30: FALSE | CD30: =+Table1[[#This Row],[Nombres]]&" "&Table1[[#This Row],[Ap_paterno]]&" "&Table1[[#This Row],[Ap_materno]] -> Carlos Galindo Calderon
A31: 1797 | B31: Lopez | C31: Ortega | D31: Beatriz | E31: 28824 | F31: Hidalgo | G31: LOOB7811303E5 | H31: Aldama No. 10 | I31: Centro | J31: Tlanalapa | K31: Hidalgo | L31: 43930 | M31: México | N31: Administracion de la calidad | O31: TRUE | Q31: A | S31: Administrativo | T31: 7711195439 | U31: 24 | W31: 44829 | X31: 13-03-78-0821-2 | Y31: Mexicana | Z31: LOOB781130MHGPRT04 | AA31: 2 | AB31: TRUE | AC31: 44060 | AD31: 44060 | AF31: 45030 | AG31: F | AH31: C | AI31: FALSE | AK31: FALSE | AL31: FALSE | AR31: 45030 | AU31: 5256781821733198 | AV31: Banamex | AW31: 0 | AX31: 0 | AY31: 0.0 | BA31: 0 | BB31: 545.89 | BC31: 0 | BD31: FALSE | BF31: 45042 | BG31: M | BJ31: 0000102525337 | BK31: 1397071423316 | BM31: 10 | BO31: 6 | BP31: N | BR31: FALSE | BS31: 7711293467 | BT31: Tepeapulco | BW31: FALSE | BY31: FALSE | CD31: =+Table1[[#This Row],[Nombres]]&" "&Table1[[#This Row],[Ap_paterno]]&" "&Table1[[#This Row],[Ap_materno]] -> Beatriz Lopez Ortega
A32: 1911 | B32: Sarabia | C32: Franco | D32: Luis Roberto | E32: 36086 | F32: Hidalgo | G32: SAFL981018F13 | H32: Felipe Angeles | I32: Barrio Negro | J32: Irolo | K32: Hidalgo | L32: 43991 | M32: Mexico | O32: TRUE | Q32: A | S32: Administrativo | T32: 7713922624 | X32: 1311980012-9 | Y32: Mexicana | Z32: SAFL981018HHGRRS09 | AA32: 2 | AB32: FALSE | AC32: 44403 | AD32: 44403 | AF32: 44522 | AG32: M | AH32: S | AI32: FALSE | AK32: FALSE | AL32: FALSE | AQ32: l.1911tusa@gmail.com | AR32: 44522 | AU32: 5256783613742890 | AV32: Banamex | AW32: 32 | AX32: 32 | AY32: 28.0 | AZ32: G | BA32: 0 | BB32: 424.13 | BC32: 0 | BD32: FALSE | BE32: 7712199121 | BF32: 44522 | BG32: M | BJ32: 1228118312273 | BM32: 10 | BO32: 5 | BP32: N | BQ32: M | BR32: FALSE | BS32: 7714204514 | BT32: Tepeapulco | BW32: FALSE | BY32: FALSE | CD32: =+Table1[[#This Row],[Nombres]]&" "&Table1[[#This Row],[Ap_paterno]]&" "&Table1[[#This Row],[Ap_materno]] -> Luis Roberto Sarabia Franco
A33: 1565 | B33: Lopez | C33: Hernandez | D33: Aurora Elizabeth | E33: 28302 | F33: Nuevo León | G33: LOHA7706269G3 | H33: Olmo No 130 | I33: Privada del Sauce, Sec Ebano | J33: Gral. Escobedo | K33: Nuevo Leon | L33: 66050 | M33: México | O33: FALSE | Q33: A | S33: Administrativo | U33: 0000503 0000002 | W33: 43158 | X33: 4300772762-1 | Y33: Mexicana | Z33: LOHA770626MNLPRR07 | AA33: 2 | AB33: TRUE | AC33: 43158 | AD33: 43158 | AF33: 43269 | AG33: F | AH33: C | AI33: FALSE | AK33: TRUE | AL33: TRUE | AN33: Compras, ventas, trafico | AO33: Compras, Responsable de tienda, Jefe de trafico | AP33: Trafico | AQ33: alope1522cy@gmail.com | AR33: 43279 | AU33: 5256782627440491 | AV33: Banamex | AW33: 0 | AX33: 0 | AY33: 0.0 | BA33: 1 | BB33: 423 | BC33: 1 | BD33: FALSE | BF33: 43315 | BG33: M | BJ33: 1582306991 | BK33: 0442062320301 | BM33: 10 | BO33: 2 | BP33: N | BT33: San Nicolas de los Garza | BW33: FALSE | BY33: FALSE | CD33: =+Table1[[#This Row],[Nombres]]&" "&Table1[[#This Row],[Ap_paterno]]&" "&Table1[[#This Row],[Ap_materno]] -> Aurora Elizabeth Lopez Hernandez
A34: 1564 | B34: Juarez | C34: Nieves | D34: Florencio Ivan | E34: 30172 | F34: Tlaxcala | G34: JUNF820809633 | H34: Magdalena de Quino No 3 | I34: Alfonso Espejel | J34: Calpulalpan | K34: Tlaxcala | L34: 90208 | M34: México | O34: TRUE | Q34: O | S34: Operativo | U34: 0000503 0000002 | V34: 000000000 | W34: 43144 | X34: 6104820468-1 | Y34: Mexicana | Z34: JUNF820809HTLRVL08 | AA34: 1 | AB34: TRUE | AC34: 43144 | AD34: 43144 | AF34: 43325 | AG34: M | AH34: C | AI34: FALSE | AK34: TRUE | AL34: TRUE | AN34: Manejo | AO34: Manejo de unidades de 48", full | AP34: Manejo | AQ34: ivan_jr24ju@hotmail.com | AR34: 43325 | AU34: 5256781751750998 | AV34: Banamex | AW34: 40 | AX34: 36 | AY34: 27.0 | AZ34: XL | BA34: 1 | BB34: 234.99 | BC34: 1 | BD34: FALSE | BF34: 43399 | BG34: M | BJ34: 1326055147 | BK34: 0078011381968 | BM34: 10 | BO34: 2 | BP34: N | BT34: Calpulalpan | BW34: FALSE | BY34: FALSE | CD34: =+Table1[[#This Row],[Nombres]]&" "&Table1[[#This Row],[Ap_paterno]]&" "&Table1[[#This Row],[Ap_materno]] -> Florencio Ivan Juarez Nieves
A35: 1563 | B35: Avila | C35: Aguirre | D35: Juan Antonio | E35: 28456 | F35: México | G35: AIAJ771127BK2 | H35: C. de la Gloria No 6 | I35: Loc. San Juanico | J35: Acolman | K35: México | L35: 55871 | M35: México | O35: TRUE | Q35: O | S35: Operativo | T35: 5565314118 | U35: 00000504 | V35: C-2694262 | W35: 43144 | X35: 9495772125-4 | Y35: Mexicana | Z35: AIAJ771127HMCVGN09 | AA35: 1 | AB35: TRUE | AC35: 43144 | AD35: 43144 | AF35: 43887 | AG35: M | AH35: U | AI35: FALSE | AK35: TRUE | AL35: TRUE | AN35: Manejo | AO35: Manejo | AP35: Manejo | AQ35: j.1563tusa@gmail.com | AR35: 43887 | AU35: 5256782352152295 | AV35: Banamex | AW35: 34 | AX35: 34 | AY35: 0.0 | BA35: 1 | BB35: 264.36 | BC35: 1 | BD35: FALSE | BF35: 43892 | BG35: M | BJ35: 1181201097 | BK35: 0037047358906 | BM35: 10 | BO35: 2 | BP35: N | BR35: FALSE | BT35: Aculco | BW35: FALSE | BY35: FALSE | CD35: =+Table1[[#This Row],[Nombres]]&" "&Table1[[#This Row],[Ap_paterno]]&" "&Table1[[#This Row],[Ap_materno]] -> Juan Antonio Avila Aguirre
A36: 1562 | B36: Tenopala | C36: Hernandez | D36: Gerardo Guadalupe | E36: 22192 | F36: Tlaxcala | G36: TEHG601003TY6 | H36: Isidro Candida Galvan Edif 49 Depto 7 | I36: U Hab Infonavit | J36: Calpulalpan | K36: Tlaxcala | L36: 90203 | M36: México | O36: TRUE | Q36: O | S36: Operativo | T36: 7491027818 | U36: 004-0000384386-00 | V36: b-1439279 | W36: 43144 | X36: 1380601678-1 | Y36: Mexicana | Z36: TEHG601003HTLNRR04 | AA36: 1 | AB36: TRUE | AC36: 43144 | AD36: 43144 | AF36: 44424 | AG36: M | AH36: C | AI36: FALSE | AK36: TRUE | AL36: TRUE | AM36: Se realiza reingreso por motivo de proyecto Lazaro Cardenas 15 al 20 de mayo de 2022, | AN36: Manejo | AO36: Manejo de camiones, pipas de combustible y de volteo | AP36: Manejo | AQ36: g.1562tusa@gmail.com | AR36: 44424 | AU36: 5256782567084994 | AV36: Banamex | AW36: 36 | AX36: 34 | AY36: 0.0 | BA36: 1 | BB36: 741.06 | BC36: 1 | BD36: FALSE | BF36: 44704 | BG36: M | BJ36: 1586541857 | BK36: 0082050147524 | BM36: 10 | BO36: 2 | BP36: N | BR36: FALSE | BS36: 7711470457 | BT36: Calpulalpan | BW36: FALSE | BY36: FALSE | CD36: =+Table1[[#This Row],[Nombres]]&" "&Table1[[#This Row],[Ap_paterno]]&" "&Table1[[#This Row],[Ap_materno]] -> Gerardo Guadalupe Tenopala Hernandez
A37: 1561 | B37: Orozco | C37: Palacios | D37: Noe | E37: 31586 | F37: Morelos | G37: OOPN860623HC3 | H37: Lorenzo Vazquez 3 | I37: Centro Higueron | J37: Jojutla | K37: Morelos | L37: 62906 | M37: México | O37: TRUE | Q37: O | S37: Operativo | T37: 7343454184 | U37: 00000504 | V37: 000000000 | W37: 43143 | X37: 1506862506-8 | Y37: Mexicana | Z37: OOPN860623HMSRLX01 | AA37: 1 | AB37: TRUE | AC37: 43143 | AD37: 43143 | AF37: 43509 | AG37: M | AH37: C | AI37: FALSE | AK37: TRUE | AL37: TRUE | AN37: Manejo | AO37: Manejo | AP37: Manejo | AQ37: noeop23@hotmail.com | AR37: 43509 | AU37: 5256782495996392 | AV37: Banamex | AW37: 42 | AX37: 44 | AY37: 0.0 | BA37: 1 | BB37: 275.78 | BC37: 1 | BD37: FALSE | BF37: 44249 | BG37: M | BJ37: 1094561415 | BK37: 0531098894847 | BM37: 10 | BN37: 7773404329 | BO37: 2 | BP37: N | BR37: FALSE | BT37: Jojutla | BW37: FALSE | BY37: FALSE | CD37: =+Table1[[#This Row],[Nombres]]&" "&Table1[[#This Row],[Ap_paterno]]&" "&Table1[[#This Row],[Ap_materno]] -> Noe Orozco Palacios
A38: 1593 | B38: Garcia | C38: Hernandez | D38: Julio Cesar | E38: 33718 | F38: Hidalgo | G38: GAHJ920424DE5 | H38: Emiliano Zapata SN | I38: Del trabajo | J38: Tepeapulco | K38: Hidalgo | L38: 43976 | M38: México | O38: TRUE | Q38: O | S38: Operativo | T38: 791913274 | V38: D118469-2 | W38: 43248 | X38: 1310921958-7 | Y38: Mexicana | Z38: GAHJ920424HHGRRL07 | AA38: 1 | AB38: TRUE | AC38: 43248 | AD38: 43248 | AF38: 43312 | AG38: M | AH38: U | AI38: FALSE | AK38: TRUE | AL38: TRUE | AN38: Manejo | AO38: Manejo | AP38: Manejo | AQ38: 9204julioc@gmail.com | AR38: 43312 | AU38: 5256782473000993 | AV38: Banamex | AW38: 30 | AX38: 30 | AY38: 25.0 | AZ38: M | BA38: 1 | BB38: 375.43 | BC38: 3 | BD38: FALSE | BF38: 43315 | BG38: M | BM38: 10 | BN38: 7751220805 | BO38: 2 | BP38: N | BT38: Apan | BW38: FALSE | BY38: FALSE | CD38: =+Table1[[#This Row],[Nombres]]&" "&Table1[[#This Row],[Ap_paterno]]&" "&Table1[[#This Row],[Ap_materno]] -> Julio Cesar Garcia Hernandez
A39: 1590 | B39: Arevalo | C39: Villegas | D39: Susana | E39: 36280 | F39: Nuevo León | G39: AEVS990430540 | H39: Rio Amazonas 00112 | I39: Fracc. Mirasur 2 | J39: General de Escobedo | K39: Nuevo Leon | L39: 66070 | M39: México | N39: Licenciatura en Logística | O39: FALSE | Q39: A | S39: Administrativo | T39: 8184752185 | U39: 0000505-0000001 | W39: 43241 | X39: 0216991659-6 | Y39: Mexicana | Z39: AEVS990430MNLRLS04 | AA39: 2 | AB39: TRUE | AC39: 43241 | AD39: 43241 | AF39: 43949 | AG39: F | AH39: S | AI39: FALSE | AK39: FALSE | AL39: TRUE | AN39: Logistica | AO39: Sin experiencia | AP39: logistica y transporte | AQ39: susana30villegas@gmail.com | AR39: 43949 | AU39: 5256783165289092 | AV39: Banamex | AW39: M | AX39: 0 | AY39: 0.0 | BA39: 1 | BB39: 445.24 | BC39: 3 | BD39: FALSE | BF39: 43951 | BG39: M | BJ39: 1596749654 | BK39: 0440118007372 | BM39: 10 | BO39: 5 | BP39: N | BR39: FALSE | BT39: San Nicolas de los Garza | BW39: FALSE | BY39: FALSE | CD39: =+Table1[[#This Row],[Nombres]]&" "&Table1[[#This Row],[Ap_paterno]]&" "&Table1[[#This Row],[Ap_materno]] -> Susana Arevalo Villegas
A40: 1588 | B40: Garcia | C40: Cortes | D40: Efrain | E40: 32695 | F40: México | G40: GACE890706EY2 | H40: 1° de Mayo No 39 A | I40: Las Haciendas | J40: Apan | K40: Hidalgo | L40: 43909 | M40: México | O40: TRUE | Q40: O | S40: Operativo | T40: 2411351238 | V40: 000000 | W40: 43229 | X40: 1306891148-9 | Y40: Mexicana | Z40: GACE890706HMCRRF01 | AA40: 1 | AB40: TRUE | AC40: 43229 | AD40: 43229 | AF40: 43385 | AG40: M | AH40: C | AI40: FALSE | AK40: TRUE | AL40: TRUE | AN40: Manejo | AO40: Manejo | AP40: Manejo | AQ40: efraingar05@gmail.com | AR40: 43385 | AU40: 5256782277318195 | AV40: Banamex | AW40: 34 | AX40: 32 | AY40: 27.0 | AZ40: M | BA40: 1 | BB40: 611.18 | BC40: 3 | BD40: FALSE | BF40: 43391 | BG40: M | BJ40: 1377872421 | BK40: 0135078710898 | BM40: 10 | BO40: 2 | BP40: N | BT40: Ecatepec de Morelos | BW40: FALSE | BY40: FALSE | CD40: =+Table1[[#This Row],[Nombres]]&" "&Table1[[#This Row],[Ap_paterno]]&" "&Table1[[#This Row],[Ap_materno]] -> Efrain Garcia Cortes
A41: 1586 | B41: Torres | C41: Estrada | D41: J Guadalupe | E41: 23723 | F41: Nuevo León | G41: TOEG641212FX8 | H41: Cerro del Sabino 00115 | I41: Provileon | J41: General Escobedo | K41: Nuevo Leon | L41: 66070 | M41: México | O41: TRUE | Q41: O | S41: Operativo | V41: 00000000 | W41: 43225 | X41: 4380629129-0 | Y41: Mexicana | Z41: TOEG641212HNLRSD05 | AA41: 1 | AB41: TRUE | AC41: 43225 | AD41: 43225 | AF41: 43227 | AG41: M | AH41: S | AI41: FALSE | AK41: TRUE | AL41: TRUE | AN41: Manejo | AO41: Manejo | AP41: Manejo | AR41: 43227 | AW41: 0 | AX41: 0 | AY41: 0.0 | BA41: 1 | BB41: 92.5 | BC41: 3 | BD41: FALSE | BF41: 43535 | BG41: M | BJ41: 1434874951 | BK41: 0474022182997 | BM41: 10 | BO41: 2 | BP41: N | BT41: Dr. Arroyo | BW41: FALSE | BY41: FALSE | CD41: =+Table1[[#This Row],[Nombres]]&" "&Table1[[#This Row],[Ap_paterno]]&" "&Table1[[#This Row],[Ap_materno]] -> J Guadalupe Torres Estrada
A42: 1585 | B42: Lopez | C42: Avila | D42: Arturo | E42: 33506 | F42: México | G42: LOAA910925IN0 | H42: Rayon Oriente No 69 | I42: Centro | J42: Apan | K42: Hidalgo | L42: 43900 | M42: México | O42: TRUE | Q42: O | S42: Operativo | T42: 7751342692 | V42: 000000000 | W42: 43223 | X42: 1308910863-6 | Y42: Mexicana | Z42: LOAA910925HDFPVR05 | AA42: 1 | AB42: TRUE | AC42: 43223 | AD42: 43223 | AF42: 43250 | AG42: M | AH42: U | AI42: FALSE | AK42: FALSE | AL42: TRUE | AN42: Manejo | AO42: Manejo | AP42: Manejo | AQ42: juniorlaser@gmail.com | AR42: 43250 | AU42: 5256782681585694 | AV42: Banamex | AW42: 34 | AX42: 34 | AY42: 28.0 | AZ42: M | BA42: 1 | BB42: 92.5 | BC42: 3 | BD42: FALSE | BF42: 43535 | BG42: M | BJ42: 0128119554799 | BK42: 0913072107086 | BM42: 10 | BO42: 2 | BP42: N | BT42: Ecatepec de Morelos | BW42: FALSE | BY42: FALSE | CD42: =+Table1[[#This Row],[Nombres]]&" "&Table1[[#This Row],[Ap_paterno]]&" "&Table1[[#This Row],[Ap_materno]] -> Arturo Lopez Avila
A43: 1583 | B43: Soto | C43: Soto | D43: Mario | E43: 23945 | F43: México | G43: SOSM650722IP9 | H43: Loma del Sol , Mz 56, Lt 10 | I43: Vista Hermosa | J43: Gustavo A. Madero | K43: México | L43: 71870 | M43: México | O43: TRUE | Q43: O | S43: Operativo | T43: 5557184140 | U43: 00000504 | W43: 43214 | X43: 1981652525-7 | Y43: Mexicana | Z43: SOSM650722HDFTTR04 | AA43: 1 | AB43: TRUE | AC43: 43214 | AD43: 43214 | AF43: 43503 | AG43: M | AH43: C | AI43: FALSE | AK43: TRUE | AL43: TRUE | AN43: Manejo | AO43: Manejo | AP43: Manejo | AQ43: mariosotosoto04@gmail.com | AR43: 43503 | AU43: 5256782665528397 | AV43: Banamex | AW43: 40 | AX43: 36 | AY43: 26.0 | AZ43: G | BA43: 1 | BB43: 624.99 | BC43: 2 | BD43: FALSE | BF43: 43516 | BG43: M | BJ43: 1529218815 | BK43: 0877007219312 | BM43: 10 | BN43: 5575283993 | BO43: 2 | BP43: N | BT43: Ecatepec de Morelos | BW43: FALSE | BY43: FALSE | CD43: =+Table1[[#This Row],[Nombres]]&" "&Table1[[#This Row],[Ap_paterno]]&" "&Table1[[#This Row],[Ap_materno]] -> Mario Soto Soto
A44: 1782 | B44: Ortega | C44: Hernandez | D44: Marco Antonio | E44: 27384 | F44: México | G44: OEHM741221DV2 | H44: Duraznitos 103 | I44: Los Perales | J44: Xicotepec de Juarez | K44: Puebla | L44: 73080 | M44: Mexico | O44: TRUE | Q44: O | S44: Operativo | X44: 4800742374-1 | Y44: Mexicana | Z44: OEHM741221HDFRRR04 | AA44: 1 | AB44: TRUE | AC44: 44025 | AD44: 44025 | AF44: 44028 | AG44: M | AH44: D | AI44: FALSE | AK44: FALSE | AL44: FALSE | AN44: Manejo | AO44: Conduccion | AP44: Mecanica | AR44: 44028 | AW44: 0 | AX44: 0 | AY44: 0.0 | BA44: 0 | BB44: 130.48 | BC44: 4 | BD44: FALSE | BF44: 44126 | BG44: M | BJ44: 2376042179759 | BK44: 1935487849 | BM44: 10 | BO44: 2 | BP44: N | BR44: FALSE | BT44: Ecatepec de Morelos | BW44: FALSE | BY44: FALSE | CD44: =+Table1[[#This Row],[Nombres]]&" "&Table1[[#This Row],[Ap_paterno]]&" "&Table1[[#This Row],[Ap_materno]] -> Marco Antonio Ortega Hernandez
A45: 1794 | B45: Velazquez | C45: Montero | D45: Juan Jose | E45: 24221 | F45: México | G45: VEMJ660424TV9 | H45: Oceano Pacifico 12 | I45: Fracc la Quebrada | J45: Cuautitlan Izcalli | K45: México | L45: 54769 | M45: México | O45: TRUE | Q45: O | S45: Operativo | T45: 2228673791 | U45: 004-0000384386-00 | X45: 0184662258-5 | Y45: Mexicana | Z45: VEMJ660424HDFLNN04 | AA45: 1 | AB45: TRUE | AC45: 44053 | AD45: 44053 | AF45: 44546 | AG45: M | AH45: S | AI45: FALSE | AK45: TRUE | AL45: FALSE | AN45: Manejo | AO45: Manejo | AP45: Manejo | AQ45: j.1794tusa@gmail.com | AR45: 44546 | AU45: 5256782828193493 | AV45: Banamex | AW45: 40 | AX45: 34 | AY45: 0.0 | BA45: 0 | BB45: 516.34 | BC45: 4 | BD45: FALSE | BF45: 44672 | BG45: M | BJ45: 0896039356881 | BK45: 1789223536 | BM45: 10 | BO45: 2 | BP45: N | BR45: FALSE | BS45: 5549918168 | BT45: Ecatepec de Morelos | BW45: FALSE | BY45: FALSE | CD45: =+Table1[[#This Row],[Nombres]]&" "&Table1[[#This Row],[Ap_paterno]]&" "&Table1[[#This Row],[Ap_materno]] -> Juan Jose Velazquez Montero
A46: 1795 | B46: Franco | C46: Hernández | D46: Arizair | E46: 31024 | F46: Tlaxcala | G46: FAHA841208RW6 | H46: Durango S/N | I46: Diaz Ordaz 023 | J46: Tlaxcala | K46: Tlaxcala | L46: 90226 | M46: México | O46: TRUE | Q46: O | S46: Operativo | T46: 7491104340 | U46: 004-0000384386-00 | X46: 1307840315-4 | Y46: Mexicana | Z46: FAHA841208HTLRRR00 | AA46: 1 | AB46: FALSE | AC46: 44053 | AD46: 44053 | AF46: 44334 | AG46: M | AH46: U | AI46: FALSE | AK46: TRUE | AL46: FALSE | AN46: MANEJO | AO46: MANEJO | AP46: MANEJO | AQ46: a.1795tusa@gmail.com | AR46: 44334 | AU46: 5256783377239091 | AV46: Banamex | AW46: 32 | AX46: 34 | AY46: 0.0 | BA46: 0 | BB46: 317.87 | BC46: 4 | BD46: FALSE | BF46: 44337 | BG46: M | BJ46: 0078010656657 | BK46: 378407365 | BM46: 10 | BO46: 2 | BP46: N | BQ46: M | BR46: FALSE | BT46: Nanacamilpa de Mariano Arista | BW46: FALSE | BY46: FALSE | CD46: =+Table1[[#This Row],[Nombres]]&" "&Table1[[#This Row],[Ap_paterno]]&" "&Table1[[#This Row],[Ap_materno]] -> Arizair Franco Hernández
A47: 1798 | B47: Bocardo | C47: Salazar | D47: Ever Joanan | E47: 31876 | F47: Nuevo León | G47: BOSE870409IHA | H47: Portal Sur 102 B | I47: Portal del Parque | J47: Garcia | K47: Nuevo Leon | L47: 66023 | M47: México | O47: FALSE | Q47: A | S47: Administrativo | U47: 004-0000384386-00 | X47: 4303874788-7 | Y47: Mexicana | Z47: BOSE870409HNLCLV02 | AA47: 2 | AB47: TRUE | AC47: 44068 | AD47: 44068 | AF47: 44148 | AG47: M | AH47: S | AI47: FALSE | AK47: TRUE | AL47: FALSE | AN47: Mantenimiento | AO47: Mantenimiento | AP47: Mantenimiento | AR47: 44148 | AU47: 4152313462162475 | AV47: Banamex | AW47: 0 | AX47: 0 | AY47: 0.0 | BA47: 0 | BB47: 350.29 | BC47: 4 | BD47: FALSE | BF47: 44153 | BG47: M | BJ47: 2124106843420 | BK47: 0619052210799 | BM47: 10 | BO47: 4 | BP47: N | BR47: FALSE | BT47: Monterrey | BW47: FALSE | BY47: FALSE | CD47: =+Table1[[#This Row],[Nombres]]&" "&Table1[[#This Row],[Ap_paterno]]&" "&Table1[[#This Row],[Ap_materno]] -> Ever Joanan Bocardo Salazar
A48: 1799 | B48: Olivares | C48: Betancourt | D48: Alan Javier | E48: 34692 | F48: México | G48: OIBA941224UX8 | H48: Ignacio Cruz SN | I48: Alfredo V Bonfil | J48: Tlanalapa | K48: Hidalgo | L48: 43904 | M48: México | O48: TRUE | Q48: A | S48: Administrativo | T48: 7711295843 | U48: 004-0000384386-00 | W48: 44099 | X48: 1314940063-5 | Y48: Mexicana | Z48: OIBA941224HMCLTL00 | AA48: 2 | AB48: TRUE | AC48: 44098 | AD48: 44098 | AF48: 44225 | AG48: M | AH48: C | AI48: FALSE | AK48: TRUE | AL48: TRUE | AQ48: olivaresalan73@gmail.com | AR48: 44225 | AU48: 5256783377487294 | AV48: Banamex | AW48: 40 | AX48: 32 | AY48: 0.0 | BA48: 0 | BB48: 333.29 | BC48: 3 | BD48: FALSE | BF48: 44305 | BG48: M | BJ48: 1396134845837 | BK48: 1313072108896 | BM48: 10 | BO48: 3 | BP48: N | BQ48: G | BR48: FALSE | BT48: Sin Especificar | BW48: FALSE | BY48: FALSE | CD48: =+Table1[[#This Row],[Nombres]]&" "&Table1[[#This Row],[Ap_paterno]]&" "&Table1[[#This Row],[Ap_materno]] -> Alan Javier Olivares Betancourt
A49: 1801 | B49: Ruiz | C49: Andriano | D49: Luis Enrique | E49: 34493 | F49: Hidalgo | G49: RUAL940608KQ2 | H49: Ocampo Sur SN | I49: San Pablo | J49: Apan | K49: Hidalgo | L49: 43906 | M49: Mexico | O49: FALSE | Q49: O | S49: Operativo | T49: 7751112035 | U49: 004-0000384386-00 | X49: 1312941090-1 | Y49: Mexicana | Z49: RUAL940608HHGZNS08 | AA49: 1 | AB49: FALSE | AC49: 44103 | AD49: 44103 | AF49: 44196 | AG49: M | AH49: U | AI49: FALSE | AK49: TRUE | AL49: FALSE | AN49: Mecanica | AO49: Manejo | AP49: Manejo | AQ49: luis.adriano0806@gmail.com | AR49: 44196 | AU49: 5256783273296294 | AV49: Banamex | AW49: 36 | AX49: 36 | AY49: 0.0 | BA49: 0 | BB49: 482.46 | BC49: 3 | BD49: FALSE | BE49: 8115388353 | BF49: 44207 | BG49: M | BJ49: 0137129984329 | BK49: 1213072101809 | BM49: 10 | BO49: 3 | BP49: N | BR49: FALSE | BT49: Apan | BW49: FALSE | BY49: FALSE | CD49: =+Table1[[#This Row],[Nombres]]&" "&Table1[[#This Row],[Ap_paterno]]&" "&Table1[[#This Row],[Ap_materno]] -> Luis Enrique Ruiz Andriano
A50: 1802 | B50: Rodriguez | C50: Pinal | D50: Fabian Ernesto | E50: 30039 | F50: México | G50: ROPF820329HA8 | H50: Jaguey Prieto MZ37 LT6 | I50: Plan de Ayala | J50: Sahagun | K50: Hidalgo | L50: 43996 | M50: Mèxico | O50: TRUE | Q50: O | S50: Operativo | T50: 5542721822 | U50: 004-0000384386-00 | X50: 4500821991-2 | Y50: Mexicana | Z50: ROPF820329HDFDNB01 | AA50: 1 | AB50: TRUE | AC50: 44124 | AD50: 44124 | AF50: 44440 | AG50: M | AH50: S | AI50: FALSE | AK50: TRUE | AL50: FALSE | AN50: Manejo | AO50: Manejo | AP50: Mecanica | AQ50: figuraelian@gmail.com | AR50: 44440 | AU50: 5579100309106142 | AV50: Banamex | AW50: 0 | AX50: 0 | AY50: 0.0 | BA50: 0 | BB50: 400.94 | BC50: 5 | BD50: FALSE | BE50: 7712406095 | BF50: 44452 | BG50: M | BJ50: 1738255966 | BK50: 1214047512362 | BM50: 10 | BO50: 2 | BP50: N | BQ50: 0 | BR50: FALSE | BS50: 5615174518 | BT50: Ecatepec de Morelos | BW50: FALSE | BY50: FALSE | CD50: =+Table1[[#This Row],[Nombres]]&" "&Table1[[#This Row],[Ap_paterno]]&" "&Table1[[#This Row],[Ap_materno]] -> Fabian Ernesto Rodriguez Pinal
A51: 1804 | B51: Perez | C51: Muñoz | D51: Mario Alfredo | E51: 25039 | F51: Hidalgo | G51: PEMM680720P99 | H51: Ocampo Nte No. 44 | I51: Centro | J51: Apan | K51: Hidalgo | L51: 43900 | M51: Mexico | O51: TRUE | Q51: O | S51: Operativo | T51: 7296172928 | U51: 54 | W51: 44829 | X51: 6290680399-4 | Y51: Mexicana | Z51: PEMM680720HHGRXR06 | AA51: 1 | AB51: TRUE | AC51: 44130 | AD51: 44130 | AF51: 45076 | AG51: M | AH51: C | AI51: FALSE | AK51: TRUE | AL51: FALSE | AN51: Manejo | AO51: Manejo | AP51: Manejo | AQ51: 20076851MAPM@gmail.com | AR51: 45076 | AU51: 5256784035305399 | AV51: Banamex | AW51: 38 | AX51: 30 | AY51: 0.0 | BA51: 0 | BB51: 347.1 | BC51: 5 | BD51: FALSE | BE51: 7711895525 | BF51: 45085 | BG51: M | BJ51: 1377270119 | BK51: 0134051122821 | BM51: 10 | BO51: 3 | BP51: N | BR51: FALSE | BS51: 7481321216 | BT51: Apan | BU51: 44897 | BW51: FALSE | BY51: FALSE | CD51: =+Table1[[#This Row],[Nombres]]&" "&Table1[[#This Row],[Ap_paterno]]&" "&Table1[[#This Row],[Ap_materno]] -> Mario Alfredo Perez Muñoz
A52: 1806 | B52: Nuñez | C52: Pacheco | D52: Guadalupe Luis | E52: 26430 | F52: México | G52: NUPG720511D10 | H52: Emiliano Zapata Edif 2 Depto 401 | I52: Villlas el gigante | J52: Coacalco | K52: Mexico | L52: 55709 | M52: México | O52: TRUE | Q52: O | S52: Operativo | T52: 5524991107 | W52: 44165 | X52: 9290726873-1 | Y52: Mexicana | Z52: NUPG720511HDFXCD01 | AA52: 1 | AB52: TRUE | AC52: 44154 | AD52: 44154 | AF52: 44367 | AG52: M | AH52: C | AI52: FALSE | AK52: TRUE | AL52: FALSE | AN52: Manejo | AO52: Manejo de unidades varias, trasladista y carga | AP52: Manejo | AQ52: luis_nunez714@hotmail.com | AR52: 44376 | AU52: 5256783256592099 | AV52: Banamex | AW52: 0 | AX52: 0 | AY52: 0.0 | BA52: 0 | BB52: 322.82 | BC52: 6 | BD52: FALSE | BF52: 44408 | BG52: M | BJ52: 2016420551 | BK52: 0613025393969 | BM52: 10 | BO52: 3 | BP52: N | BQ52: M | BR52: TRUE | BS52: 5518935789 | BT52: Ecatepec de Morelos | BW52: FALSE | BY52: FALSE | CD52: =+Table1[[#This Row],[Nombres]]&" "&Table1[[#This Row],[Ap_paterno]]&" "&Table1[[#This Row],[Ap_materno]] -> Guadalupe Luis Nuñez Pacheco
A53: 1809 | B53: Bello | C53: Serrano | D53: Miguel Angel | E53: 27033 | F53: Tlaxcala | G53: BESM740104U23 | H53: Prol. Benito Juarez 4 | I53: Centro | J53: Emiliano Zapata | K53: Hidalgo | L53: 43960 | M53: Mexico | O53: TRUE | Q53: O | S53: Operativo | W53: 44165 | X53: 1393745252-5 | Y53: Mexicana | Z53: BESM740104HTLLRG06 | AA53: 1 | AB53: TRUE | AC53: 44159 | AF53: 44159 | AG53: M | AH53: C | AI53: FALSE | AK53: TRUE | AL53: FALSE | AN53: Manejo | AO53: Manejo | AP53: Manejo | AQ53: m.1809tusa@gmail.com | AW53: 0 | AX53: 0 | AY53: 0.0 | BA53: 0 | BB53: 130.48 | BC53: 6 | BD53: FALSE | BF53: 44173 | BG53: M | BJ53: 1838206628 | BK53: 0351052083714 | BM53: 10 | BO53: 2 | BP53: N | BR53: TRUE | BT53: Calpulalpan | BW53: FALSE | BY53: FALSE | CD53: =+Table1[[#This Row],[Nombres]]&" "&Table1[[#This Row],[Ap_paterno]]&" "&Table1[[#This Row],[Ap_materno]] -> Miguel Angel Bello Serrano
A54: 1582 | B54: De La Rosa | C54: Arteaga | D54: Rafael | E54: 27324 | F54: México | G54: ROAR741022259 | H54: Xolotl No 53 | I54: Ancon de los Reyes | J54: Los Reyes la Paz | K54: Estado de México | L54: 56410 | M54: México | O54: TRUE | Q54: O | S54: Operativo | T54: 5575435397 | W54: 43214 | X54: 9693740107-1 | Y54: Mexicana | Z54: ROAR741022HDFSRF02 | AA54: 1 | AB54: TRUE | AC54: 43214 | AD54: 43214 | AF54: 43270 | AG54: M | AH54: C | AI54: FALSE | AK54: TRUE | AL54: TRUE | AN54: Manejo | AO54: Manejo | AP54: Manejo | AQ54: rafita22.delarosa@gmail.com | AR54: 43270 | AS54: 96937401071 | AU54: 5256782633579696 | AV54: Banamex | AW54: 40 | AX54: 36 | AY54: 26.0 | AZ54: M | BA54: 1 | BB54: 624.99 | BC54: 2 | BD54: FALSE | BF54: 43535 | BG54: M | BJ54: 1175921145 | BK54: 3977084759985 | BM54: 10 | BN54: 5524257231 | BO54: 2 | BP54: N | BT54: Ecatepec de Morelos | BW54: FALSE | BY54: FALSE | CD54: =+Table1[[#This Row],[Nombres]]&" "&Table1[[#This Row],[Ap_paterno]]&" "&Table1[[#This Row],[Ap_materno]] -> Rafael De La Rosa Arteaga
A55: 1581 | B55: Ambriz | C55: Ramos | D55: Jesus Francisco | E55: 33081 | F55: Tlaxcala | G55: AIRJ900627N77 | H55: Carr. San Marcos No 2 | I55: La Trinidad | J55: Otumba | K55: Estado de México | L55: 55900 | M55: México | O55: TRUE | Q55: O | S55: Operativo | T55: 2722253497 | W55: 43214 | X55: 9408905337-8 | Y55: Mexicana | Z55: AIRJ900627HTLMMS09 | AA55: 1 | AB55: TRUE | AC55: 43214 | AD55: 43214 | AF55: 43256 | AG55: M | AH55: U | AI55: FALSE | AK55: TRUE | AL55: TRUE | AN55: Manejo | AO55: Manejo | AP55: Manejo | AQ55: 5576669118jar@gmail.com | AR55: 43256 | AU55: 5256782613779191 | AV55: Banamex | AW55: 32 | AX55: 32 | AY55: 28.0 | AZ55: M | BA55: 1 | BB55: 92.5 | BC55: 2 | BD55: FALSE | BF55: 43327 | BG55: M | BJ55: 1255551826 | BK55: 0332081755795 | BM55: 10 | BN55: 5564072240 | BO55: 2 | BP55: N | BT55: Calpulalpan | BW55: FALSE | BY55: FALSE | CD55: =+Table1[[#This Row],[Nombres]]&" "&Table1[[#This Row],[Ap_paterno]]&" "&Table1[[#This Row],[Ap_materno]] -> Jesus Francisco Ambriz Ramos
A56: 1580 | B56: Franco | C56: Lozano | D56: Marcos Abraham | E56: 35716 | F56: Hidalgo | G56: FALM9710138B6 | H56: Riva Palacios No 27 | I56: Plaza Vieja | J56: Tepeapulco | K56: Hidalgo | L56: 43976 | M56: México | N56: Sin Especialidad | O56: FALSE | Q56: O | S56: Operativo | T56: 7751890757 | U56: 0000505-0000001 | V56: 00000 | W56: 43214 | X56: 3716972006-9 | Y56: Mexicana | Z56: FALM971013HHGRZR09 | AA56: 1 | AB56: TRUE | AC56: 43214 | AD56: 43214 | AF56: 44026 | AG56: M | AH56: C | AI56: FALSE | AK56: TRUE | AL56: FALSE | AN56: Manejo | AO56: Manejo | AP56: Manejo | AQ56: marcosabrahamfrancolozano97@hotmail.com | AR56: 44026 | AU56: 5256782681609296 | AV56: Banamex | AW56: 34 | AX56: 32 | AY56: 0.0 | BA56: 1 | BB56: 341.53 | BC56: 2 | BD56: FALSE | BF56: 44028 | BG56: M | BJ56: 1389923694 | BK56: 1196104685754 | BM56: 10 | BN56: 7911051115 | BO56: 3 | BP56: N | BR56: FALSE | BT56: Pachuca de Soto | BW56: FALSE | BY56: FALSE | CD56: =+Table1[[#This Row],[Nombres]]&" "&Table1[[#This Row],[Ap_paterno]]&" "&Table1[[#This Row],[Ap_materno]] -> Marcos Abraham Franco Lozano
A57: 1574 | B57: Rodriguez | C57: Roldan | D57: Renato | E57: 24386 | F57: Hidalgo | G57: RORR661006L71 | H57: Aldama No 13 A | I57: Centro | J57: Emiliano Zapata | K57: Hidalgo | L57: 43960 | M57: México | O57: TRUE | Q57: O | S57: Operativo | T57: 5540056609 | W57: 43172 | X57: 1384650059-6 | Y57: Mexicana | Z57: RORR661006HHGDLN06 | AA57: 1 | AB57: TRUE | AC57: 43172 | AD57: 43172 | AF57: 43182 | AG57: M | AH57: C | AI57: FALSE | AK57: TRUE | AL57: FALSE | AN57: Manejo | AO57: Quinta rueda, autobus | AP57: Manejo | AQ57: renato.1735@hotmail.com | AR57: 43182 | AS57: 1302035722 | AU57: 5256782646462997 | AV57: Banamex | AW57: 38 | AX57: 30 | AY57: 25.0 | AZ57: M | BA57: 1 | BB57: 92.5 | BC57: 2 | BD57: FALSE | BF57: 43194 | BG57: M | BJ57: 0353037859232 | BK57: 0000018665267 | BM57: 10 | BN57: 5514240479 | BO57: 2 | BP57: N | BT57: Emiliano Zapata | BW57: FALSE | BY57: FALSE | CD57: =+Table1[[#This Row],[Nombres]]&" "&Table1[[#This Row],[Ap_paterno]]&" "&Table1[[#This Row],[Ap_materno]] -> Renato Rodriguez Roldan
A58: 1579 | B58: Valencia | C58: Arce | D58: Macario | E58: 31718 | F58: Hidalgo | G58: VAAM861102MJ0 | H58: Barrio de Chapultepec No 14 | I58: Santa Monica | J58: Epazoyucan | K58: Hidalgo | L58: 43590 | M58: México | O58: TRUE | Q58: O | S58: Operativo | T58: 7714059764 | U58: 004-0000384386-00 | W58: 43213 | X58: 1311860700-4 | Y58: Mexicana | Z58: VAAM861102HHGLRC09 | AA58: 1 | AB58: TRUE | AC58: 43213 | AD58: 43213 | AF58: 44440 | AG58: M | AH58: C | AI58: FALSE | AK58: TRUE | AL58: TRUE | AN58: Manejo | AO58: Manejo | AP58: Manejo | AQ58: m.1579tusa@gmail.com | AR58: 44440 | AU58: 5256782129191394 | AV58: Banamex | AW58: 36 | AX58: 32 | AY58: 27.0 | AZ58: G | BA58: 1 | BB58: 380.58 | BC58: 2 | BD58: FALSE | BF58: 44452 | BG58: M | BJ58: 1361744404 | BK58: 0365086594079 | BM58: 10 | BN58: 7751997958 | BO58: 2 | BP58: N | BR58: FALSE | BS58: 5535560168 | BT58: Epazoyucan | BW58: FALSE | BY58: FALSE | CD58: =+Table1[[#This Row],[Nombres]]&" "&Table1[[#This Row],[Ap_paterno]]&" "&Table1[[#This Row],[Ap_materno]] -> Macario Valencia Arce
A59: 1578 | B59: Rivas | C59: Avila - Baja 1 | D59: Karen | E59: 33861 | F59: Hidalgo | G59: RIAK920914K43 | H59: Manuel Díaz Infante No 127 | I59: Tadeo de Niza | J59: Cd. Sahagun | K59: Hidalgo | L59: 43996 | M59: México | N59: Licenciatura en Contabilidad | O59: TRUE | Q59: A | S59: Administrativo | T59: 7919134873 | W59: 43207 | X59: 1310924312-4 | Y59: Mexicana | Z59: RIAK920914MHGVVR00 | AA59: 2 | AB59: TRUE | AC59: 43207 | AD59: 43207 | AF59: 43343 | AG59: F | AH59: S | AI59: FALSE | AK59: TRUE | AL59: FALSE | AN59: Nóminas, cuentas por pagar y cobrar | AO59: Nóminas, cuentas por pagar, cuentas por cobrar. | AP59: Finanzas | AQ59: karen_rivas141@hotmail.com | AR59: 43343 | AU59: 5256782661999097 | AV59: Banamex | AW59: CH | AX59: 0 | AY59: 0.0 | AZ59: M | BA59: 1 | BB59: 403.79 | BC59: 2 | BD59: FALSE | BF59: 43346 | BG59: M | BJ59: 1118231966 | BK59: 1219123517738 | BM59: 10 | BN59: 7751353092 | BO59: 5 | BP59: N | BT59: Tepeapulco | BW59: FALSE | BY59: FALSE | CD59: =+Table1[[#This Row],[Nombres]]&" "&Table1[[#This Row],[Ap_paterno]]&" "&Table1[[#This Row],[Ap_materno]] -> Karen Rivas Avila - Baja 1
A60: 1577 | B60: Gutierrez | C60: Gonzalez | D60: Gabriela | E60: 28421 | F60: Hidalgo | G60: GUGG771023MJ9 | H60: Cedro No 12 | I60: Fraccionamiento del Bosque | J60: Cd. Sahagun | K60: Hidalgo | L60: 43994 | M60: México | N60: Ingeniería en Sistemas Computacionales | O60: TRUE | Q60: A | S60: Administrativo | T60: 5515324383 | W60: 43202 | X60: 1311770089-1 | Y60: Mexicana | Z60: GUGG771023MHGTNB05 | AA60: 2 | AB60: TRUE | AC60: 43202 | AD60: 43202 | AF60: 43280 | AG60: F | AH60: U | AI60: FALSE | AK60: TRUE | AL60: FALSE | AN60: Computacion, Logistica, Ventas y atencion a clientes | AO60: Computacion, Logistica, Ventas y atencion a clientes | AP60: Facturación, conocimientos basicos de contabilidad | AQ60: gagugo2310@gmail.com | AR60: 43280 | AU60: 5256782662002594 | AV60: Banamex | AW60: G | AX60: 30 | AY60: 24.0 | AZ60: G | BA60: 1 | BB60: 423 | BC60: 2 | BD60: FALSE | BF60: 43315 | BG60: M | BJ60: 1525125906 | BK60: 1224005921621 | BM60: 10 | BN60: 7711213868 | BO60: 5 | BP60: N | BT60: Tepeapulco | BW60: FALSE | BY60: FALSE | CD60: =+Table1[[#This Row],[Nombres]]&" "&Table1[[#This Row],[Ap_paterno]]&" "&Table1[[#This Row],[Ap_materno]] -> Gabriela Gutierrez Gonzalez
A61: 1576 | B61: Hernandez | C61: Cortes | D61: Juan Pablo | E61: 29704 | F61: México | G61: HECJ810428AA6 | H61: Rio papaloapan MZ 2 Lt 9 | I61: Portezuelos | J61: Chimalhuacan | K61: México | L61: 56337 | M61: México | O61: TRUE | Q61: O | S61: Operativo | T61: 7755936122 | U61: 00000504 | V61: 000000 | W61: 43192 | X61: 4298811618-4 | Y61: Mexicana | Z61: HECJ810428HMCRRN13 | AA61: 1 | AB61: TRUE | AC61: 43192 | AD61: 43192 | AF61: 43623 | AG61: M | AH61: C | AI61: FALSE | AK61: TRUE | AL61: TRUE | AN61: Manejo | AO61: Manejo de enganchados | AP61: Manejo | AQ61: juanphc@outlook.com | AR61: 43623 | AU61: 5256782897986496 | AV61: Banamex | AW61: 40 | AX61: 36 | AY61: 0.0 | BA61: 1 | BB61: 442.57 | BC61: 2 | BD61: FALSE | BF61: 43878 | BG61: M | BJ61: 1206050716031 | BK61: 0000123134065 | BM61: 10 | BN61: 7757718043 | BO61: 1 | BP61: N | BR61: TRUE | BT61: Nezahualcoyotl | BW61: FALSE | BY61: FALSE | CD61: =+Table1[[#This Row],[Nombres]]&" "&Table1[[#This Row],[Ap_paterno]]&" "&Table1[[#This Row],[Ap_materno]] -> Juan Pablo Hernandez Cortes
A62: 1575 | B62: Trejo | C62: Maqueda | D62: Jose de Jesus | E62: 34751 | F62: Tamaulipas | G62: TEMJ950221DG2 | H62: Lucha de clases No 1308 A | I62: Croc | J62: Monterrey | K62: Nuevo Leon | L62: 64200 | M62: México | N62: Técnico en Desarrollo de Negocios | O62: TRUE | Q62: A | S62: Administrativo | T62: 8121561880 | U62: 0000503 0000002 | V62: 000000000 | W62: 43185 | X62: 4313959963-3 | Y62: Mexicana | Z62: TEMJ950221HTSRQS08 | AA62: 2 | AB62: TRUE | AC62: 43185 | AD62: 43185 | AF62: 43225 | AG62: M | AH62: S | AI62: FALSE | AK62: TRUE | AL62: TRUE | AN62: Ventas | AO62: Ventas, RH, Facturacion y cobranza | AP62: Rastre | AQ62: jose_tre_95@hotmail.com | AR62: 43225 | AU62: 5256782652033799 | AV62: Banamex | AW62: 30 | AX62: 28 | AY62: 26.0 | AZ62: CH | BA62: 1 | BB62: 423 | BC62: 2 | BD62: FALSE | BF62: 43535 | BG62: M | BJ62: 1440133108609 | BK62: 132807260134 | BM62: 10 | BO62: 4 | BP62: N | BT62: Aldama | BW62: FALSE | BY62: FALSE | CD62: =+Table1[[#This Row],[Nombres]]&" "&Table1[[#This Row],[Ap_paterno]]&" "&Table1[[#This Row],[Ap_materno]] -> Jose de Jesus Trejo Maqueda
A63: 1573 | B63: De Jesus | C63: Maldonado | D63: Aaron | E63: 35928 | F63: Hidalgo | G63: JEMA990513140 | H63: Av. Guadalupe No 6 | I63: La Rosa el Susto | J63: Singuilucan | K63: Hidalgo | L63: 43790 | M63: México | O63: FALSE | Q63: O | S63: Operativo | T63: 7751562974 | U63: 0000503 0000002 | V63: 0000000000 | W63: 43172 | X63: 3413992169-5 | Y63: Mexicana | Z63: JEMA990513HHGSLR09 | AA63: 1 | AB63: TRUE | AC63: 43172 | AD63: 43172 | AF63: 43291 | AG63: M | AH63: U | AI63: FALSE | AK63: TRUE | AL63: TRUE | AN63: Manejo | AO63: Manejo de quinta rueda | AP63: Manejo | AQ63: aarondejesusmaldonado@gmail.com | AR63: 43291 | AU63: 5256782626908795 | AV63: Banamex | AW63: 36 | AX63: 36 | AY63: 28.0 | AZ63: G | BA63: 1 | BB63: 327.75 | BC63: 2 | BD63: FALSE | BF63: 43315 | BG63: M | BJ63: 1601181701 | BK63: 1123118094325 | BM63: 10 | BN63: 5518808066 | BO63: 2 | BP63: N | BT63: Tulancingo de Bravo | BW63: FALSE | BY63: FALSE | CD63: =+Table1[[#This Row],[Nombres]]&" "&Table1[[#This Row],[Ap_paterno]]&" "&Table1[[#This Row],[Ap_materno]] -> Aaron De Jesus Maldonado
A64: 1610 | B64: Hernandez | C64: Hernandez | D64: Victor Manuel | E64: 30501 | F64: Durango | G64: HEHV8307042U4 | H64: 10 Norte 1234 | I64: Villas de Carrizalejo | J64: Cienega de Flores | K64: Nuevo Leon | L64: 66062 | M64: México | O64: TRUE | Q64: O | S64: Operativo | T64: 8115868105 | U64: 00000504 | V64: 0000000 | W64: 43300 | X64: 3103830352-0 | Y64: Mexicana | Z64: HEHV830704HDGRRC09 | AA64: 1 | AB64: TRUE | AC64: 43300 | AD64: 43300 | AF64: 43899 | AG64: M | AH64: S | AI64: FALSE | AK64: TRUE | AL64: TRUE | AM64: PRACTICANTE ICET | AN64: Manejo | AO64: Chofer de pipa, caballerango | AP64: Manejo | AQ64: vichernandez0407@gmail.com | AR64: 43899 | AU64: 5256782721137894 | AV64: Banamex | AW64: 34 | AX64: 34 | AY64: 0.0 | BA64: 1 | BB64: 130.48 | BC64: 4 | BD64: FALSE | BF64: 43913 | BG64: M | BJ64: 0401102575014 | BK64: 0510040301710 | BM64: 10 | BO64: 2 | BP64: N | BR64: FALSE | BT64: Durango | BW64: FALSE | BY64: FALSE | CD64: =+Table1[[#This Row],[Nombres]]&" "&Table1[[#This Row],[Ap_paterno]]&" "&Table1[[#This Row],[Ap_materno]] -> Victor Manuel Hernandez Hernandez
A65: 1612 | B65: Guzman | C65: Diaz | D65: Ruben | E65: 35203 | F65: Campeche | G65: GUDR9605188V0 | H65: 8 Norte No 211 | I65: Villas del carrizalejo | J65: Cienega de Flores | K65: Nuevo Leon | L65: 65573 | M65: México | O65: TRUE | Q65: O | S65: Operativo | U65: 00000504 | W65: 43302 | X65: 5814962954-3 | Y65: Mexicana | Z65: GUDR960518HCCZZB07 | AA65: 1 | AB65: TRUE | AC65: 43302 | AD65: 43302 | AF65: 43512 | AG65: M | AH65: C | AI65: FALSE | AK65: TRUE | AL65: TRUE | AM65: PRACTICANTE ICET | AN65: Manejo | AP65: Manejo | AQ65: montejoeli@gmail.com | AR65: 43512 | AS65: 58149629543 | AU65: 5256782762354697 | AV65: Banamex | AW65: 32 | AX65: 32 | AY65: 27.0 | AZ65: M | BA65: 1 | BB65: 349.17 | BC65: 4 | BD65: FALSE | BF65: 43516 | BG65: M | BJ65: 1652186270 | BK65: 1859099826775 | BM65: 10 | BN65: 8121121480 | BO65: 2 | BP65: N | BT65: Campeche | BW65: FALSE | BY65: FALSE | CD65: =+Table1[[#This Row],[Nombres]]&" "&Table1[[#This Row],[Ap_paterno]]&" "&Table1[[#This Row],[Ap_materno]] -> Ruben Guzman Diaz
A66: 1621 | B66: Villegas | C66: Martinez | D66: Juan Carlos | E66: 29629 | F66: Hidalgo | G66: VIMJ810212LV2 | H66: Priv 67 San Moises 527 LT 14 | I66: Priv de San Fernando 42184 | J66: Pachuca | K66: Hidalgo | L66: 42184 | M66: México | O66: TRUE | Q66: O | S66: Operativo | T66: 7712319817 | U66: 00000504 | V66: 000000000 | W66: 43311 | X66: 13038102474 | Y66: Mexicana | Z66: VIMJ810212HHGLRN09 | AA66: 1 | AB66: TRUE | AC66: 43311 | AD66: 43311 | AF66: 43740 | AG66: M | AH66: U | AI66: FALSE | AK66: TRUE | AL66: FALSE | AN66: Conductor de Autobuses | AO66: Manejo | AP66: Conductor de Autobuses | AQ66: juancharly32@gmail.com | AR66: 43740 | AU66: 5256782767813697 | AV66: Banamex | AW66: 42 | AX66: 36 | AY66: 0.0 | BA66: 1 | BB66: 350.77 | BC66: 4 | BD66: FALSE | BF66: 43747 | BG66: M | BJ66: 1175100027 | BK66: 0740071585786 | BM66: 10 | BO66: 2 | BP66: N | BR66: FALSE | BT66: Pachuca de Soto | BW66: FALSE | BY66: FALSE | CD66: =+Table1[[#This Row],[Nombres]]&" "&Table1[[#This Row],[Ap_paterno]]&" "&Table1[[#This Row],[Ap_materno]] -> Juan Carlos Villegas Martinez
A67: 1628 | B67: Martinez | C67: Hernandez | D67: Alejandro | E67: 26862 | F67: México | G67: MAHA7307176B7 | H67: Retorno 27 de Tempestad Mza 27 Lt 30 | I67: San Jeronimo Cuatro Vientos | J67: Mexico | K67: Estado de Mexico | L67: 56589 | M67: México | O67: TRUE | Q67: O | S67: Operativo | T67: 7757537326 | V67: 000000000 | W67: 43321 | X67: 3989731028-8 | Y67: Mexicana | Z67: MAHA730717HDFRRL03 | AA67: 1 | AB67: TRUE | AC67: 43321 | AD67: 43321 | AF67: 43342 | AG67: M | AH67: U | AI67: FALSE | AK67: TRUE | AL67: TRUE | AN67: Manejo | AO67: Manejo de camiones | AP67: Manejo | AQ67: a.martinez7301@gmail.com | AR67: 43342 | AS67: 0908098141 | AU67: 5256782754447491 | AV67: Banamex | AW67: 42 | AX67: 36 | AY67: 26.0 | AZ67: XXG | BA67: 1 | BB67: 92.5 | BC67: 0 | BD67: FALSE | BF67: 43348 | BG67: M | BJ67: 6164042794219 | BM67: 10 | BO67: 2 | BP67: N | BT67: Acolman | BW67: FALSE | BY67: FALSE | CD67: =+Table1[[#This Row],[Nombres]]&" "&Table1[[#This Row],[Ap_paterno]]&" "&Table1[[#This Row],[Ap_materno]] -> Alejandro Martinez Hernandez
A68: 1630 | B68: Muñoz | C68: Ruiz | D68: Lizbeth | E68: 33321 | F68: Hidalgo | G68: MURL910324A70 | H68: Josefa Ortiz de Dominguez 18 | I68: Del Trabajo | J68: Tepeapulco | K68: Hidalgo | L68: 43976 | M68: México | N68: Licenciatura en Contabilidad | O68: TRUE | Q68: A | S68: Administrativo | T68: 7751441459 | U68: 00000504 | W68: 43334 | X68: 1313910650-7 | Y68: Mexicana | Z68: MURL910324MHGXZZ03 | AA68: 2 | AB68: TRUE | AC68: 43334 | AD68: 43334 | AF68: 43854 | AG68: F | AH68: S | AI68: FALSE | AK68: TRUE | AL68: FALSE | AN68: Contabilidad | AO68: Contabilidad | AP68: Contabilidad | AQ68: liz.m.ruiz.18@outlook.com | AR68: 43854 | AU68: 5256782995394593 | AV68: Banamex | AW68: CH | AX68: 0 | AY68: 0.0 | BA68: 1 | BB68: 424.78 | BC68: 4 | BD68: FALSE | BF68: 43859 | BG68: M | BJ68: 1197119161664 | BK68: 1197119161664 | BM68: 10 | BN68: 7751042939 | BO68: 5 | BP68: N | BR68: FALSE | BT68: Tepeapulco | BW68: FALSE | BY68: FALSE | CD68: =+Table1[[#This Row],[Nombres]]&" "&Table1[[#This Row],[Ap_paterno]]&" "&Table1[[#This Row],[Ap_materno]] -> Lizbeth Muñoz Ruiz
A69: 1631 | B69: Mejia | C69: Curiel | D69: David | E69: 24244 | F69: Hidalgo | G69: MEDC660517GUA | H69: Av. de los Arboles L.2 | I69: Priv. de los arboles II | J69: Mineral de la reforma | K69: Hidalgo | L69: 42185 | M69: México | O69: TRUE | Q69: O | S69: Operativo | T69: 7712447483 | U69: 00000504 | V69: 000000000 | W69: 43335 | X69: 1391660904-6 | Y69: Mexicana | Z69: MEDC660517HHGJRV05 | AA69: 1 | AB69: TRUE | AC69: 43335 | AD69: 43335 | AF69: 43887 | AG69: M | AH69: C | AI69: FALSE | AK69: TRUE | AL69: FALSE | AN69: Manejo | AO69: Manejo de Autobus y Trailer | AP69: Manejo | AQ69: d.1631tusa@gmail.com | AR69: 43887 | AU69: 5256782787925794 | AV69: Banamex | AW69: 44 | AX69: 36 | AY69: 0.0 | BA69: 1 | BB69: 433.21 | BC69: 4 | BD69: FALSE | BF69: 43892 | BG69: M | BJ69: 1757653394 | BK69: 1760053862815 | BM69: 10 | BO69: 1 | BP69: N | BR69: FALSE | BT69: Tulancingo de Bravo | BW69: FALSE | BY69: FALSE | CD69: =+Table1[[#This Row],[Nombres]]&" "&Table1[[#This Row],[Ap_paterno]]&" "&Table1[[#This Row],[Ap_materno]] -> David Mejia Curiel
A70: 1633 | B70: Cervantes | C70: Pacheco - Baja 1 | D70: Daniel | E70: 32799 | F70: México | G70: CEPD891018H51 | H70: Cristina Pacheco Pza 1 Mz B Lt 1 | I70: Barrio I | J70: Ecatepec | K70: México | L70: 55067 | M70: México | N70: Bachillerato | O70: TRUE | Q70: O | S70: Operativo | T70: 5585054217 | U70: 00000504 | V70: C-9583705 | W70: 43335 | X70: 9407893054-5 | Y70: Mexicana | Z70: CEPD891018HMCRCN03 | AA70: 1 | AB70: TRUE | AC70: 43335 | AD70: 43335 | AF70: 43451 | AG70: M | AH70: C | AI70: FALSE | AK70: TRUE | AL70: TRUE | AN70: Manejo | AO70: Chofer vendedor y entregador preventa | AP70: Manejo | AQ70: d.1633tusa@gmail.com | AR70: 43451 | AU70: 5256782796964396 | AV70: Banamex | AW70: 40 | AX70: 36 | AY70: 27.0 | AZ70: G | BA70: 1 | BB70: 237.26 | BC70: 0 | BD70: FALSE | BF70: 43475 | BG70: M | BJ70: 1430624491 | BK70: 1741079154406 | BM70: 10 | BN70: 5576697975 | BT70: Ecatepec de Morelos | BW70: FALSE | BY70: FALSE | CD70: =+Table1[[#This Row],[Nombres]]&" "&Table1[[#This Row],[Ap_paterno]]&" "&Table1[[#This Row],[Ap_materno]] -> Daniel Cervantes Pacheco - Baja 1
A71: 1634 | B71: Martinez | C71: Hernandez -BAJA- | D71: Isael | E71: 29704 | F71: México | G71: MAHI810428L83 | H71: Melchor Ocampo8 | I71: Av Hidalgo y Lerdo de Tejada | J71: Hidalgo | K71: Hidalgo | L71: 42190 | M71: Mexico | N71: Sin Especialidad | O71: FALSE | Q71: O | S71: Operativo | T71: 7717469567 | U71: 00000504 | V71: 000000000 | W71: 43335 | X71: 1300810261-1 | Y71: Mexicana | Z71: MAHI810428HDFRRS05 | AA71: 1 | AB71: TRUE | AC71: 43335 | AD71: 43335 | AF71: 43465 | AG71: M | AH71: U | AI71: FALSE | AK71: TRUE | AL71: FALSE | AM71: PROGRAMA REFERIDOS- POR JUAN JOSE PERALTA | AN71: Manejo | AO71: Manejo de Autobuses | AP71: Manejo | AQ71: i.1634tusa@gmail.com | AR71: 43467 | AU71: 5256782791786893 | AV71: Banamex | AW71: 40 | AX71: 0 | AY71: 0.0 | BA71: 1 | BB71: 330.6 | BC71: 4 | BD71: FALSE | BF71: 43872 | BG71: M | BJ71: 1620071625140 | BK71: 0000119862250 | BM71: 10 | BN71: 7751583960 | BO71: 3 | BP71: N | BR71: FALSE | BT71: Ecatepec de Morelos | BW71: FALSE | BY71: FALSE | CD71: =+Table1[[#This Row],[Nombres]]&" "&Table1[[#This Row],[Ap_paterno]]&" "&Table1[[#This Row],[Ap_materno]] -> Isael Martinez Hernandez -BAJA-
A72: 1637 | B72: Resendiz | C72: Aguilar | D72: Fernando | E72: 27284 | F72: México | G72: REAF740912L30 | H72: 2da cda de nuestra Sra del Rocio 9 C | I72: La guadalupana | J72: Huehuetoca | K72: México | L72: 54680 | M72: México | N72: Secundaria | O72: TRUE | Q72: O | S72: Operativo | T72: 5582882073 | U72: 00000504 | V72: 000000000 | W72: 43349 | X72: 4591744586-3 | Y72: Mexicana | Z72: REAF740912HDFSGR06 | AA72: 1 | AB72: TRUE | AC72: 43349 | AD72: 43349 | AF72: 43428 | AG72: M | AH72: C | AI72: FALSE | AK72: TRUE | AL72: TRUE | AN72: Manejo | AO72: Manejo | AP72: Manejo | AQ72: resendizferr2228@gmail.com | AR72: 43428 | AU72: 5256782817226098 | AV72: Banamex | AW72: 40 | AX72: 34 | AY72: 27.0 | AZ72: G | BA72: 1 | BB72: 328.09 | BC72: 4 | BD72: FALSE | BF72: 43437 | BG72: M | BJ72: 1699752177 | BK72: 1956086993836 | BM72: 10 | BN72: 5515881034 | BT72: Ecatepec de Morelos | BW72: FALSE | BY72: FALSE | CD72: =+Table1[[#This Row],[Nombres]]&" "&Table1[[#This Row],[Ap_paterno]]&" "&Table1[[#This Row],[Ap_materno]] -> Fernando Resendiz Aguilar
A73: 475 | B73: Serna | C73: Lopez | D73: Noe Benjamin | E73: 25787 | F73: Hidalgo | G73: SELN700807QF9 | H73: Narcizo Mendoza Nº 18 | I73: Tepetates | J73: Tepatates | K73: Hidalgo | L73: 43990 | M73: Mexico | N73: Sin Especialidad | O73: TRUE | Q73: O | R73: Operativa | S73: Operativa | T73: 7919134192 | U73: NS03688701 | V73: B-7590610 | W73: 38254 | X73: 96987002654 | Y73: Mexicana | Z73: SELN700807HHGRPX03 | AA73: 1 | AB73: FALSE | AC73: 37609 | AD73: 37613 | AF73: 38323 | AG73: M | AH73: C | AI73: FALSE | AK73: FALSE | AL73: FALSE | AN73: Manejo de Todo Tipo de Unidades | AO73: Manejo | AP73: Mecanica | AR73: 38323 | AU73: 1252810980 | AV73: Bancomer | AW73: 38 | AX73: 34 | AY73: 28.0 | AZ73: 40 | BA73: 1 | BB73: 0 | BC73: 0 | BD73: FALSE | BF73: 42276 | BG73: M | BM73: 2 | BO73: 3 | BP73: N | BT73: Tepeapulco | BW73: FALSE | BY73: FALSE | CD73: =+Table1[[#This Row],[Nombres]]&" "&Table1[[#This Row],[Ap_paterno]]&" "&Table1[[#This Row],[Ap_materno]] -> Noe Benjamin Serna Lopez
A74: 474 | B74: Nieva | C74: Islas | D74: Jose Francisco Baja | E74: 29313 | F74: Hidalgo | G74: NIIF800402S53 | H74: A.V. 18 de Marzo Nº 34 | I74: Av. 18 de Marzo | J74: Tepeapulco | K74: Hidalgo | L74: 43973 | M74: Mexico | O74: TRUE | Q74: O | R74: Operativa | S74: Trafico | T74: 7919131692 | U74: NS03688701 | W74: 38254 | X74: 11008003409 | Y74: Mexicana | AA74: 1 | AB74: FALSE | AC74: 39731 | AD74: 39731 | AF74: 39778 | AG74: M | AH74: C | AI74: FALSE | AK74: FALSE | AL74: FALSE | AM74: A. 19/12/2002 B 23/12/2002 A 10/10/2008 B26/11/2008 | AN74: Manejo de Todo Tipo de Unidades | AO74: Manejo | AP74: Mecanica | AR74: 39778 | AU74: 2641090895 | AV74: Bancomer | AW74: 38 | AX74: 36 | AY74: 28.0 | AZ74: 40 | BA74: 1 | BB74: 0 | BC74: 0 | BD74: FALSE | BE74: 7711278185 | BF74: 41398 | BG74: M | BH74: 2641115405 | BM74: 2 | BO74: 2 | BP74: N | BT74: Tepeapulco | BW74: FALSE | BY74: FALSE | CD74: =+Table1[[#This Row],[Nombres]]&" "&Table1[[#This Row],[Ap_paterno]]&" "&Table1[[#This Row],[Ap_materno]] -> Jose Francisco Baja Nieva Islas
A75: 471 | B75: Delgadillo | C75: Navarrete | D75: Dario | E75: 24022 | G75: DEND6507106H0 | H75: Domicilio conocido San Miguel Atepoxco | I75: San Miguel Atepoxco | J75: San Miguel Atepoxco | K75: México | L75: 55970 | M75: Mexico | O75: TRUE | Q75: O | R75: Operativa | S75: Trafico | T75: 5513033465 | U75: NS03688701 | V75: C-2475649 | W75: 38254 | X75: 37-98-65-0101-5 | Y75: Mexicana | Z75: DEND651007HMCLVR02 | AA75: 1 | AB75: TRUE | AC75: 37596 | AD75: 37600 | AF75: 40008 | AG75: M | AH75: C | AI75: FALSE | AK75: FALSE | AL75: TRUE | AN75: Manejo de Todo Tipo de Unidades | AO75: Manejo | AP75: Mecanica | AR75: 40008 | AU75: 1252094894 | AV75: Bancomer | AW75: 40 | AX75: 34 | AY75: 28.0 | AZ75: 40 | BA75: 1 | BB75: 240 | BC75: 3 | BD75: FALSE | BE75: 8115388367 | BF75: 40008 | BG75: M | BH75: 1440557854 | BM75: 2 | BO75: 2 | BP75: N | BW75: FALSE | BY75: FALSE | CD75: =+Table1[[#This Row],[Nombres]]&" "&Table1[[#This Row],[Ap_paterno]]&" "&Table1[[#This Row],[Ap_materno]] -> Dario Delgadillo Navarrete
A76: 469 | B76: Martinez | C76: Rodriguez | D76: Fernando | E76: 27946 | F76: México | G76: MARF760705TV8 | H76: Calle rio Mextlalpan norte Nº 1 | I76: Pblo. Santa Maria | J76: Acolman | K76: México | L76: 55870 | M76: Mexico | N76: Sin Especialidad | O76: FALSE | Q76: O | R76: Operativa | S76: Operativa | U76: NS03688701 | V76: B-107117 | W76: 38254 | X76: 94997601987 | Y76: Mexicana | Z76: MARF760705HMCRDR05 | AA76: 1 | AB76: FALSE | AC76: 37578 | AD76: 37579 | AF76: 38565 | AG76: M | AH76: C | AI76: FALSE | AK76: FALSE | AL76: FALSE | AN76: Manejo de Todo Tipo de Unidades | AO76: Manejo | AP76: Mecanica | AR76: 38565 | AU76: 1213042014 | AV76: Bancomer | AW76: 38 | AX76: 34 | AY76: 26.5 | AZ76: 38 | BA76: 1 | BB76: 0 | BC76: 0 | BD76: FALSE | BF76: 42276 | BG76: M | BM76: 2 | BO76: 3 | BP76: N | BT76: Ecatepec de Morelos | BW76: FALSE | BY76: FALSE | CD76: =+Table1[[#This Row],[Nombres]]&" "&Table1[[#This Row],[Ap_paterno]]&" "&Table1[[#This Row],[Ap_materno]] -> Fernando Martinez Rodriguez
A77: 467 | B77: Mendez | C77: Aguirre | D77: Carlos | E77: 27702 | F77: México | G77: MEAC751104238 | H77: Calle Hidalgo Nº 15 | I77: San Lorenzo | J77: San Lorenzo Tlalminolpan | K77: México | L77: 55800 | M77: Mexico | O77: TRUE | Q77: O | R77: Operativa | S77: Operativa | T77: 5949561836 | U77: NS03688701 | V77: C-6485659 | W77: 38254 | X77: 13-02-75-0486-2 | Y77: Mexicana | Z77: MEAC751104HMCNGR09 | AA77: 1 | AB77: TRUE | AC77: 37530 | AD77: 37530 | AF77: 39125 | AG77: M | AH77: C | AI77: FALSE | AK77: FALSE | AL77: TRUE | AN77: Manejo de Todo Tipo de Unidades | AO77: Manejo | AP77: Mecanica | AR77: 39125 | AU77: 1224630726 | AV77: Bancomer | AW77: 40 | AX77: 34 | AY77: 26.0 | AZ77: 44 | BA77: 1 | BB77: 193 | BC77: 3 | BD77: FALSE | BF77: 42278 | BG77: M | BH77: 1456087191 | BM77: 2 | BO77: 2 | BP77: N | BT77: San Martin de las Piramides | BW77: FALSE | BY77: FALSE | CD77: =+Table1[[#This Row],[Nombres]]&" "&Table1[[#This Row],[Ap_paterno]]&" "&Table1[[#This Row],[Ap_materno]] -> Carlos Mendez Aguirre
A78: 459 | B78: Valdez | C78: Sanchez | D78: Arturo | E78: 28942 | F78: México | G78: VASA790328QH0 | H78: Av. Tlajinga Nº 4 | I78: Del valle | J78: San Juan Teotihuacan | K78: México | L78: 55800 | M78: Mexico | O78: TRUE | Q78: O | R78: Operativa | S78: Trafico | T78: 5526623959 | U78: NS03688701 | V78: C-2693990 | W78: 38254 | X78: 94-95-79-0460-3 | Y78: Mexicana | Z78: VASA790328HMCLNR07 | AA78: 1 | AB78: TRUE | AC78: 37460 | AD78: 37468 | AF78: 39163 | AG78: M | AH78: C | AI78: FALSE | AK78: FALSE | AL78: TRUE | AN78: Manejo de Todo Tipo de Unidades | AO78: Manejo | AP78: Mecanica | AR78: 39163 | AU78: 1219457542 | AV78: Bancomer | AW78: 42 | AX78: 34 | AY78: 28.5 | AZ78: 44 | BA78: 1 | BB78: 183 | BC78: 3 | BD78: FALSE | BF78: 39889 | BG78: M | BH78: 1436182097 | BM78: 2 | BO78: 2 | BP78: N | BT78: Sin Especificar | BW78: FALSE | BY78: FALSE | CD78: =+Table1[[#This Row],[Nombres]]&" "&Table1[[#This Row],[Ap_paterno]]&" "&Table1[[#This Row],[Ap_materno]] -> Arturo Valdez Sanchez
A79: 458 | B79: Maldonado | C79: Mendoza | D79: Ricardo | E79: 28960 | F79: Nuevo León | G79: MAMR790415VA4 | H79: Maria Greever Nº 202 | I79: Los Robles | J79: Monterrey | K79: Nuevo Leon | L79: 66636 | M79: Mexico | N79: Ingeniería Civil | O79: FALSE | Q79: A | R79: Administrativa | S79: Trafico | T79: 8183145949 | U79: NS03688701 | W79: 38254 | X79: 03-97-79-5850-7 | Y79: Mexicana | Z79: MAMR790415HNLLNC02 | AA79: 2 | AB79: FALSE | AC79: 38051 | AD79: 38064 | AF79: 39307 | AG79: M | AH79: S | AI79: FALSE | AK79: FALSE | AL79: TRUE | AM79: 883 | AN79: Computacion | AO79: Trafico | AP79: Computacion | AQ79: richardmm17@hotmail.com | AR79: 39307 | AU79: 1218768307 | AV79: Bancomer | AW79: 40 | AX79: 36 | AY79: 27.0 | AZ79: 42 | BA79: 1 | BB79: 230 | BC79: 3 | BD79: FALSE | BF79: 39721 | BG79: M | BM79: 2 | BO79: 5 | BP79: N | BT79: Monterrey | BW79: FALSE | BY79: FALSE | CD79: =+Table1[[#This Row],[Nombres]]&" "&Table1[[#This Row],[Ap_paterno]]&" "&Table1[[#This Row],[Ap_materno]] -> Ricardo Maldonado Mendoza
A80: 445 | B80: Vega | C80: Fragoso | D80: Rogelio | E80: 19253 | F80: México | G80: VEFR520916KV1 | H80: Av. Hidalgo S/N | I80: Cuahutemoc | J80: Axapusco | K80: México | L80: 55940 | M80: Mexico | O80: TRUE | Q80: O | R80: Operativa | S80: Operativa | U80: NS03688701 | V80: B-7803635 | W80: 38254 | X80: 01-73-52-6478-8 | Y80: Mexicana | Z80: VEFR520916HMCGRG05 | AA80: 1 | AB80: TRUE | AC80: 37228 | AD80: 37229 | AF80: 39011 | AG80: M | AH80: C | AI80: FALSE | AK80: FALSE | AL80: FALSE | AN80: Manejo de Todo Tipo de Unidades | AO80: Manejo | AP80: Mecanica | AR80: 39011 | AS80: 1303036890 | AU80: 1233843556 | AV80: Bancomer | AW80: 38 | AX80: 36 | AY80: 28.0 | AZ80: 42 | BA80: 1 | BB80: 0 | BC80: 3 | BD80: FALSE | BF80: 42277 | BG80: M | BM80: 2 | BO80: 1 | BP80: N | BT80: Otumba | BW80: FALSE | BY80: FALSE | CD80: =+Table1[[#This Row],[Nombres]]&" "&Table1[[#This Row],[Ap_paterno]]&" "&Table1[[#This Row],[Ap_materno]] -> Rogelio Vega Fragoso
A81: 443 | B81: Reyes | C81: Sarabia | D81: Miguel Angel | E81: 25486 | F81: México | G81: RESM691010SSA | H81: Av. San Francisco Nº 15 | I81: San Francisco Mazapa | J81: San Francisco Mazapa | K81: México | L81: 55830 | M81: Mexico | O81: TRUE | Q81: O | R81: Operativa | S81: Trafico | T81: 5949582725 | U81: NS03688701 | V81: B-6327704 | W81: 38254 | X81: 94-92-69-0647-3 | Y81: Mexicana | Z81: RESM691010HMCYRG04 | AA81: 1 | AB81: TRUE | AC81: 37222 | AD81: 37222 | AF81: 39931 | AG81: M | AH81: C | AI81: FALSE | AK81: FALSE | AL81: FALSE | AN81: Manejo de Todo Tipo de Unidades | AO81: Manejo | AP81: Mecanica | AR81: 39931 | AU81: 1278515867 | AV81: Bancomer | AW81: 40 | AX81: 34 | AY81: 27.0 | AZ81: 42 | BA81: 1 | BB81: 316 | BC81: 3 | BD81: FALSE | BF81: 39931 | BG81: M | BH81: 1440555355 | BI81: 7711896874 | BM81: 2 | BO81: 2 | BP81: N | BT81: Sin Especificar | BW81: FALSE | BY81: FALSE | CD81: =+Table1[[#This Row],[Nombres]]&" "&Table1[[#This Row],[Ap_paterno]]&" "&Table1[[#This Row],[Ap_materno]] -> Miguel Angel Reyes Sarabia
A82: 441 | B82: Badillo | C82: Delgadillo | D82: Rosaura | E82: 15156 | F82: Hidalgo | G82: BADR410629SZ8 | H82: Xochiatipan Nº 46 | I82: Rojo Gomez | J82: Sahagun | K82: Hidalgo | L82: 43996 | M82: Mexico | N82: Técnico en Secretariado Ejecutivo | O82: TRUE | Q82: A | R82: Administrativa | S82: Administrativo | T82: 7919131900 | U82: 00000504 | W82: 37155 | X82: 13-64-41-1042-4 | Y82: Mexicana | Z82: BADR410629HHGDLS01 | AA82: 2 | AB82: FALSE | AC82: 35578 | AD82: 37155 | AF82: 43677 | AG82: F | AH82: C | AI82: FALSE | AK82: TRUE | AL82: FALSE | AM82: Ingreso 28/05/1997 | AN82: Secretaria | AO82: Auxiliar | AP82: Computacion | AQ82: facturacion1@trasladosuniversales.com | AR82: 37894 | AU82: 5256781408057490 | AV82: Banamex | AW82: G | AX82: 38 | AY82: 0.0 | AZ82: 36 | BA82: 0 | BB82: 328.09 | BC82: 3 | BD82: FALSE | BF82: 43713 | BG82: M | BM82: 2 | BO82: 3 | BP82: N | BR82: FALSE | BT82: Epazoyucan | BW82: FALSE | BY82: FALSE | CD82: =+Table1[[#This Row],[Nombres]]&" "&Table1[[#This Row],[Ap_paterno]]&" "&Table1[[#This Row],[Ap_materno]] -> Rosaura Badillo Delgadillo
A83: 1479 | B83: De Leon | C83: Salazar | D83: Jonathan | E83: 32159 | F83: Nuevo León | G83: LESJ880117TW6 | H83: Paseo del Huerto | I83: Infonavit Monterreal | J83: Escobedo | K83: Nuevo Leon | L83: 66056 | M83: México | O83: TRUE | Q83: O | S83: Operativo | U83: 0000503 0000002 | V83: 0000000000 | W83: 42808 | X83: 4305886979-3 | Y83: Mexicana | Z83: LESJ880117HNLNLN04 | AA83: 1 | AB83: TRUE | AC83: 42808 | AD83: 42808 | AF83: 43260 | AG83: M | AH83: C | AI83: FALSE | AK83: TRUE | AL83: FALSE | AN83: Manejo | AO83: Ventas | AP83: Mecanica | AQ83: jonathan.011788@hotmail.com | AR83: 43260 | AU83: 5256782269980291 | AV83: Banamex | AW83: 40 | AX83: 38 | AY83: 8.0 | AZ83: 40 | BA83: 1 | BB83: 509.8 | BC83: 2 | BD83: FALSE | BF83: 43267 | BG83: M | BJ83: 0467074639141 | BK83: 1298946595 | BM83: 10 | BO83: 2 | BP83: N | BT83: Monterrey | BW83: FALSE | BY83: FALSE | CD83: =+Table1[[#This Row],[Nombres]]&" "&Table1[[#This Row],[Ap_paterno]]&" "&Table1[[#This Row],[Ap_materno]] -> Jonathan De Leon Salazar
A84: 1371 | B84: Lazcano | C84: Rodriguez | D84: Andres Mario | E84: 34640 | F84: Nuevo León | G84: LARA941102HNL | H84: Mariano Matamoros 302 | I84: Centro | J84: Hidalgo | K84: Nuevo Leon | L84: 65610 | M84: México | N84: Sin Especialidad | O84: FALSE | Q84: A | S84: Administrativa | X84: 47-12-94-6867-5 | Y84: Mexicana | Z84: LARA941102HNLZDN01 | AA84: 2 | AB84: FALSE | AC84: 42398 | AD84: 42398 | AF84: 42552 | AG84: M | AH84: S | AI84: FALSE | AK84: TRUE | AL84: FALSE | AN84: Manejo de unidades | AO84: Liberacion de unidades | AP84: Liberacion de unidades | AR84: 42552 | AU84: 5256781871873290 | AV84: Banamex | AW84: 0 | AX84: 0 | AY84: 0.0 | AZ84: 0 | BA84: 1 | BB84: 369.81 | BC84: 0 | BD84: FALSE | BF84: 42612 | BG84: M | BJ84: 0814132046528 | BK84: 1219122602662 | BM84: 10 | BO84: 3 | BP84: N | BT84: Monterrey | BW84: FALSE | BY84: FALSE | CD84: =+Table1[[#This Row],[Nombres]]&" "&Table1[[#This Row],[Ap_paterno]]&" "&Table1[[#This Row],[Ap_materno]] -> Andres Mario Lazcano Rodriguez
A85: 1370 | B85: López | C85: Hernández | D85: Ignacio | E85: 31444 | F85: Hidalgo | G85: LOHI860201FB1 | H85: And Melchor Ocampo 23 | I85: Independencia | J85: Cd.Sahagun | K85: Hidalgo | L85: 43994 | M85: México | N85: Ingeniería Industrial | O85: TRUE | P85: 8001964 | Q85: A | S85: Administrativa | X85: 1305861241-0 | Y85: Mexicana | Z85: LOHI860201HHGPRG03 | AA85: 2 | AB85: FALSE | AC85: 42397 | AD85: 42397 | AF85: 42478 | AG85: M | AH85: C | AI85: FALSE | AK85: TRUE | AL85: FALSE | AN85: Trafico | AO85: Trafico | AP85: Trafico | AR85: 42476 | AU85: 5256781873681394 | AV85: Banamex | AW85: 34 | AX85: 34 | AY85: 27.0 | AZ85: 38 | BA85: 1 | BB85: 387.67 | BC85: 2 | BD85: FALSE | BF85: 42496 | BG85: M | BJ85: 1223097736268 | BK85: 0413070103579 | BM85: 10 | BO85: 5 | BP85: N | BT85: Tepeapulco | BW85: FALSE | BY85: FALSE | CD85: =+Table1[[#This Row],[Nombres]]&" "&Table1[[#This Row],[Ap_paterno]]&" "&Table1[[#This Row],[Ap_materno]] -> Ignacio López Hernández
A86: 1350 | B86: Cruz | C86: Damian | D86: Roberto Manuel | E86: 33356 | F86: Hidalgo | G86: CUDR910428I9A | H86: Benito Juarez 1 | I86: Santa Clara | J86: Emiliano Zapata | K86: Hidalgo | L86: 43961 | M86: México | N86: Licenciatura en Contabilidad | O86: TRUE | Q86: A | S86: Administrativo | U86: 0000501-0000001 | W86: 42278 | X86: 13-10-91-4001-5 | Y86: Mexicana | Z86: CUDR910428HHGRMB02 | AA86: 2 | AB86: TRUE | AC86: 42284 | AD86: 42284 | AF86: 42529 | AG86: M | AH86: S | AI86: FALSE | AK86: TRUE | AL86: FALSE | AN86: Contabilidad | AO86: Contabilidad | AP86: Contabilidad | AR86: 42529 | AU86: 5256781753314694 | AV86: Banamex | AW86: 30 | AX86: 32 | AY86: 6.0 | AZ86: 34 | BA86: 1 | BB86: 304.41 | BC86: 2 | BD86: FALSE | BF86: 42549 | BG86: M | BJ86: CRDMRB9104281 | BK86: IDMEX12843244 | BM86: 10 | BO86: 5 | BP86: N | BT86: Apan | BW86: FALSE | BY86: FALSE | CD86: =+Table1[[#This Row],[Nombres]]&" "&Table1[[#This Row],[Ap_paterno]]&" "&Table1[[#This Row],[Ap_materno]] -> Roberto Manuel Cruz Damian
A87: 1107 | B87: Alonso | C87: Gonzalez | D87: Norma Berenice Asuncion | E87: 30909 | F87: San Luis Potosí | G87: AOGN840815 | H87: Tonala 319 | I87: Fraccionamiento San Isidro | J87: Apodaca | K87: Nuevo Leon | L87: 66646 | M87: Mexico | O87: TRUE | Q87: O | R87: Operativa | S87: Operativa | T87: 0444881154297 | U87: NS03688701 | W87: 41081 | X87: 14-11-84-0542-3 | Y87: Mexicana | Z87: AOGN8410815MSPLNR01 | AA87: 1 | AB87: TRUE | AC87: 41081 | AD87: 41081 | AF87: 41177 | AG87: F | AH87: C | AI87: FALSE | AK87: TRUE | AL87: TRUE | AM87: Practicante enviado por ICET | AN87: Manejo de | AO87: Manejo | AP87: Manejo | AR87: 41177 | AU87: 5177126458589990 | AV87: Banamex | AW87: G | AX87: 38 | AY87: 6.0 | AZ87: 40 | BA87: 0 | BB87: 0 | BC87: 0 | BD87: FALSE | BE87: 7711896862 | BF87: 41193 | BG87: M | BM87: 10 | BO87: 2 | BP87: N | BT87: Tamuin | BW87: FALSE | BY87: FALSE | CD87: =+Table1[[#This Row],[Nombres]]&" "&Table1[[#This Row],[Ap_paterno]]&" "&Table1[[#This Row],[Ap_materno]] -> Norma Berenice Asuncion Alonso Gonzalez
A88: 1106 | B88: Vargas | C88: Hernandez | D88: Sergio | E88: 25284 | F88: Hidalgo | G88: VAHS690322 | H88: Rancheria San Vicente | I88: Rancheria San Vicente | J88: Tlanalapa | K88: Hidalgo | L88: 43930 | M88: Mexico | O88: FALSE | Q88: A | R88: Administrativa | S88: Administrativa | U88: NS03688701 | W88: 41078 | X88: 13-94-69-1607-2 | Y88: Mexicana | Z88: VAHS690322HHGRRR08 | AA88: 2 | AB88: FALSE | AC88: 41078 | AD88: 41078 | AF88: 41253 | AG88: M | AH88: C | AI88: FALSE | AK88: FALSE | AL88: FALSE | AN88: Mantenimiento de instalaciones y vigilancia en la noche | AP88: Vigilancia | AR88: 41253 | AU88: 5256780882333690 | AV88: Banamex | AW88: 40 | AX88: 36 | AY88: 6.0 | AZ88: 40 | BA88: 1 | BB88: 194.05 | BC88: 0 | BD88: FALSE | BF88: 42279 | BG88: M | BM88: 10 | BT88: Cuautepec de Hinojosa | BW88: FALSE | BY88: FALSE | CD88: =+Table1[[#This Row],[Nombres]]&" "&Table1[[#This Row],[Ap_paterno]]&" "&Table1[[#This Row],[Ap_materno]] -> Sergio Vargas Hernandez
A89: 1333 | B89: Flores | C89: Leos | D89: Luis Fernando | E89: 32367 | F89: Nuevo León | G89: FOLL8808129Y2 | H89: Francisco I Madero 512 | I89: Ampliacion Lazaro Cardenas | J89: Escobedo | K89: Nuevo Leon | L89: 66050 | M89: Mexico | N89: Sin Especialidad | O89: TRUE | Q89: A | S89: Administrativo | T89: 8110364223 | U89: 004-0000384386-00 | W89: 42168 | X89: 43048801609 | Y89: Mexicana | Z89: FOLL880812HNLLSS01 | AA89: 2 | AB89: FALSE | AC89: 42168 | AD89: 42168 | AE89: 42736 | AF89: 44676 | AG89: M | AH89: S | AI89: FALSE | AK89: TRUE | AL89: TRUE | AN89: Facturacion | AO89: Logistica | AP89: Administrativo | AQ89: lflores.Navistar@outlook.com | AR89: 44676 | AS89: 1911624158 | AU89: 5256786086591090 | AV89: Banamex | AW89: 38 | AX89: 32 | AY89: 0.0 | BA89: 1 | BB89: 476.43 | BC89: 2 | BD89: FALSE | BE89: 8119106393 | BF89: 44677 | BG89: M | BJ89: 0458108442424 | BK89: 0719032101069 | BM89: 10 | BO89: 3 | BP89: N | BR89: FALSE | BS89: 8127711202 | BT89: Monterrey | BW89: FALSE | BY89: FALSE | CD89: =+Table1[[#This Row],[Nombres]]&" "&Table1[[#This Row],[Ap_paterno]]&" "&Table1[[#This Row],[Ap_materno]] -> Luis Fernando Flores Leos
A90: 1368 | B90: Redonda | C90: Martinez | D90: Jose Manuel | E90: 33389 | F90: México | G90: REMM910513IA6 | H90: Morelos Sin Numero | I90: Palomar Maquixco | J90: Teotihuacan | K90: Estado de México | L90: 55800 | M90: México | O90: TRUE | Q90: O | S90: Operativa | T90: 5539381789 | X90: 94-09-91-4871-3 | Y90: Mexicana | Z90: REMM910531HMCDRN05 | AA90: 1 | AB90: FALSE | AC90: 42406 | AD90: 42406 | AF90: 42552 | AG90: M | AH90: U | AI90: FALSE | AK90: TRUE | AL90: FALSE | AN90: Manejo Todo tIpo de Unidades | AO90: Manejo | AP90: Mecanica | AR90: 42552 | AU90: 5256781889702390 | AV90: Banamex | AW90: 38 | AX90: 36 | AY90: 29.0 | AZ90: 36 | BA90: 1 | BB90: 328.38 | BC90: 4 | BD90: FALSE | BF90: 42627 | BG90: M | BJ90: 1112591958454 | BK90: 0118711439910 | BM90: 10 | BO90: 2 | BP90: N | BT90: Sin Especificar | BW90: FALSE | BY90: FALSE | CD90: =+Table1[[#This Row],[Nombres]]&" "&Table1[[#This Row],[Ap_paterno]]&" "&Table1[[#This Row],[Ap_materno]] -> Jose Manuel Redonda Martinez
A91: 1369 | B91: Garcia | C91: Caballero | D91: Juan Carlos | E91: 30149 | F91: México | G91: GACJ820717IP5 | H91: Edif 2 Dpt 006 | I91: U Hab San Pablo 2 | J91: Tultitlan | K91: Estado de México | L91: 54930 | M91: México | O91: TRUE | Q91: O | S91: Operacion | T91: 5517043064 | X91: 20-00-82-2724-9 | Y91: Mexicana | Z91: GACJ820717HDFRBN07 | AA91: 1 | AB91: FALSE | AC91: 42406 | AD91: 42406 | AF91: 42585 | AG91: M | AH91: U | AI91: FALSE | AK91: TRUE | AL91: FALSE | AN91: Manejo Todo Tipo de Unidades | AO91: Operacion | AP91: Mecanica | AQ91: namirgarcialimon@gmail.com | AR91: 42608 | AU91: 5256781873624295 | AV91: Banamex | AW91: 30 | AX91: 32 | AY91: 27.0 | AZ91: 0 | BA91: 1 | BB91: 332.85 | BC91: 3 | BD91: FALSE | BF91: 42712 | BG91: M | BJ91: 5619089124349 | BK91: 0000135004918 | BM91: 10 | BO91: 2 | BP91: N | BT91: Aculco | BW91: FALSE | BY91: FALSE | CD91: =+Table1[[#This Row],[Nombres]]&" "&Table1[[#This Row],[Ap_paterno]]&" "&Table1[[#This Row],[Ap_materno]] -> Juan Carlos Garcia Caballero
A92: 1105 | B92: Mendoza | C92: Zamora | D92: Pedro | E92: 29517 | F92: Hidalgo | G92: MEZP8010232TA | H92: 18 de Julio No. 10 | I92: Guadalupe | J92: Apan | K92: Hidalgo | L92: 43909 | M92: Mexico | N92: Licenciatura en Contabilidad | O92: TRUE | P92: 6403269 | Q92: A | R92: Administrativa | S92: Administrativa | T92: 7489126750 | U92: NS03688701 | W92: 41059 | X92: 13-02-80-0232-0 | Y92: Mexicana | Z92: MEZP801023HHGNMD06 | AA92: 2 | AB92: TRUE | AC92: 41059 | AD92: 41095 | AF92: 41121 | AG92: M | AH92: S | AI92: FALSE | AK92: TRUE | AL92: TRUE | AN92: Auxiliar de Contabilidad | AO92: Administracion | AP92: contabilidad | AQ92: mendozazamora_pedro@hotmail.com | AR92: 41128 | AU92: 5256780883705599 | AV92: Banamex | AW92: 36 | AX92: 32 | AY92: 27.0 | AZ92: 38 | BA92: 1 | BB92: 211.75 | BC92: 2 | BD92: FALSE | BF92: 42278 | BG92: M | BM92: 10 | BO92: 5 | BP92: N | BT92: Apan | BW92: FALSE | BY92: FALSE | CD92: =+Table1[[#This Row],[Nombres]]&" "&Table1[[#This Row],[Ap_paterno]]&" "&Table1[[#This Row],[Ap_materno]] -> Pedro Mendoza Zamora
A93: 1104 | B93: Torres | C93: Sanchez | D93: Aldo | E93: 34257 | F93: Nuevo León | G93: TOSA9310155U8 | H93: Circuito los Molinos 314 | I93: Exhacienda Santa Rosa | J93: Apodaca | K93: Nuevo Leon | L93: 66610 | M93: Mexico | N93: Técnico en Desarrollo de Negocios | O93: TRUE | Q93: A | R93: Administrativa | S93: Administrativa | T93: 81485336 | U93: NS03688701 | V93: 2265394 | W93: 41057 | X93: 43-12-93-4822-3 | Y93: Mexicana | Z93: TOSA931015HNLRNL01 | AA93: 2 | AB93: TRUE | AC93: 41057 | AD93: 41057 | AF93: 41815 | AG93: M | AH93: S | AI93: FALSE | AK93: TRUE | AL93: FALSE | AN93: Practicas profesionales | AO93: Atencion a clientes | AP93: Mercadotecnia | AQ93: aldoocioon@gmail.com | AR93: 41821 | AU93: 5256781038571498 | AV93: Banamex | AW93: 36 | AX93: 32 | AY93: 28.0 | AZ93: 38 | BA93: 1 | BB93: 340.29 | BC93: 2 | BD93: FALSE | BF93: 43621 | BG93: M | BM93: 10 | BO93: 4 | BP93: N | BT93: Galeana | BW93: FALSE | BY93: FALSE | CD93: =+Table1[[#This Row],[Nombres]]&" "&Table1[[#This Row],[Ap_paterno]]&" "&Table1[[#This Row],[Ap_materno]] -> Aldo Torres Sanchez
A94: 1103 | B94: Atanacio | C94: Maldonado | D94: Andres | E94: 18597 | F94: Hidalgo | H94: Lote 25 Manzana 12 | I94: Palmillas | J94: Sahagun | K94: Hidalgo | L94: 43999 | M94: Mexico | O94: FALSE | Q94: A | R94: Administrativa | S94: Administrativa | U94: NS03688701 | W94: 41044 | X94: 13-74-50-0469-0 | Y94: Mexicana | Z94: AAMA501130HHGTLN01 | AA94: 2 | AB94: TRUE | AC94: 41044 | AD94: 41044 | AF94: 41464 | AG94: M | AH94: C | AI94: FALSE | AK94: FALSE | AL94: FALSE | AN94: Vigilar las instalaciones | AO94: Vigilancia | AP94: Manejo de personal | AR94: 41464 | AU94: 5256780690088395 | AV94: Banamex | AW94: 34 | AX94: 34 | AY94: 7.0 | AZ94: 34 | BA94: 1 | BB94: 72.2 | BC94: 0 | BD94: FALSE | BF94: 42278 | BG94: M | BM94: 10 | BO94: 1 | BP94: N | BT94: Cuautepec de Hinojosa | BW94: FALSE | BY94: FALSE | CD94: =+Table1[[#This Row],[Nombres]]&" "&Table1[[#This Row],[Ap_paterno]]&" "&Table1[[#This Row],[Ap_materno]] -> Andres Atanacio Maldonado
A95: 1102 | B95: Najera | C95: Tapia | D95: Jahaziel | E95: 31337 | F95: Coahuila | G95: NATJ851017NZ0 | H95: Primera Internacional N° 47 | I95: Ampliacion Lazaro Cardenas | J95: Torreon | K95: Cohauila | L95: 27390 | M95: Mexico | O95: TRUE | Q95: O | R95: Operativa | S95: Operativa | T95: 8717814226 | U95: NS03688701 | W95: 41045 | X95: 32-04-85-2264-6 | Y95: Mexicana | Z95: NATJ851017HCLJPH03 | AA95: 1 | AB95: FALSE | AC95: 41044 | AD95: 41045 | AF95: 41183 | AG95: M | AH95: C | AI95: FALSE | AK95: TRUE | AL95: TRUE | AM95: Se contrata con licencia estatal se hace el compromiso de que obtenga la licencia federal en 6 meses | AN95: Manejo de todo tipo de unidades | AO95: Mecanica | AP95: Mecanica | AQ95: jahaziel.nat@gmail | AR95: 41212 | AU95: 5256780690088395 | AV95: Banamex | AW95: 44 | AX95: 44 | AY95: 28.5 | AZ95: 46 | BA95: 1 | BB95: 0 | BC95: 0 | BD95: FALSE | BE95: 8115397269 | BF95: 41394 | BG95: M | BM95: 10 | BO95: 2 | BP95: N | BW95: FALSE | BY95: FALSE | CD95: =+Table1[[#This Row],[Nombres]]&" "&Table1[[#This Row],[Ap_paterno]]&" "&Table1[[#This Row],[Ap_materno]] -> Jahaziel Najera Tapia
A96: 1101 | B96: Sanchez | C96: Gutierrez | D96: Juan Raymundo | E96: 31776 | F96: Hidalgo | G96: SAGJ861230 | H96: Av. Puebla 66 | I96: Benito Juarez | J96: Cd. Sahagun | K96: Hidalgo | L96: 43994 | M96: Mexico | N96: Ingeniería Industrial | O96: TRUE | P96: 6837144 | Q96: A | R96: Administrativa | S96: Administrativa | T96: 017919135614 | U96: NS03688701 | W96: 41029 | X96: 13-10-86-1322-8 | Y96: Mexicana | Z96: SAGJ861230HHGNTN08 | AA96: 2 | AB96: TRUE | AC96: 41029 | AD96: 41029 | AF96: 41050 | AG96: M | AH96: S | AI96: FALSE | AK96: TRUE | AL96: TRUE | AN96: Asignacion de Traslados | AO96: Manejo de personal | AP96: Manejo de personal | AR96: 41057 | AU96: 5256780318854798 | AV96: Banamex | AW96: 40 | AX96: 38 | AY96: 8.0 | AZ96: 40 | BA96: 1 | BB96: 257.61 | BC96: 0 | BD96: FALSE | BF96: 42278 | BG96: M | BM96: 10 | BO96: 5 | BP96: N | BT96: Tepeapulco | BW96: FALSE | BY96: FALSE | CD96: =+Table1[[#This Row],[Nombres]]&" "&Table1[[#This Row],[Ap_paterno]]&" "&Table1[[#This Row],[Ap_materno]] -> Juan Raymundo Sanchez Gutierrez
A97: 1099 | B97: Hernandez | C97: Islas | D97: Roberto baja | E97: 23609 | F97: Hidalgo | G97: HEIR640820EM3 | H97: Emiliano Zapata 3A | I97: Centro | J97: Emiliano Zapata | K97: Hidalgo | L97: 43960 | M97: Mexico | O97: TRUE | Q97: O | R97: Operativa | S97: Operativa | T97: 017489150423 | U97: NS03688701 | V97: B-2791409 | W97: 41024 | X97: 13-85-64-0139-6 | Y97: Mexicana | Z97: HEIR640820HHGRSB04 | AA97: 1 | AB97: TRUE | AC97: 41024 | AD97: 41024 | AF97: 41387 | AG97: M | AH97: C | AI97: FALSE | AK97: TRUE | AL97: TRUE | AN97: Manejo de unidades | AO97: Manejo | AP97: Manejo | AR97: 41387 | AU97: 5256780816740192 | AV97: Banamex | AW97: 0 | AX97: 0 | AY97: 26.0 | AZ97: 0 | BA97: 1 | BB97: 169.58 | BC97: 1 | BD97: FALSE | BE97: 7711895527 | BF97: 41397 | BG97: M | BL97: Se retira con renuncia voluntaria, debido a un traslado que no realizo y se tuvo la queja del cliente. sin adeundo alguno | BM97: 10 | BO97: 2 | BP97: N | BT97: Emiliano Zapata | BW97: FALSE | BY97: FALSE | CD97: =+Table1[[#This Row],[Nombres]]&" "&Table1[[#This Row],[Ap_paterno]]&" "&Table1[[#This Row],[Ap_materno]] -> Roberto baja Hernandez Islas
A98: 1098 | B98: Perez | C98: Coronel | D98: Miguel Gorgonio BAJA | E98: 25820 | F98: México | G98: PECM700909729 | H98: Calle Puerto de Manzanilllo S/n | I98: Fco. I. Madero | J98: Jaltepec | K98: México | L98: 55965 | M98: Mexico | O98: TRUE | Q98: O | R98: Operativa | S98: Operativa | T98: 015929232333 | U98: NS03688701 | V98: 0439222 | W98: 40982 | X98: 62-89-70-2054-1 | Y98: Mexicana | Z98: PECM700909HMCRRG02 | AA98: 1 | AB98: TRUE | AC98: 40982 | AD98: 40982 | AF98: 41144 | AG98: M | AH98: C | AI98: FALSE | AK98: TRUE | AL98: TRUE | AM98: numero particular adicional 0455522749094 | AN98: Manejo de unidades | AO98: Manejo | AP98: Manejo | AR98: 41193 | AU98: 5256780766876590 | AV98: Banamex | AW98: 38 | AX98: 38 | AY98: 0.0 | AZ98: 38 | BA98: 1 | BB98: 70 | BC98: 0 | BD98: FALSE | BF98: 44314 | BG98: M | BM98: 10 | BO98: 1 | BP98: N | BR98: FALSE | BT98: Sin Especificar | BW98: FALSE | BY98: FALSE | CD98: =+Table1[[#This Row],[Nombres]]&" "&Table1[[#This Row],[Ap_paterno]]&" "&Table1[[#This Row],[Ap_materno]] -> Miguel Gorgonio BAJA Perez Coronel
A99: 1097 | B99: Flores | C99: Montalvo | D99: Jose Luis | E99: 29837 | F99: México | H99: Calz de los Prirules Mza 7 Lt 19 | I99: Morelos | J99: Cd. Sahagun | K99: Hidalgo | L99: 43999 | M99: Mexico | O99: TRUE | Q99: O | R99: Operativa | S99: Operativa | T99: 9153787 | U99: NS03688701 | V99: 4958140 | W99: 40976 | X99: 12-00-81-4700-6 | Y99: Mexicana | Z99: FOML810908HDFLNS01 | AA99: 1 | AB99: TRUE | AC99: 40976 | AD99: 40976 | AF99: 41239 | AG99: M | AH99: C | AI99: FALSE | AK99: TRUE | AL99: TRUE | AM99: Numero anterior 8115388360 | AN99: Manejo de unidades | AO99: Manejo | AP99: Manejo | AR99: 41240 | AU99: 5256786016967998 | AV99: Banamex | AW99: 34 | AX99: 34 | AY99: 29.0 | AZ99: 34 | BA99: 1 | BB99: 70 | BC99: 0 | BD99: FALSE | BE99: 7711278191 | BF99: 41394 | BG99: M | BL99: NUMERO DE CUENTA BANCARIA ANTERIOR 5256780766879594 Se da de baja al operador porque se tuvo reporte de la gasolinera, indicando que el operador vendio $200 de diesel y no los cargo a la unidad que llevaba. | BM99: 10 | BO99: 1 | BP99: N | BT99: Acolman | BW99: FALSE | BY99: FALSE | CD99: =+Table1[[#This Row],[Nombres]]&" "&Table1[[#This Row],[Ap_paterno]]&" "&Table1[[#This Row],[Ap_materno]] -> Jose Luis Flores Montalvo
A100: 1096 | B100: Correa | C100: Robles | D100: Gonzalo | E100: 24911 | F100: Hidalgo | G100: CORG6803142B2 | H100: 30 de Abril 53 | I100: San Antonio el Desmonte | J100: Pachuca | K100: Hidalgo | L100: 42111 | M100: mexico | N100: Técnico Mecánico de Diésel | O100: TRUE | Q100: O | R100: Operativa | S100: Operativa | T100: 7712112953 | U100: 0000501-0000002 | W100: 40976 | X100: 01-92-68-1143-9 | Y100: Mexicana | Z100: CORG680314HHGRBN00 | AA100: 1 | AB100: TRUE | AC100: 40976 | AD100: 40976 | AF100: 42314 | AG100: M | AH100: C | AI100: FALSE | AK100: TRUE | AL100: TRUE | AM100: Numero Anterior 7712406093 | AN100: Manejo de unidades | AO100: Manejo | AP100: Mecanica | AR100: 42314 | AU100: 5256781543389691 | AV100: Banamex | AW100: 40 | AX100: 36 | AY100: 8.0 | AZ100: 42 | BA100: 1 | BB100: 281.4 | BC100: 4 | BD100: FALSE | BF100: 42418 | BG100: M | BJ100: 095046882647 | BK100: 0000095244195 | BL100: NUMERO DE CUENTA BANCARIA ANTERIOR 5256780239092098 | BM100: 10 | BO100: 3 | BP100: N | BT100: Pachuca de Soto | BW100: FALSE | BY100: FALSE | CD100: =+Table1[[#This Row],[Nombres]]&" "&Table1[[#This Row],[Ap_paterno]]&" "&Table1[[#This Row],[Ap_materno]] -> Gonzalo Correa Robles
...

Sheet TUSA
A1: Id_matricula | B1: Ap_paterno | C1: Ap_materno | D1: Nombres | E1: Id_empresa | F1: Fecha_nacimto | G1: Lugar_nacimto | H1: Reg_fed_causantes | I1: Direccion | J1: Colonia | K1: Ciudad | L1: Estado | M1: Codigo_postal | N1: Pais | O1: Escolaridad | P1: Especialidad | Q1: Estado_estudios | R1: Puesto | S1: Area | T1: Telefono | U1: Id_no_poliza | V1: Tipo_nomina | W1: Fecha_ingreso_poliza | X1: No_IMSS | Y1: Nacionalidad | Z1: No_CURP | AA1: Id_empleado | AB1: Contrato_eventual | AC1: Fecha_ingreso | AD1: Fecha_alta_IMSS | AE1: Fecha_planta | AF1: Fecha_de_baja | AG1: Sexo | AH1: Estado_civil | AI1: Pension_alimenticia | AJ1: No_oficio | AK1: Disp_para_viajar | AL1: Disp_cambio_residencia | AM1: Observaciones | AN1: Habilidades_especificas | AO1: Areas_de_experiencia | AP1: Areas_de_interes | AQ1: Correo_electronico | AR1: Fecha_baja_IMSS | AS1: No_credito_infonavit | AT1: No_credito_fonacot | AU1: No_cta_bancaria | AV1: Institucion_bancaria | AW1: Camisa | AX1: Pantalon | AY1: Zapatos | AZ1: Chamarra | BA1: Playera | BB1: Sueldo_promedio | BC1: Contacto | BD1: No_cred_elector | BE1: Folio_cred_elector | BF1: No_celular | BG1: No_adicional | BH1: Tipo_sangre | BI1: Fecha_captura | BJ1: Movto | BK1: Nombre completo
A2: 5009 | B2: de Mexico | C2: S.A. de C.V. | D2: Autocamiones | E2: 0 | H2: AME050824259 | I2: Av. Fray Marcos de Niza 3486 Sur | J2: San Rafael | K2: Culianacan | L2: Sinaloa | M2: 80150 | N2: Mexico | Q2: Truncado | R2: Operativo | S2: Operativa | U2: 004-0000384386-00 | V2: Indefinido | Y2: Mexicana | Z2: AME050824259 | AA2: 1 | AB2: FALSE | AC2: 41953 | AI2: FALSE | AK2: FALSE | AL2: FALSE | AW2: 0 | AX2: 0 | AY2: 0 | AZ2: 0 | BB2: 0 | BC2: FALSE | BI2: 41955 | BJ2: A | BK2: =+Table13[[#This Row],[Nombres]]&" "&Table13[[#This Row],[Ap_paterno]]&" "&Table13[[#This Row],[Ap_materno]] -> Autocamiones de Mexico S.A. de C.V.
A3: 5008 | B3: Planta | C3: Sanchez | D3: International | E3: 1 | F3: 31172 | G3: México | I3: Ejercito Nacional 904 8 piso Col. | J3: Las Palmas | K3: Mexico | L3: México | M3: 11560 | N3: Mexico | P3: Tecnico Programador | Q3: Truncado | R3: Operativo | S3: Operativa | U3: NS03688701 | V3: Indefinido | W3: 38477 | Y3: Mexicana | AA3: 1 | AB3: TRUE | AC3: 38477 | AD3: 38477 | AF3: 38718 | AG3: F | AH3: C | AI3: FALSE | AK3: TRUE | AL3: TRUE | AN3: Armador | AO3: Sistemas | AP3: Relaciones Humanas | AR3: 38718 | AV3: Bancomer | AW3: 0 | AX3: 0 | AY3: 0 | AZ3: 0 | BB3: 0 | BC3: FALSE | BI3: 42276 | BJ3: M | BK3: =+Table13[[#This Row],[Nombres]]&" "&Table13[[#This Row],[Ap_paterno]]&" "&Table13[[#This Row],[Ap_materno]] -> International Planta Sanchez
A4: 5007 | B4: Universales | D4: Traslados | E4: 1 | F4: 31172 | G4: Hidalgo | I4: Carr. Sahagun Tlanalapa | J4: Ranch. San Vicente | K4: Tlanalapa | L4: Hidalgo | M4: 43930 | N4: Mexico | P4: Preparatoria | Q4: Truncado | R4: Operativo | S4: Trafico | T4: 7711895536 | U4: 004-0000384386-00 | V4: Indefinido | W4: 38477 | Y4: Mexicana | AA4: 1 | AB4: TRUE | AC4: 38477 | AG4: M | AH4: V | AI4: TRUE | AK4: TRUE | AL4: TRUE | AM4: Enganchados Traslados | AN4: Manejo de Todo Tipo de Unidades | AO4: Manejo | AP4: Manejo de personal | AQ4: tusatrafic@prodigy.net.mx | AV4: Bancomer | AW4: 0 | AX4: 0 | AY4: 0 | AZ4: 0 | BB4: 0 | BC4: FALSE | BI4: 41416 | BJ4: M | BK4: =+Table13[[#This Row],[Nombres]]&" "&Table13[[#This Row],[Ap_paterno]]&" "&Table13[[#This Row],[Ap_materno]] -> Traslados Universales
A5: 5006 | B5: Mercantiles | C5: Suc. Guadalajara | D5: Agencias | E5: 1 | F5: 31172 | G5: Yucatán | I5: Calle 86-B No. 646, Av. Juarez | J5: Centro | K5: Merida | L5: Yucatan | M5: 97000 | N5: Mexico | P5: Tecnico Programador | Q5: Terminado | R5: Operativo | S5: Trafico | T5: 9999840292 | U5: 004-0000384386-00 | V5: Indefinido | W5: 38576 | Y5: Mexicana | AA5: 1 | AB5: FALSE | AC5: 38576 | AD5: 38576 | AG5: M | AH5: C | AI5: FALSE | AK5: TRUE | AL5: TRUE | AN5: Manejo de Todo Tipo de Unidades | AP5: Relaciones Humanas | AV5: Bancomer | BC5: FALSE | BI5: 39889 | BJ5: M | BK5: =+Table13[[#This Row],[Nombres]]&" "&Table13[[#This Row],[Ap_paterno]]&" "&Table13[[#This Row],[Ap_materno]] -> Agencias Mercantiles Suc. Guadalajara
A6: 5005 | B6: Mercantiles | C6: Suc. Cancun | D6: Agencias | E6: 1 | F6: 31172 | G6: Yucatán | I6: Calle 86-B Nº 646 AV. Juarez | J6: Centro | K6: Merida | L6: Yucatan | M6: 97000 | N6: Mexico | P6: Tecnico Analista en Sistemas Computacionales | Q6: Truncado | R6: Operativo | S6: Trafico | T6: 9999840292 | U6: 004-0000384386-00 | V6: Indefinido | W6: 38477 | Y6: Mexicana | AA6: 1 | AB6: TRUE | AC6: 38477 | AD6: 1134204 | AG6: F | AH6: V | AI6: TRUE | AK6: TRUE | AL6: TRUE | AM6: Asignadas Agencias Mercantiles | AN6: Manejo de Todo Tipo de Unidades | AO6: Sistemas | AP6: Relaciones Humanas | AV6: Bancomer | BC6: FALSE | BI6: 41703 | BJ6: M | BK6: =+Table13[[#This Row],[Nombres]]&" "&Table13[[#This Row],[Ap_paterno]]&" "&Table13[[#This Row],[Ap_materno]] -> Agencias Mercantiles Suc. Cancun
A7: 5004 | B7: Mercantiles | C7: Suc. Villahermosa | D7: Agencias | E7: 1 | F7: 31172 | G7: Yucatán | I7: Calle 86-B Nº 646 AV. Juarez | J7: Centro | K7: Merida | L7: Yucatan | M7: 97000 | N7: Mexico | P7: Tecnico Programador | Q7: Truncado | R7: Operativo | S7: Trafico | T7: 9999840292 | U7: 004-0000384386-00 | V7: Indefinido | W7: 38477 | Y7: Mexicana | AA7: 1 | AB7: TRUE | AC7: 38477 | AD7: 38477 | AG7: F | AH7: V | AI7: FALSE | AK7: TRUE | AL7: TRUE | AM7: Asignadas Agencias Mercantiles | AN7: Manejo de Todo Tipo de Unidades | AO7: Sistemas | AP7: Relaciones Humanas | AV7: Bancomer | BC7: FALSE | BI7: 39889 | BJ7: M | BK7: =+Table13[[#This Row],[Nombres]]&" "&Table13[[#This Row],[Ap_paterno]]&" "&Table13[[#This Row],[Ap_materno]] -> Agencias Mercantiles Suc. Villahermosa
A8: 5003 | B8: Mercantiles | C8: Suc. Tuxtla | D8: Agencias | E8: 1 | F8: 31172 | G8: Yucatán | I8: Calle 86-B Nº 646 AV. Juarez | J8: Centro | K8: Merida | L8: Yucatan | M8: 97000 | N8: Mexico | P8: Tecnico Programador | Q8: Truncado | R8: Operativo | S8: Trafico | T8: 9999480292 | U8: 004-0000384386-00 | V8: Indefinido | W8: 38477 | Y8: Mexicana | AA8: 1 | AB8: TRUE | AC8: 38477 | AD8: 38477 | AG8: M | AH8: V | AI8: TRUE | AK8: TRUE | AL8: TRUE | AM8: Asignadas Agencias Mercantiles | AN8: Manejo de Todo Tipo de Unidades | AO8: Sistemas | AP8: Relaciones Humanas | AV8: Bancomer | BC8: FALSE | BI8: 39891 | BJ8: M | BK8: =+Table13[[#This Row],[Nombres]]&" "&Table13[[#This Row],[Ap_paterno]]&" "&Table13[[#This Row],[Ap_materno]] -> Agencias Mercantiles Suc. Tuxtla
A9: 5002 | B9: Mercantiles | C9: Suc. Merida | D9: Agencias | E9: 1 | F9: 31172 | G9: Yucatán | I9: Calle 88-B Nº 649 AV. Juarez | J9: Centro | K9: Merida | L9: Yucatan | M9: 97000 | N9: Mexico | P9: Tecnico Programador | Q9: Truncado | R9: Operativo | S9: Trafico | T9: 9999840292 | U9: 004-0000384386-00 | V9: Indefinido | W9: 38477 | Y9: Mexicana | AA9: 1 | AB9: FALSE | AC9: 38477 | AD9: 38477 | AG9: F | AH9: V | AI9: FALSE | AK9: TRUE | AL9: TRUE | AM9: Asignadas Agencias Mercantiles | AN9: Manejo de Todo Tipo de Unidades | AO9: Manejo | AP9: Relaciones Humanas | AV9: Bancomer | BC9: FALSE | BI9: 39889 | BJ9: M | BK9: =+Table13[[#This Row],[Nombres]]&" "&Table13[[#This Row],[Ap_paterno]]&" "&Table13[[#This Row],[Ap_materno]] -> Agencias Mercantiles Suc. Merida
A10: 5001 | B10: ATM | D10: Autotransportacion Mexicana | E10: 1 | F10: 31172 | G10: Nuevo León | I10: San Bernardino 200 | J10: Residencial California | K10: Monterrey | L10: Nuevo Leon | M10: 66050 | N10: Mexico | P10: Tecnico Programador | Q10: Truncado | R10: Operativo | S10: Trafico | T10: 8183072284 | U10: 004-0000384386-00 | V10: Indefinido | W10: 38477 | Y10: Mexicana | AA10: 1 | AB10: TRUE | AC10: 38477 | AD10: 38477 | AG10: F | AH10: V | AI10: TRUE | AK10: TRUE | AL10: TRUE | AM10: Enganchados ATM | AN10: Manejo de Todo Tipo de Unidades | AO10: Sistemas | AP10: Relaciones Humanas | AQ10: atmmosa@prodigy.net.mx | AV10: Bancomer | BC10: FALSE | BI10: 39889 | BJ10: M | BK10: =+Table13[[#This Row],[Nombres]]&" "&Table13[[#This Row],[Ap_paterno]]&" "&Table13[[#This Row],[Ap_materno]] -> Autotransportacion Mexicana ATM
A11: 2390 | B11: Hernandez | C11: Angeles | D11: Wilibaldo | E11: 0 | F11: 34558 | G11: Tlaxcala | H11: HEAW940812C49 | I11: Cristobal Colon | J11: Calvario | K11: Tepeapulco | L11: Hidalgo | M11: 43976 | N11: Mexico | O11: Medio Superior | P11: Técnico en computación | Q11: Terminado | R11: Operativo | S11: Operativo | T11: 7753780353 | V11: Normal | X11: 1312941064-6 | Y11: Mexicana | Z11: HEAW940812HTLRNL00 | AA11: 1 | AB11: TRUE | AC11: 45891 | AG11: M | AH11: S | AI11: FALSE | AK11: TRUE | AL11: FALSE | AM11: mamá/ 7752354294 hermano | AQ11: w.2389atm@gmail.com | AW11: 36 | AX11: 32 | AY11: 26 | AZ11: M | BA11: M | BB11: 296.37 | BC11: FALSE | BD11: 2597801709 | BE11: 1196092703886 | BF11: 8115388290 | BH11: O+ | BI11: 45891 | BJ11: A | BK11: =+Table13[[#This Row],[Nombres]]&" "&Table13[[#This Row],[Ap_paterno]]&" "&Table13[[#This Row],[Ap_materno]] -> Wilibaldo Hernandez Angeles
A12: 2389 | B12: Hernandez | C12: Puga | D12: Gonzalo | E12: 0 | F12: 33875 | G12: Veracruz | H12: HEPG9209289XA | I12: Sauce | J12: Prado segundo sector | K12: El carmen | L12: Nuevo León | M12: 66580 | N12: Mexico | O12: Superior | P12: Comercio internacional | Q12: Terminado | R12: Administrativo | S12: Administrativo | T12: 8140690472 | V12: Normal | X12: 98119200917 | Y12: Mexicana | Z12: HEPG920928HVZRGN08 | AA12: 2 | AB12: TRUE | AC12: 45889 | AD12: 45889 | AG12: M | AH12: C | AI12: FALSE | AK12: TRUE | AL12: FALSE | AM12: Pareja/ 5527754513 Hermana | AN12: Office | AO12: Logistica | AP12: Logistica | AQ12: g.2389atm@gmail.com | AW12: 30 | AX12: 30 | AY12: 26 | AZ12: CH | BA12: CH | BB12: 642.5182 | BC12: FALSE | BD12: 2410920718 | BE12: 5916090760391 | BF12: 8119109371 | BH12: O+ | BI12: 45890 | BJ12: M | BK12: =+Table13[[#This Row],[Nombres]]&" "&Table13[[#This Row],[Ap_paterno]]&" "&Table13[[#This Row],[Ap_materno]] -> Gonzalo Hernandez Puga
A13: 2388 | B13: Padilla | C13: Alarcon | D13: Ernesto | E13: 0 | F13: 34671 | G13: Edo de México | H13: PAAE941203FQ6 | I13: Venustiano Carranza | J13: Centro | K13: Atotonilco El Grande | L13: Hidalgo | M13: 43300 | N13: Mexico | O13: Secundaria | Q13: Terminado | R13: Operativo | S13: Operativo | T13: 7711174097 | V13: Normal | X13: 1716941562-1 | Y13: Mexicana | Z13: PAAE941203HMCDLR08 | AA13: 1 | AB13: TRUE | AC13: 45884 | AD13: 45884 | AG13: M | AH13: D | AI13: FALSE | AK13: TRUE | AL13: TRUE | AM13: 5510238370 papá/ 5549328752 hermano | AQ13: e.2388atm@gmail.com | AW13: 32 | AX13: 32 | AY13: 27 | AZ13: M | BA13: CH | BB13: 296.37 | BC13: FALSE | BD13: 2634007518 | BE13: 181094826037 | BF13: 7712199092 | BH13: O+ | BI13: 45884 | BJ13: A | BK13: =+Table13[[#This Row],[Nombres]]&" "&Table13[[#This Row],[Ap_paterno]]&" "&Table13[[#This Row],[Ap_materno]] -> Ernesto Padilla Alarcon
A14: 2387 | B14: Ruiz | C14: Atanacio | D14: Juan Jose | E14: 0 | F14: 33234 | G14: Hidalgo | H14: RUAJ901227EW5 | I14: Francisco Villa Mza33 L262 | J14: Alfredo V. Bonfil | K14: Tlanalapa | L14: Hidalgo | M14: 43930 | N14: Mexico | O14: Secundaria | Q14: Terminado | R14: Operativo | S14: Operativo | T14: 5565105482 | V14: Normal | X14: 0816907783-4 | Y14: Mexicana | Z14: RUAJ901227HHGZTN01 | AA14: 1 | AB14: TRUE | AC14: 45881 | AD14: 45881 | AG14: M | AH14: U | AI14: FALSE | AK14: TRUE | AL14: TRUE | AM14: conyugue/ 7911250858 papá | AQ14: j.2387atm@gmail.com | AU14: 5.2567845e+15 | AV14: Banamex | AW14: 42 | AX14: 34 | AY14: 27 | AZ14: G | BA14: G | BB14: 296.37 | BC14: FALSE | BD14: 2753520064 | BE14: 1399097514610 | BF14: 8115388299 | BH14: A+ | BI14: 45881 | BJ14: M | BK14: =+Table13[[#This Row],[Nombres]]&" "&Table13[[#This Row],[Ap_paterno]]&" "&Table13[[#This Row],[Ap_materno]] -> Juan Jose Ruiz Atanacio
A15: 2386 | B15: Fuentes | C15: Sibaja | D15: Gabriel | E15: 0 | F15: 25629 | G15: Oaxaca | H15: FUSG700302UQ5 | I15: Francisco Mina | J15: Vicente Guerrero | K15: Comalcalco | L15: Tabasco | M15: 86350 | N15: Mexico | O15: Medio Superior | Q15: Terminado | R15: Operativo | S15: Operativo | T15: 9932473702 | V15: Normal | X15: 7887700358-8 | Y15: Mexicana | Z15: FUSG700302HOCNBB05 | AA15: 1 | AB15: TRUE | AC15: 45877 | AD15: 45877 | AG15: M | AH15: C | AI15: FALSE | AK15: TRUE | AL15: TRUE | AM15: hermano/ 9331177554 esposa fuentessibajag@gmail.com | AQ15: g.2386atm@gmail.com | AU15: 5.2567845e+15 | AV15: Banamex | AW15: 42 | AX15: 38 | AY15: 27 | AZ15: XG | BA15: XG | BB15: 296.37 | BC15: FALSE | BD15: 1609437862 | BE15: 527062954758 | BF15: 8115388351 | BH15: B+ | BI15: 45877 | BJ15: M | BK15: =+Table13[[#This Row],[Nombres]]&" "&Table13[[#This Row],[Ap_paterno]]&" "&Table13[[#This Row],[Ap_materno]] -> Gabriel Fuentes Sibaja
A16: 2385 | B16: Cruz | C16: Garcia | D16: Enrique | E16: 0 | F16: 27590 | G16: Distrito Federal | H16: CUGE7507151N4 | I16: Privada del pesebre | J16: Rancho Don Antonio IV Sección | K16: Tizayuca | L16: Hidalgo | M16: 43810 | N16: Mexico | O16: Secundaria | Q16: Terminado | R16: Operativo | S16: Operativo | T16: 3339569782 | V16: Normal | X16: 9493752034-7 | Y16: Mexicana | Z16: CUGE750715HDFRRN08 | AA16: 1 | AB16: TRUE | AC16: 45874 | AD16: 45874 | AG16: M | AH16: U | AI16: FALSE | AK16: TRUE | AL16: TRUE | AM16: esposa Zuleima/ Alondra hija 5612877646 | AQ16: e.2385atm@gmail.com | AU16: 5.2567845e+15 | AV16: Banamex | AW16: 36 | AX16: 30 | AY16: 27 | AZ16: G | BA16: M | BB16: 296.37 | BC16: FALSE | BD16: 2272104437 | BE16: 1364016102795 | BF16: 8115387702 | BH16: O+ | BI16: 45874 | BJ16: A | BK16: =+Table13[[#This Row],[Nombres]]&" "&Table13[[#This Row],[Ap_paterno]]&" "&Table13[[#This Row],[Ap_materno]] -> Enrique Cruz Garcia
A17: 2384 | B17: Garcia | C17: Tapia | D17: Fernando | E17: 0 | F17: 37392 | G17: Veracruz | H17: GATF0205163R9 | I17: Alondra M26 L | J17: Fracc. Campo de Tiro | K17: Pachuca de Soto | L17: Hidalgo | M17: 42039 | N17: Mexico | O17: Medio Superior | P17: Tecnico Agropecuario | Q17: Truncado | R17: Operativo | S17: Operativo | T17: 7711872480 | V17: Normal | X17: 1216020928-9 | Y17: Mexicana | Z17: GATF020516HVZRPRA8 | AA17: 1 | AB17: TRUE | AC17: 45870 | AD17: 45870 | AG17: M | AH17: U | AI17: FALSE | AK17: TRUE | AL17: FALSE | AM17: hermana/ mamá 5657079366 madre correo personal garciatapiafernando798@gmail.com | AQ17: f.2384atm@gmail.com | AU17: 5.5791004e+15 | AV17: Banamex | AW17: 42 | AX17: 42 | AY17: 28 | AZ17: XG | BA17: XG | BB17: 296.37 | BC17: FALSE | BD17: 2787068738 | BE17: 1875126557527 | BF17: 7712199185 | BH17: O+ | BI17: 45870 | BJ17: A | BK17: =+Table13[[#This Row],[Nombres]]&" "&Table13[[#This Row],[Ap_paterno]]&" "&Table13[[#This Row],[Ap_materno]] -> Fernando Garcia Tapia
A18: 2383 | B18: Castillo | C18: Saldaña | D18: Armando | E18: 0 | F18: 26982 | G18: Distrito Federal | H18: CASA731114K12 | I18: San Martin Caballero int 40 | J18: Lomas de San Francisco Tepojaco | K18: Cuautitlan Izcalli | L18: Hidalgo | M18: 54745 | N18: Mexico | O18: Medio Superior | P18: Económico administrativo | Q18: Truncado | R18: Operativo | S18: Operativo | T18: 5640018430 | V18: Normal | X18: 9089732372-2 | Y18: Mexicana | Z18: CASA731114HDFSLR04 | AA18: 1 | AB18: TRUE | AC18: 45870 | AD18: 45870 | AG18: M | AH18: C | AI18: FALSE | AK18: TRUE | AL18: FALSE | AM18: esposa/5524716766 papá correo arman,chory@gmail,com | AQ18: a.2383atm@gmail.com | AU18: 5.5791005e+15 | AV18: Banamex | AW18: 34 | AX18: 36 | AY18: 28 | AZ18: G | BA18: G | BB18: 296.37 | BC18: FALSE | BD18: 2583600888 | BE18: 6465002786573 | BF18: 7711896884 | BH18: O+ | BI18: 45870 | BJ18: M | BK18: =+Table13[[#This Row],[Nombres]]&" "&Table13[[#This Row],[Ap_paterno]]&" "&Table13[[#This Row],[Ap_materno]] -> Armando Castillo Saldaña
A19: 2382 | B19: Gonzalez | C19: Lopez | D19: Gregorio | E19: 0 | F19: 28570 | G19: Nuevo León | H19: GOLG780321CS3 | I19: Av. La amistad | J19: Hidalgo | K19: Sahagun | L19: Hidalgo | M19: 43975 | N19: Mexico | O19: Secundaria | Q19: Terminado | R19: Operativo | S19: Operativo | T19: 7751112153 | V19: Normal | X19: 4394783403-2 | Y19: Mexicana | Z19: GOLG780321HNLNPR01 | AA19: 1 | AB19: TRUE | AC19: 45870 | AD19: 45870 | AG19: M | AH19: U | AI19: FALSE | AK19: TRUE | AL19: TRUE | AM19: esposa/ 8131049501 hermano correo personal arelymairim@gmail.com | AQ19: g.2382atm@gmail.com | AU19: 5.2041661e+15 | AV19: Banamex | AW19: 44 | AX19: 42 | AY19: 29 | AZ19: XG | BA19: XG | BB19: 296.37 | BC19: FALSE | BD19: 1450945413 | BE19: 2148039905876 | BF19: 7711896885 | BH19: B+ | BI19: 45870 | BJ19: M | BK19: =+Table13[[#This Row],[Nombres]]&" "&Table13[[#This Row],[Ap_paterno]]&" "&Table13[[#This Row],[Ap_materno]] -> Gregorio Gonzalez Lopez
A20: 2381 | B20: Coronel | C20: Delgado | D20: Javier | E20: 0 | F20: 32239 | G20: Tlaxcala | H20: CODJ880406DQ1 | I20: Hidalgo | J20: Santa Clara | K20: Emiliano Zapata | L20: Hidalgo | M20: 43961 | N20: Mexico | O20: Medio Superior | P20: Técnico en informática | Q20: Terminado | R20: Operativo | S20: Operativo | T20: 7911107791 | V20: Normal | X20: 6107881460-7 | Y20: Mexicana | Z20: CODJ880406HTLRLV00 | AA20: 1 | AB20: TRUE | AC20: 45863 | AD20: 45863 | AG20: M | AH20: C | AI20: FALSE | AK20: TRUE | AL20: FALSE | AM20: esposa/ 2482414544 papá | AQ20: j.2381atm@gmail.com | AU20: 5.2567845e+15 | AV20: Banamex | AW20: 44 | AX20: 34 | AY20: 28 | AZ20: XG | BA20: XG | BB20: 296.37 | BC20: FALSE | BD20: 2001522633 | BE20: 1228079380002 | BF20: 7711278223 | BH20: O+ | BI20: 45863 | BJ20: A | BK20: =+Table13[[#This Row],[Nombres]]&" "&Table13[[#This Row],[Ap_paterno]]&" "&Table13[[#This Row],[Ap_materno]] -> Javier Coronel Delgado
A21: 2380 | B21: Rendon | C21: Peralta | D21: Juan | E21: 0 | F21: 29871 | G21: Distrito Federal | H21: REPJ811012PF5 | I21: Av. Cisnes Norte Esquina con privada de las gaviotas | J21: Villas de Pachuca | K21: Pachuca | L21: Hidalgo | M21: 42083 | N21: Mexico | O21: Medio Superior | Q21: Truncado | R21: Operativo | S21: Operativo | T21: 5620442744 | V21: Normal | X21: 9697811273-6 | Y21: Mexicana | Z21: REPJ811012HDFNRN09 | AA21: 1 | AB21: TRUE | AC21: 45856 | AD21: 45856 | AG21: M | AH21: U | AI21: FALSE | AK21: FALSE | AL21: FALSE | AM21: Esposa Yessica/ Hija 7714220832 America | AQ21: j.2380atm@gmail.com | AU21: 5.2567845e+15 | AV21: Banamex | AW21: 38 | AX21: 36 | AY21: 27 | AZ21: G | BA21: G | BB21: 296.37 | BC21: FALSE | BD21: 2495026071 | BE21: 916020345200 | BF21: 8119106400 | BH21: O+ | BI21: 45856 | BJ21: M | BK21: =+Table13[[#This Row],[Nombres]]&" "&Table13[[#This Row],[Ap_paterno]]&" "&Table13[[#This Row],[Ap_materno]] -> Juan Rendon Peralta
A22: 2379 | B22: Cruz | C22: Hernandez | D22: Enrique | E22: 0 | F22: 34006 | G22: Hidalgo | H22: CUHE9302061L4 | I22: Insurgentes M3 | J22: Manuel Ávila Camacho | K22: Mineral de la Reforma | L22: Hidalgo | M22: 42182 | N22: Mexico | O22: Medio Superior | Q22: Terminado | R22: Operativo | S22: Operativo | T22: 7712075434 | V22: Normal | X22: 1310931438-8 | Y22: Mexicana | Z22: CUHE930206HHGRRN02 | AA22: 1 | AB22: TRUE | AC22: 45856 | AD22: 45856 | AG22: M | AH22: U | AI22: FALSE | AK22: TRUE | AL22: TRUE | AM22: Esposa Yazmin/7711772579 Freddy tellez cuñado | AQ22: e.2379atm@gmail.com | AU22: 5.2567841e+15 | AV22: Banamex | AW22: 38 | AX22: 36 | AY22: 26 | AZ22: G | BA22: G | BB22: 296.37 | BC22: FALSE | BD22: 1514585788 | BE22: 728088630585 | BF22: 8115388374 | BH22: A+ | BI22: 45856 | BJ22: A | BK22: =+Table13[[#This Row],[Nombres]]&" "&Table13[[#This Row],[Ap_paterno]]&" "&Table13[[#This Row],[Ap_materno]] -> Enrique Cruz Hernandez
A23: 2378 | B23: Hernandez | C23: Abundiz | D23: Guillermo | E23: 0 | F23: 32714 | G23: Distrito Federal | H23: HEAG890725CK6 | I23: Camino al Valle de las monjas | J23: San Mateo Tlaltenango | K23: Cuajimalpa de Morelos | L23: Distrito Federal | M23: 5600 | N23: Mexico | O23: Medio Superior | Q23: Truncado | R23: Operativo | S23: Operativo | T23: 7207039736 | V23: Normal | W23: 45853 | X23: 37068900499 | Y23: Mexicana | Z23: HEAG890725HDFRBL01 | AA23: 1 | AB23: TRUE | AC23: 45853 | AD23: 45853 | AG23: M | AH23: S | AI23: FALSE | AK23: TRUE | AL23: TRUE | AM23: Mama/ 5580948795 Hermana | AN23: operador | AO23: operador | AP23: operador | AQ23: g.2378atm@gmail.com | AU23: 5.5791005e+15 | AV23: Banamex | AW23: 28 | AX23: 30 | AY23: 26 | AZ23: M | BA23: M | BB23: 296.37 | BC23: FALSE | BD23: 2802083469 | BE23: 810079218843 | BF23: 8115388372 | BH23: O- | BI23: 45856 | BJ23: M | BK23: =+Table13[[#This Row],[Nombres]]&" "&Table13[[#This Row],[Ap_paterno]]&" "&Table13[[#This Row],[Ap_materno]] -> Guillermo Hernandez Abundiz
A24: 2377 | B24: Medina | C24: Lechuga | D24: Rodolfo Joel | E24: 0 | F24: 29415 | G24: Distrito Federal | H24: MELR8007132K2 | I24: Privada Agave Verde Mza 1 lote 14 B | J24: Fraccionamiento los Agaves | K24: Tultitlan de Mariano Escobedo | L24: Edo de México | M24: 54926 | N24: Mexico | O24: Secundaria | Q24: Terminado | R24: Operativo | S24: Operativo | T24: 5538027252 | V24: Normal | W24: 45853 | X24: 94988032994 | Y24: Mexicana | Z24: MELR800713HDFDCD05 | AA24: 1 | AB24: TRUE | AC24: 45853 | AD24: 45853 | AF24: 45860 | AG24: M | AH24: U | AI24: FALSE | AK24: FALSE | AL24: FALSE | AM24: Conocido/ 5569821381 Esposa | AN24: Manejo | AO24: Operador | AP24: Operador | AQ24: r.2377atm@gmail.com | AR24: 45860 | AW24: 48 | AX24: 42 | AY24: 27 | AZ24: XXG | BA24: XXG | BB24: 296.37 | BC24: FALSE | BD24: 1803845267 | BE24: 5591026382486 | BH24: O+ | BI24: 45861 | BJ24: M | BK24: =+Table13[[#This Row],[Nombres]]&" "&Table13[[#This Row],[Ap_paterno]]&" "&Table13[[#This Row],[Ap_materno]] -> Rodolfo Joel Medina Lechuga
A25: 2376 | B25: Velazquez | C25: Cadena | D25: Eduardo | E25: 0 | F25: 29323 | G25: Edo de México | H25: VECE8004122U1 | I25: Francisco Villa | J25: Ampliacion los Reyes la Paz | K25: La Paz | L25: Edo de México | M25: 56400 | N25: Mexico | O25: Secundaria | Q25: Terminado | R25: Operativo | S25: Operativo | T25: 5535929405 | V25: Normal | W25: 45853 | X25: 96028009007 | Y25: Mexicana | Z25: VECE800412HMCLDD02 | AA25: 1 | AB25: TRUE | AC25: 45853 | AD25: 45853 | AG25: M | AH25: U | AI25: FALSE | AK25: FALSE | AL25: FALSE | AM25: Mama/ 5558538524 Hermana | AN25: Manejo | AO25: Operador | AP25: Operador | AQ25: e.2376atm@gmail.com | AU25: 5.2567845e+15 | AV25: Banamex | AW25: 28 | AX25: 32 | AY25: 25 | AZ25: CH | BA25: CH | BB25: 296.37 | BC25: FALSE | BD25: 1858923301 | BE25: 3998035057183 | BF25: 7711278231 | BH25: O+ | BI25: 45853 | BJ25: A | BK25: =+Table13[[#This Row],[Nombres]]&" "&Table13[[#This Row],[Ap_paterno]]&" "&Table13[[#This Row],[Ap_materno]] -> Eduardo Velazquez Cadena
A26: 2375 | B26: Cruz | C26: Espinoza | D26: Emmanuel | E26: 0 | F26: 33814 | G26: Hidalgo | H26: CUEE920729FB4 | I26: 16 de septiembre | J26: Xala | K26: Axapusco | L26: Hidalgo | M26: 55963 | N26: Mexico | O26: Secundaria | Q26: Terminado | R26: Operativo | S26: Operativo | T26: 5534890259 | V26: Normal | X26: 4414922045-9 | Y26: Mexicana | Z26: CUEE920729HHGRSM00 | AA26: 1 | AB26: TRUE | AC26: 45842 | AD26: 45842 | AF26: 45867 | AG26: M | AH26: U | AI26: FALSE | AK26: TRUE | AL26: TRUE | AM26: Karen esposa/7911100613 papa Eulalio Cruz | AQ26: e.2375atm@gmail.com | AR26: 45867 | AU26: 5.2041662e+15 | AV26: Banamex | AW26: 40 | AX26: 34 | AY26: 28 | AZ26: G | BA26: G | BB26: 296.37 | BC26: FALSE | BD26: 2058251162 | BE26: 482086757462 | BH26: O+ | BI26: 45874 | BJ26: M | BK26: =+Table13[[#This Row],[Nombres]]&" "&Table13[[#This Row],[Ap_paterno]]&" "&Table13[[#This Row],[Ap_materno]] -> Emmanuel Cruz Espinoza
A27: 2374 | B27: Garcia | C27: Ramirez | D27: German | E27: 0 | F27: 33821 | G27: Tlaxcala | H27: GARG920805R43 | I27: emilio Sanchez Piedras | J27: Las Vigas | K27: Tlaxcala | L27: Tlaxcala | M27: 90250 | N27: Mexico | O27: Secundaria | Q27: Terminado | R27: Operativo | S27: Operativo | T27: 2219957132 | V27: Normal | X27: 9412921613-4 | Y27: Mexicana | Z27: GARG920805HTLRMR05 | AA27: 1 | AB27: TRUE | AC27: 45835 | AD27: 45835 | AG27: M | AH27: U | AI27: FALSE | AK27: TRUE | AL27: FALSE | AM27: esposa/ 2219957587 mamá | AQ27: g.2374atm@gmail.com | AU27: 5.2567844e+15 | AV27: Banamex | AW27: 36 | AX27: 32 | AY27: 27 | AZ27: M | BA27: M | BB27: 296.37 | BC27: FALSE | BD27: 2728518784 | BE27: 480087552057 | BF27: 7711995166 | BH27: O+ | BI27: 45835 | BJ27: A | BK27: =+Table13[[#This Row],[Nombres]]&" "&Table13[[#This Row],[Ap_paterno]]&" "&Table13[[#This Row],[Ap_materno]] -> German Garcia Ramirez
A28: 2373 | B28: Lopez | C28: Ortiz | D28: Anahi Daniela | E28: 0 | F28: 35167 | G28: Edo de México | H28: LOOA960412FY3 | I28: Jose Maria Morelos lote 14 Mza 22 | J28: Palmillas | K28: CD Sahagun | L28: Hidalgo | M28: 43998 | N28: Mexico | O28: Superior | P28: Contaduria | Q28: Terminado | R28: Administrativo | S28: Administrativo | T28: 7911006712 | V28: Normal | W28: 45828 | X28: 13149608559 | Y28: Mexicana | Z28: LOOA960412MMCPRN08 | AA28: 2 | AB28: TRUE | AC28: 45834 | AD28: 45834 | AG28: F | AH28: S | AI28: FALSE | AK28: TRUE | AL28: TRUE | AM28: Mama/ 7911022212 Papa | AN28: Diseñar | AO28: Contabilidad | AP28: Contabilidad | AQ28: a.2373atm@gmail.com | AU28: 5.2567845e+15 | AV28: Banamex | AW28: XG | AX28: 40 | AY28: 26 | AZ28: XG | BA28: XG | BB28: 619.2144 | BC28: FALSE | BD28: 1495838660 | BE28: 1209097721671 | BF28: 7711278193 | BH28: B+ | BI28: 45834 | BJ28: A | BK28: =+Table13[[#This Row],[Nombres]]&" "&Table13[[#This Row],[Ap_paterno]]&" "&Table13[[#This Row],[Ap_materno]] -> Anahi Daniela Lopez Ortiz
A29: 2372 | B29: Plata | C29: Zarate | D29: Christian | E29: 0 | F29: 29994 | G29: Distrito Federal | H29: PAZC820212IA5 | I29: 3ra cerrada de la herradura | J29: Rancho San Antonio | K29: Tiayuca | L29: Hidalgo | M29: 43810 | N29: Mexico | O29: Secundaria | Q29: Terminado | R29: Operativo | S29: Operativo | T29: 5549011936 | V29: Normal | X29: 3706820430-6 | Y29: Mexicana | Z29: PAZC820212HDFLRH03 | AA29: 1 | AB29: TRUE | AC29: 45832 | AD29: 45832 | AF29: 45860 | AG29: M | AH29: U | AI29: FALSE | AK29: FALSE | AL29: FALSE | AM29: suegra/ 5636015851 esposa | AQ29: c.2372atm@gmail.com | AR29: 45860 | AU29: 5.2041662e+15 | AV29: Banamex | AW29: 36 | AX29: 30 | AY29: 27 | AZ29: G | BA29: G | BB29: 296.37 | BC29: FALSE | BD29: 2774004053 | BE29: 1894052662807 | BH29: O+ | BI29: 45861 | BJ29: M | BK29: =+Table13[[#This Row],[Nombres]]&" "&Table13[[#This Row],[Ap_paterno]]&" "&Table13[[#This Row],[Ap_materno]] -> Christian Plata Zarate
A30: 2371 | B30: Cortes | C30: Sanchez | D30: Jorge | E30: 0 | F30: 35401 | G30: Hidalgo | H30: COSJ961202F86 | I30: Columbo | J30: Villas de San Francisco 2do sector | K30: General Escobedo | L30: Nuevo León | M30: 66062 | N30: Mexico | O30: Superior | P30: Ing en Mecanica | Q30: Terminado | R30: Administrativo | S30: Administrativo | T30: 7751287573 | V30: Normal | W30: 45828 | X30: 13159638868 | Y30: Mexicana | Z30: COSJ961202HHGRNR07 | AA30: 2 | AB30: TRUE | AC30: 45828 | AD30: 45828 | AG30: M | AH30: C | AI30: FALSE | AK30: TRUE | AL30: FALSE | AM30: Esposa/ 8131256092 Papa | AN30: Almacen | AO30: Almacen | AP30: Almacen | AQ30: j.2371atm@gmail.com | AU30: 5.2567845e+15 | AV30: Banamex | AW30: 32 | AX30: 30 | AY30: 27 | AZ30: M | BA30: M | BB30: 517.9791 | BC30: FALSE | BD30: 1564272933 | BE30: 1199099608337 | BF30: 7717944077 | BH30: O+ | BI30: 45828 | BJ30: M | BK30: =+Table13[[#This Row],[Nombres]]&" "&Table13[[#This Row],[Ap_paterno]]&" "&Table13[[#This Row],[Ap_materno]] -> Jorge Cortes Sanchez
A31: 2370 | B31: Carmona | C31: Rocha | D31: Oscar | E31: 0 | F31: 35807 | G31: Tlaxcala | H31: CARO980112UJ4 | I31: Manuel P. Montes | J31: San Felipe Hidalgo | K31: Nanacamilpa de Mariano Arista | L31: Tlaxcala | M31: 90288 | N31: Mexico | O31: Medio Superior | P31: Operador | Q31: Terminado | R31: Operativo | S31: Operativo | T31: 4426017584 | V31: Normal | W31: 45825 | X31: 61169880814 | Y31: Mexicana | Z31: CARO980112HTLRCS05 | AA31: 1 | AB31: TRUE | AC31: 45825 | AD31: 45825 | AG31: M | AH31: S | AI31: FALSE | AK31: TRUE | AL31: FALSE | AM31: Padre/ 7487661312 Madre | AN31: operador | AO31: Operador | AP31: Operador | AQ31: o.2370atm@gmail.com | AU31: 5.2567845e+15 | AV31: Banamex | AW31: 34 | AX31: 34 | AY31: 28 | AZ31: M | BA31: M | BB31: 296.37 | BC31: FALSE | BD31: 2778149880 | BE31: 308105857539 | BF31: 7712024091 | BH31: O+ | BI31: 45827 | BJ31: M | BK31: =+Table13[[#This Row],[Nombres]]&" "&Table13[[#This Row],[Ap_paterno]]&" "&Table13[[#This Row],[Ap_materno]] -> Oscar Carmona Rocha
A32: 2369 | B32: Lopez | C32: Villordo | D32: Jair Isael | E32: 0 | F32: 34743 | G32: Hidalgo | H32: LOVJ950213GH6 | I32: Hidalgo | J32: Localidad Lazaro Cardenas | K32: Apan | L32: Hidalgo | M32: 43921 | N32: Mexico | O32: Secundaria | Q32: Terminado | R32: Operativo | S32: Operativo | T32: 7751620171 | V32: Normal | W32: 45825 | X32: 68149503127 | Y32: Mexicana | Z32: LOVJ950213HHGPLR01 | AA32: 1 | AB32: TRUE | AC32: 45825 | AD32: 45825 | AF32: 45878 | AG32: M | AH32: S | AI32: FALSE | AK32: FALSE | AL32: FALSE | AM32: Mama/ 7757843164 Papa | AN32: Operador | AO32: operador | AP32: Operador | AQ32: j.2369atm@gmail.com | AR32: 45878 | AU32: 5.2567835e+15 | AV32: Banamex | AW32: 32 | AX32: 32 | AY32: 25 | AZ32: M | BA32: M | BB32: 296.37 | BC32: FALSE | BD32: 2050302024 | BE32: 148095469802 | BH32: O+ | BI32: 45878 | BJ32: M | BK32: =+Table13[[#This Row],[Nombres]]&" "&Table13[[#This Row],[Ap_paterno]]&" "&Table13[[#This Row],[Ap_materno]] -> Jair Isael Lopez Villordo
A33: 2368 | B33: Moncayo | C33: Palacios | D33: Daniel Rodrigo | E33: 0 | F33: 32706 | G33: Nuevo León | H33: MOPD8907179R5 | I33: Tauro | J33: Residencial Orion | K33: Apodaca | L33: Nuevo León | M33: 66633 | N33: Mexico | O33: Superior | P33: Administracion de Empresas | Q33: Terminado | R33: Administrativo | S33: Administrativo | T33: 8123551434 | V33: Normal | W33: 45810 | X33: 43128917275 | Y33: Mexicana | Z33: MOPD890717HNLNLN08 | AA33: 2 | AB33: TRUE | AC33: 45810 | AD33: 45810 | AG33: M | AH33: C | AI33: FALSE | AK33: TRUE | AL33: TRUE | AM33: Esposa/ 8134035853 Papa | AN33: Paciente | AO33: Logistica y cadena de suministro | AP33: Logistica | AQ33: d.2368atm@gmail.com | AU33: 5.5791005e+15 | AV33: Banamex | AW33: 40 | AX33: 34 | AY33: 28 | AZ33: XG | BA33: XG | BB33: 721.8449 | BC33: FALSE | BD33: 1803096531 | BE33: 623078393284 | BF33: 8112445533 | BH33: O+ | BI33: 45810 | BJ33: A | BK33: =+Table13[[#This Row],[Nombres]]&" "&Table13[[#This Row],[Ap_paterno]]&" "&Table13[[#This Row],[Ap_materno]] -> Daniel Rodrigo Moncayo Palacios
A34: 2367 | B34: Rosillo | C34: Castillo | D34: Jorge Arturo | E34: 0 | F34: 24629 | G34: Distrito Federal | H34: ROCJ670606BJ5 | I34: Lindavista | J34: Ampliación Vicente Villada | K34: Nezahualcoyotl | L34: Edo de México | M34: 57719 | N34: Mexico | O34: Secundaria | Q34: Terminado | R34: Operativo | S34: Operativo | T34: 5518459361 | V34: Normal | X34: 0789671986-6 | Y34: Mexicana | Z34: ROCJ670606HDFSSR07 | AA34: 1 | AB34: TRUE | AC34: 45807 | AD34: 45807 | AG34: M | AH34: C | AI34: FALSE | AK34: TRUE | AL34: TRUE | AM34: esposa/ 5588418747 casa | AQ34: j.2367atm@gmail.com | AU34: 5.2567844e+15 | AV34: Banamex | AW34: 40 | AX34: 34 | AY34: 27 | AZ34: G | BA34: G | BB34: 296.37 | BC34: FALSE | BD34: 2390756170 | BE34: 1913033222964 | BF34: 7711895511 | BH34: O+ | BI34: 45807 | BJ34: A | BK34: =+Table13[[#This Row],[Nombres]]&" "&Table13[[#This Row],[Ap_paterno]]&" "&Table13[[#This Row],[Ap_materno]] -> Jorge Arturo Rosillo Castillo
A35: 2366 | B35: Elizalde | C35: Asuerez | D35: Ernesto | E35: 0 | F35: 33540 | G35: Sinaloa | H35: EIAE911029E20 | I35: Rosso Fiorentino | J35: Arezzo Residencial | K35: Garcia | L35: Nuevo León | M35: 66633 | N35: Mexico | O35: Superior | P35: Quimico Farmaceutico | Q35: Terminado | R35: Administrativo | S35: Administrativo | T35: 6674673779 | V35: Normal | W35: 45805 | X35: 2312912391-7 | Y35: Mexicana | Z35: EIAE911029HSLLSR00 | AA35: 2 | AB35: TRUE | AC35: 45805 | AD35: 45805 | AG35: M | AH35: S | AI35: FALSE | AK35: TRUE | AL35: TRUE | AM35: Amigo/ 6621137915 Mama | AN35: RP | AO35: Distribucion, logistica | AP35: Operaciones | AQ35: e.2366atm@gmail.com | AU35: 5.2567845e+15 | AV35: Banamex | AW35: 44 | AX35: 38 | AY35: 30 | AZ35: XG | BA35: XG | BB35: 687.259 | BC35: FALSE | BD35: 1829374354 | BE35: 1087084806284 | BF35: 8115535321 | BH35: B+ | BI35: 45805 | BJ35: A | BK35: =+Table13[[#This Row],[Nombres]]&" "&Table13[[#This Row],[Ap_paterno]]&" "&Table13[[#This Row],[Ap_materno]] -> Ernesto Elizalde Asuerez
A36: 2365 | B36: Lozano | C36: Resendiz | D36: Salvador | E36: 0 | F36: 30449 | G36: Hidalgo | H36: LORS830513FN3 | I36: 2do calleon de la presa | J36: Purificacion | K36: Teotihuacan | L36: Edo de México | M36: 55804 | N36: Mexico | O36: Primaria | Q36: Terminado | R36: Operativo | S36: Operativo | T36: 5634442276 | V36: Normal | X36: 0317832213-1 | Y36: Mexicana | Z36: LORS830513HHGZSL01 | AA36: 1 | AB36: TRUE | AC36: 45800 | AD36: 45800 | AF36: 45829 | AG36: M | AH36: S | AI36: FALSE | AK36: TRUE | AL36: TRUE | AM36: papá/5574314566 cuñada correo personal: chavalozano243@gmail.com | AQ36: s.2365atm@gmail.com | AR36: 45829 | AU36: 5.2567844e+15 | AV36: Banamex | AW36: 36 | AX36: 34 | AY36: 28 | AZ36: XG | BA36: XG | BB36: 296.37 | BC36: FALSE | BD36: 2028420039 | BE36: 4528059254262 | BH36: A+ | BI36: 45833 | BJ36: M | BK36: =+Table13[[#This Row],[Nombres]]&" "&Table13[[#This Row],[Ap_paterno]]&" "&Table13[[#This Row],[Ap_materno]] -> Salvador Lozano Resendiz
A37: 2364 | B37: Rodriguez | C37: Espinosa | D37: Leonardo | E37: 0 | F37: 37201 | G37: Hidalgo | H37: ROEL011106HS6 | I37: Calle 1 de mayo | J37: Nueva | K37: Emiliano Zapata | L37: Hidalgo | M37: 43961 | N37: Mexico | O37: Superior | P37: Administración de la mercadotecnia | Q37: Terminado | R37: Operativo | S37: Operativo | T37: 5642741396 | V37: Normal | X37: 2617011766-2 | Y37: Mexicana | Z37: ROEL011106HHGDSNA1 | AA37: 1 | AB37: TRUE | AC37: 45776 | AD37: 45776 | AF37: 45777 | AG37: M | AH37: U | AI37: FALSE | AK37: FALSE | AL37: FALSE | AM37: papá/ 8442952211 hermano | AQ37: l.2364atm@gmail.com | AR37: 45777 | AW37: 34 | AX37: 34 | AY37: 27 | AZ37: M | BA37: M | BB37: 296.37 | BC37: FALSE | BD37: 2167666477 | BE37: 355127607775 | BH37: A+ | BI37: 45861 | BJ37: M | BK37: =+Table13[[#This Row],[Nombres]]&" "&Table13[[#This Row],[Ap_paterno]]&" "&Table13[[#This Row],[Ap_materno]] -> Leonardo Rodriguez Espinosa
A38: 2363 | B38: Jimenez | C38: Lopez | D38: Luis Antonio | E38: 0 | F38: 31373 | G38: Distrito Federal | H38: JILL8511222A5 | I38: Privadariotuxpan Edificio 101 | J38: Fraccionamiento Paseos de Chavarria | K38: Mineral de la Reforma | L38: Hidalgo | M38: 42186 | N38: Mexico | O38: Secundaria | Q38: Terminado | R38: Operativo | S38: Operativo | T38: 7711411642 | V38: Normal | X38: 9405851948-2 | Y38: Mexicana | Z38: JILL851122HDFMPS05 | AA38: 1 | AB38: TRUE | AC38: 45776 | AD38: 45776 | AF38: 45786 | AG38: M | AH38: U | AI38: FALSE | AK38: TRUE | AL38: TRUE | AM38: mamá/ 7714600991 casa/ 7713633126 esposa | AN38: Maneja quinra rueda, tomó curso de canacar | AQ38: l.2363atm@gmail.com | AR38: 45786 | AW38: 34 | AX38: 32 | AY38: 26 | AZ38: M | BA38: M | BB38: 296.37 | BC38: FALSE | BD38: 2281255300 | BE38: 1902067187858 | BH38: O+ | BI38: 45840 | BJ38: M | BK38: =+Table13[[#This Row],[Nombres]]&" "&Table13[[#This Row],[Ap_paterno]]&" "&Table13[[#This Row],[Ap_materno]] -> Luis Antonio Jimenez Lopez
A39: 2362 | B39: Noya | C39: Vazquez | D39: Mariana | E39: 0 | F39: 36020 | G39: Hidalgo | H39: NOVM980813285 | I39: Adivinos | J39: San Isidro | K39: Tlanalapa | L39: Hidalgo | M39: 43935 | N39: Mexico | O39: Superior | P39: Ing Logistica y transporte | Q39: Terminado | R39: Administrativo | S39: Administrativo | T39: 2462219083 | V39: Normal | W39: 45772 | X39: 22139862258 | Y39: Mexicana | Z39: NOVM980813MHGYZR00 | AA39: 2 | AB39: TRUE | AC39: 45772 | AD39: 45772 | AF39: 45874 | AG39: F | AH39: U | AI39: FALSE | AK39: TRUE | AL39: TRUE | AM39: Pareja/ 7711882869 Tia | AN39: Atencion al cliente | AO39: Trafico | AP39: Almacen inventarios | AQ39: m.2362atm@gmail.com | AR39: 45874 | AU39: 5.2567844e+15 | AV39: Banamex | AW39: G | AX39: 34 | AY39: 24 | AZ39: G | BA39: G | BB39: 642.581 | BC39: FALSE | BD39: 1500065900 | BE39: 465106530801 | BH39: A+ | BI39: 45883 | BJ39: M | BK39: =+Table13[[#This Row],[Nombres]]&" "&Table13[[#This Row],[Ap_paterno]]&" "&Table13[[#This Row],[Ap_materno]] -> Mariana Noya Vazquez
A40: 2361 | B40: Garcia | C40: Perez | D40: Jesus Rafael | E40: 0 | F40: 33106 | G40: Hidalgo | H40: GAPJ900821QN4 | I40: Mza 2 Lt16 | J40: 21 de Julio | K40: CD Sahagun | L40: Hidalgo | M40: 43995 | N40: Mexico | O40: Medio Superior | P40: Tecnico mecanico | Q40: Terminado | R40: Administrativo | S40: Administrativo | T40: 7752161713 | V40: Normal | W40: 45763 | X40: 13109031925 | Y40: Mexicana | Z40: GAPJ900821HHGRRS08 | AA40: 2 | AB40: TRUE | AC40: 45763 | AD40: 45763 | AG40: M | AH40: C | AI40: FALSE | AK40: TRUE | AL40: TRUE | AM40: Esposa/ 7757596960 Mama | AN40: Mecanica | AO40: Almacen | AP40: Mecanica | AQ40: j.2361atm@gmail.com | AU40: 5.2567839e+15 | AV40: Banamex | AW40: 44 | AX40: 40 | AY40: 28 | AZ40: XXG | BA40: XXG | BB40: 518 | BC40: FALSE | BD40: 2382931714 | BE40: 1224086993571 | BF40: 7712198988 | BH40: A+ | BI40: 45763 | BJ40: A | BK40: =+Table13[[#This Row],[Nombres]]&" "&Table13[[#This Row],[Ap_paterno]]&" "&Table13[[#This Row],[Ap_materno]] -> Jesus Rafael Garcia Perez
A41: 2360 | B41: Vergara | C41: Muñoz | D41: Daniel | E41: 0 | F41: 36249 | G41: Puebla | H41: VEMD990330D74 | I41: Carretera Mexico-Tuxpan | J41: Catalina | K41: Huauchinango | L41: Puebla | M41: 73176 | N41: Mexico | O41: Medio Superior | Q41: Terminado | R41: Operativo | S41: Operativo | T41: 2224414310 | V41: Normal | X41: 4815999891-2 | Y41: Mexicana | Z41: VEMD990330HPLRXN04 | AA41: 1 | AB41: TRUE | AC41: 45758 | AD41: 45758 | AF41: 45759 | AG41: M | AH41: S | AI41: FALSE | AK41: TRUE | AL41: TRUE | AM41: mamá, 2227903671 hermana | AQ41: d.2360atm@gmail.com | AR41: 45759 | AW41: 34 | AX41: 34 | AY41: 27 | AZ41: G | BA41: M | BB41: 296.37 | BC41: FALSE | BD41: 1653248878 | BE41: 612118804510 | BH41: A+ | BI41: 45861 | BJ41: M | BK41: =+Table13[[#This Row],[Nombres]]&" "&Table13[[#This Row],[Ap_paterno]]&" "&Table13[[#This Row],[Ap_materno]] -> Daniel Vergara Muñoz
A42: 2359 | B42: Muñoz | C42: Hernandez | D42: Rodolfo | E42: 0 | F42: 27029 | G42: Edo de México | H42: MUHR731231M98 | I42: Fuente de la juventud | J42: Las Fuentes | K42: Singuilucan | L42: Hidalgo | M42: 43780 | N42: Mexico | O42: Secundaria | Q42: Terminado | R42: Operativo | S42: Operativo | T42: 7751049400 | V42: Normal | X42: 3990731744-8 | Y42: Mexicana | Z42: MUHR731231HMCXRD02 | AA42: 1 | AB42: TRUE | AC42: 45751 | AD42: 45751 | AF42: 45793 | AG42: M | AH42: C | AI42: FALSE | AK42: TRUE | AL42: TRUE | AM42: esposa/ 7751291576 hijo | AQ42: r.2359atm@gmail.com | AR42: 45793 | AU42: 5.2567844e+15 | AV42: Banamex | AW42: 36 | AX42: 32 | AY42: 27 | AZ42: M | BA42: M | BB42: 296.37 | BC42: FALSE | BD42: 2611093561 | BE42: 1121009016547 | BH42: O+ | BI42: 45852 | BJ42: M | BK42: =+Table13[[#This Row],[Nombres]]&" "&Table13[[#This Row],[Ap_paterno]]&" "&Table13[[#This Row],[Ap_materno]] -> Rodolfo Muñoz Hernandez
A43: 2358 | B43: Lopez | C43: Romero | D43: Angel Abraham | E43: 0 | F43: 37288 | G43: Distrito Federal | H43: LORA020201C66 | I43: Rio tigris Mza76 | J43: Valle de Guadalupe | K43: Sahagún | L43: Hidalgo | M43: 43995 | N43: Mexico | O43: Secundaria | Q43: Terminado | R43: Operativo | S43: Operativo | T43: 7752348636 | V43: Normal | X43: 1616023543-4 | Y43: Mexicana | Z43: LORA020201HDFPMNA8 | AA43: 1 | AB43: TRUE | AC43: 45737 | AD43: 45737 | AG43: M | AH43: S | AI43: FALSE | AK43: TRUE | AL43: TRUE | AM43: hermano/ 5522201121 papá | AQ43: a.2358atm@gmail.com | AU43: 5.2567844e+15 | AV43: Banamex | AW43: 40 | AX43: 42 | AY43: 29 | AZ43: XG | BA43: XG | BB43: 582.18 | BC43: FALSE | BD43: 2751180640 | BE43: 1209126784709 | BF43: 7712406091 | BH43: O+ | BI43: 45740 | BJ43: M | BK43: =+Table13[[#This Row],[Nombres]]&" "&Table13[[#This Row],[Ap_paterno]]&" "&Table13[[#This Row],[Ap_materno]] -> Angel Abraham Lopez Romero
A44: 2357 | B44: Aguilar | C44: Galdamez | D44: Fernando | E44: 0 | F44: 28007 | G44: Chiapas | H44: AUGF760904TH0 | I44: Buho | J44: Valle de San Francisco | K44: Escobedo | L44: Nuevo León | M44: 66064 | N44: Mexico | O44: Superior | P44: Ingeniero Agronomo | Q44: Terminado | R44: Administrativo | S44: Administrativo | T44: 9611343484 | V44: Normal | W44: 45736 | X44: 71957336861 | Y44: Mexicana | Z44: AUGF760904HCSGLR09 | AA44: 2 | AB44: TRUE | AC44: 45736 | AD44: 45737 | AG44: M | AH44: C | AI44: FALSE | AK44: TRUE | AL44: TRUE | AM44: Esposa/ 9611856416 Hermana | AN44: Mecanica | AO44: Asesoria | AP44: Financiera | AQ44: f.2357atm@gmail.com | AU44: 5.2567862e+15 | AV44: Banamex | AW44: 40 | AX44: 36 | AY44: 27 | AZ44: G | BA44: M | BB44: 517.98 | BC44: FALSE | BD44: 2497111429 | BE44: 1868046714175 | BF44: 7711895523 | BH44: O+ | BI44: 45737 | BJ44: M | BK44: =+Table13[[#This Row],[Nombres]]&" "&Table13[[#This Row],[Ap_paterno]]&" "&Table13[[#This Row],[Ap_materno]] -> Fernando Aguilar Galdamez
A45: 2356 | B45: Palos | C45: Cabrera | D45: Ivan Michelle | E45: 0 | F45: 30820 | G45: Nuevo León | H45: PACI840518T11 | I45: Santa Ines | J45: Residencia California | K45: Escobedo | L45: Nuevo León | M45: 66055 | N45: Mexico | O45: Medio Superior | P45: Tec programador analista | Q45: Terminado | R45: Administrativo | S45: Administrativo | T45: 8115591575 | V45: Normal | W45: 45736 | X45: 47008476468 | Y45: Mexicana | Z45: PACI840518HNLLBV01 | AA45: 2 | AB45: TRUE | AC45: 45736 | AD45: 45737 | AF45: 45744 | AG45: M | AH45: D | AI45: FALSE | AK45: TRUE | AL45: TRUE | AM45: Mama/ 8135820311 Hermano | AN45: Office | AO45: Almacen y logistica | AP45: Logistica | AQ45: i.2356atm@gmail.com | AR45: 45744 | AW45: 36 | AX45: 32 | AY45: 29 | AZ45: G | BA45: M | BB45: 517.98 | BC45: FALSE | BD45: 1812464183 | BE45: 491062443720 | BH45: O- | BI45: 45824 | BJ45: M | BK45: =+Table13[[#This Row],[Nombres]]&" "&Table13[[#This Row],[Ap_paterno]]&" "&Table13[[#This Row],[Ap_materno]] -> Ivan Michelle Palos Cabrera
A46: 2355 | B46: Rosas | C46: Hernandez | D46: Jose Noe | E46: 0 | F46: 27759 | G46: Edo de México | H46: ROHN751231V61 | I46: Tlatelolco | J46: Santo Domingo Aztacameca | K46: Axapusco | L46: Edo de México | M46: 55955 | N46: Mexico | O46: Primaria | Q46: Terminado | R46: Operativo | S46: Operativo | T46: 5513021145 | V46: Normal | X46: 0225751758-7 | Y46: Mexicana | Z46: ROHN751231HMCSRX07 | AA46: 1 | AB46: TRUE | AC46: 45730 | AD46: 45730 | AF46: 45738 | AG46: M | AH46: C | AI46: FALSE | AK46: TRUE | AL46: FALSE | AM46: esposa/5614920473 hermano | AQ46: j.2355atm@gmail.com | AR46: 45738 | AW46: 36 | AX46: 36 | AY46: 27 | AZ46: M | BA46: M | BB46: 296.37 | BC46: FALSE | BD46: 2480540254 | BE46: 478024758417 | BH46: A+ | BI46: 45741 | BJ46: M | BK46: =+Table13[[#This Row],[Nombres]]&" "&Table13[[#This Row],[Ap_paterno]]&" "&Table13[[#This Row],[Ap_materno]] -> Jose Noe Rosas Hernandez
A47: 2354 | B47: Rodriguez | C47: Garcia | D47: Jesus David | E47: 0 | F47: 37255 | G47: Hidalgo | H47: ROGJ011230RG0 | I47: Guillermo Prieto | J47: Centro | K47: Tolcayuca | L47: Hidalgo | M47: 43860 | N47: Mexico | O47: Medio Superior | P47: Técnico en administración | Q47: Terminado | R47: Operativo | S47: Operativo | T47: 7712321369 | V47: Normal | X47: 0323010098-8 | Y47: Mexicana | Z47: ROGJ011230HHGDRSA8 | AA47: 1 | AB47: TRUE | AC47: 45727 | AD47: 45727 | AG47: M | AH47: S | AI47: FALSE | AK47: TRUE | AL47: TRUE | AM47: mamá/ 7712392783 papá | AQ47: j.2354atm@gmail.com | AU47: 5.2567844e+15 | AV47: Banamex | AW47: 30 | AX47: 30 | AY47: 26 | AZ47: CH | BA47: CH | BB47: 583.04 | BC47: FALSE | BD47: 2012135653 | BE47: 1444125664280 | BF47: 7712206214 | BH47: O+ | BI47: 45727 | BJ47: A | BK47: =+Table13[[#This Row],[Nombres]]&" "&Table13[[#This Row],[Ap_paterno]]&" "&Table13[[#This Row],[Ap_materno]] -> Jesus David Rodriguez Garcia
A48: 2353 | B48: Hernandez | C48: Hernandez | D48: Roberto | E48: 0 | F48: 30031 | G48: Puebla | H48: HEHR820321IA6 | I48: Juliano | J48: Camino Real | K48: Guadalupe | L48: Nuevo León | M48: 67170 | N48: Mexico | O48: Medio Superior | P48: Técnico en Sistemas Computacionales | Q48: Terminado | R48: Operativo | S48: Operativo | T48: 8110259506 | V48: Normal | X48: 0224829170-6 | Y48: Mexicana | Z48: HEHR820321HPLRRB05 | AA48: 1 | AB48: TRUE | AC48: 45726 | AD48: 45726 | AG48: M | AH48: C | AI48: FALSE | AK48: TRUE | AL48: TRUE | AM48: esposa/ 5533262648 hermana | AQ48: r.2353atm@gmail.com | AU48: 5.5791004e+15 | AV48: Banamex | AW48: 34 | AX48: 30 | AY48: 27 | AZ48: M | BA48: M | BB48: 885.17 | BC48: FALSE | BD48: 2447137532 | BE48: 2484043670100 | BF48: 7711896870 | BH48: O+ | BI48: 45726 | BJ48: A | BK48: =+Table13[[#This Row],[Nombres]]&" "&Table13[[#This Row],[Ap_paterno]]&" "&Table13[[#This Row],[Ap_materno]] -> Roberto Hernandez Hernandez
A49: 2352 | B49: Angeles | C49: Guevara | D49: Hugo Isaac | E49: 0 | F49: 38227 | G49: Veracruz | H49: AEGH040828UBA | I49: Loma Bonita | J49: Palpoala Ixcan | K49: Misantla | L49: Veracruz | M49: 93833 | N49: Mexico | O49: Medio Superior | P49: Técnico agropecuario | Q49: Terminado | R49: Operativo | S49: Operativo | T49: 2321444068 | V49: Normal | X49: 1721044872-0 | Y49: Mexicana | Z49: AEGH040828HVZNVGA2 | AA49: 1 | AB49: TRUE | AC49: 45723 | AD49: 45723 | AF49: 45755 | AG49: M | AH49: U | AI49: FALSE | AK49: TRUE | AL49: TRUE | AM49: tío/ 2321050646 madre | AQ49: h.2352atm@gmail.com | AR49: 45755 | AU49: 5.2567844e+15 | AV49: Banamex | AW49: 36 | AX49: 34 | AY49: 27 | AZ49: M | BA49: M | BB49: 296.37 | BC49: FALSE | BD49: 2366814989 | BE49: 2545132790538 | BH49: O+ | BI49: 45842 | BJ49: M | BK49: =+Table13[[#This Row],[Nombres]]&" "&Table13[[#This Row],[Ap_paterno]]&" "&Table13[[#This Row],[Ap_materno]] -> Hugo Isaac Angeles Guevara
A50: 2351 | B50: Mendia | C50: Carrion | D50: Eladio | E50: 0 | F50: 29635 | G50: Hidalgo | H50: MECE810218DX6 | I50: 22 de octubre | J50: Los Cides | K50: Tepeapulco | L50: Hidalgo | M50: 43970 | N50: Mexico | O50: Medio Superior | P50: Técnico en informática | Q50: Terminado | R50: Operativo | S50: Operativo | T50: 6131179848 | V50: Normal | X50: 1396813041-2 | Y50: Mexicana | Z50: MECE810218HHGNRL04 | AA50: 1 | AB50: TRUE | AC50: 45720 | AD50: 45720 | AF50: 45756 | AG50: M | AH50: U | AI50: FALSE | AK50: TRUE | AL50: TRUE | AM50: Sarai esposa/ 7911203304 hermana Guadalupe | AQ50: e.2351atm@gmail.com | AR50: 45756 | AU50: 5.2567844e+15 | AV50: Banamex | AW50: 40 | AX50: 40 | AY50: 28 | AZ50: XG | BA50: XG | BB50: 296.37 | BC50: FALSE | BD50: 1357570769 | BE50: 1205007762758 | BH50: O+ | BI50: 45842 | BJ50: M | BK50: =+Table13[[#This Row],[Nombres]]&" "&Table13[[#This Row],[Ap_paterno]]&" "&Table13[[#This Row],[Ap_materno]] -> Eladio Mendia Carrion
A51: 2350 | B51: Ramirez | C51: Garcia | D51: Francisco | E51: 0 | F51: 25098 | G51: Distrito Federal | H51: RAGF680917CG6 | I51: Camino Real L7 | J51: Jorge Jimenez Cantu | K51: Nicolas Romero | L51: Edo de México | M51: 54408 | N51: Mexico | O51: Medio Superior | Q51: Terminado | R51: Operativo | S51: Operativo | T51: 5629558169 | V51: Normal | X51: 9490680326-0 | Y51: Mexicana | Z51: RAGF680917HMCMRR07 | AA51: 1 | AB51: TRUE | AC51: 45716 | AD51: 45716 | AF51: 45739 | AG51: M | AH51: U | AI51: FALSE | AK51: TRUE | AL51: TRUE | AM51: alicia galinda, pareja/5638076110 estefani hija | AQ51: f.2350atmexicana@gmail.com | AR51: 45739 | AW51: 40 | AX51: 36 | AY51: 28 | AZ51: XG | BA51: G | BB51: 296.37 | BC51: FALSE | BD51: 2610193453 | BE51: 3813018372882 | BH51: O+ | BI51: 45859 | BJ51: M | BK51: =+Table13[[#This Row],[Nombres]]&" "&Table13[[#This Row],[Ap_paterno]]&" "&Table13[[#This Row],[Ap_materno]] -> Francisco Ramirez Garcia
A52: 2349 | B52: Amador | C52: Martinez | D52: Jose Alan | E52: 0 | F52: 36063 | G52: Hidalgo | H52: AAMA980925L90 | I52: Francisco Gonzalez Bocanegra | J52: Plaza Vieja | K52: Tepeapulco | L52: Hidalgo | M52: 43976 | N52: Mexico | O52: Superior | P52: Ing Telematica | Q52: Terminado | R52: Administrativo | S52: Administrativo | T52: 7752258245 | V52: Normal | W52: 45714 | X52: 8316988578-3 | Y52: Mexicana | Z52: AAMA980925HHGMRL08 | AA52: 2 | AB52: TRUE | AC52: 45714 | AD52: 45714 | AG52: M | AH52: C | AI52: FALSE | AK52: TRUE | AL52: TRUE | AM52: Esposa | AN52: Desarrollo web, analisis de datos | AO52: Almacenes, sistemas, manufactura | AP52: Tecnologica | AQ52: j.2349atm@gmail.com | AU52: 5.2567842e+15 | AV52: Banamex | AW52: 36 | AX52: 32 | AY52: 27 | AZ52: G | BA52: M | BB52: 550.58 | BC52: FALSE | BD52: 1813010923 | BE52: 1198107364210 | BF52: 7711895537 | BH52: A+ | BI52: 45736 | BJ52: M | BK52: =+Table13[[#This Row],[Nombres]]&" "&Table13[[#This Row],[Ap_paterno]]&" "&Table13[[#This Row],[Ap_materno]] -> Jose Alan Amador Martinez
A53: 2348 | B53: Lopez | C53: Rangel | D53: Julio Cesar | E53: 0 | F53: 26636 | G53: Distrito Federal | H53: LORJ721203QYA | I53: Novelistas Mza4 int 3 | J53: Purisima Atlazolpa | K53: CDMX | L53: Distrito Federal | M53: 9429 | N53: Mexico | O53: Superior | P53: Derecho | Q53: Truncado | R53: Operativo | S53: Operativo | T53: 5521713403 | V53: Normal | X53: 3094721900-9 | Y53: Mexicana | Z53: LORJ721203HDFPNL07 | AA53: 1 | AB53: TRUE | AC53: 45713 | AD53: 45714 | AG53: M | AH53: C | AI53: FALSE | AK53: TRUE | AL53: TRUE | AM53: esposa/ 5535244186 mamá | AQ53: j.2348atm@gmail.com | AU53: 5.5790701e+15 | AV53: Banamex | AW53: 42 | AX53: 38 | AY53: 27 | AZ53: XG | BA53: XG | BB53: 618.81 | BC53: FALSE | BD53: 1578528020 | BE53: 2391052877058 | BF53: 7712406095 | BH53: O+ | BI53: 45838 | BJ53: M | BK53: =+Table13[[#This Row],[Nombres]]&" "&Table13[[#This Row],[Ap_paterno]]&" "&Table13[[#This Row],[Ap_materno]] -> Julio Cesar Lopez Rangel
A54: 2347 | B54: Avila | C54: Correa | D54: Aldo Joan | E54: 0 | F54: 38178 | G54: Edo de México | H54: AICA040710T28 | I54: Azafran M23 | J54: Santa Teresa 6 | K54: Huehuetoca | L54: Edo de México | M54: 54694 | N54: Mexico | O54: Secundaria | Q54: Terminado | R54: Operativo | S54: Operativo | T54: 5578380001 | V54: Normal | X54: 2720042296-5 | Y54: Mexicana | Z54: AICA040710HMCVRLA6 | AA54: 1 | AB54: TRUE | AC54: 45706 | AD54: 45706 | AF54: 45754 | AG54: M | AH54: U | AI54: FALSE | AK54: TRUE | AL54: TRUE | AM54: esposa/ 5578824633 papá | AQ54: a.2347atm@gmail.com | AR54: 45754 | AU54: 5.2041661e+15 | AV54: Banamex | AW54: 28 | AX54: 28 | AY54: 25 | AZ54: XG | BA54: G | BB54: 296.37 | BC54: FALSE | BD54: 2625462311 | BE54: 6423132282788 | BH54: B+ | BI54: 45861 | BJ54: M | BK54: =+Table13[[#This Row],[Nombres]]&" "&Table13[[#This Row],[Ap_paterno]]&" "&Table13[[#This Row],[Ap_materno]] -> Aldo Joan Avila Correa
A55: 2346 | B55: Cortes | C55: Roldan | D55: Brayan | E55: 0 | F55: 37202 | G55: Puebla | H55: CORB011107EDA | I55: Alamos | J55: Jaltepec | K55: Axapusco | L55: Edo de México | M55: 55965 | N55: Mexico | O55: Medio Superior | Q55: Terminado | R55: Operativo | S55: Operativo | T55: 7711835934 | V55: Normal | X55: 5016013785-2 | Y55: Mexicana | Z55: CORB011107HPLRLRA5 | AA55: 1 | AB55: TRUE | AC55: 45706 | AD55: 45706 | AG55: M | AH55: U | AI55: FALSE | AK55: TRUE | AL55: TRUE | AM55: esposa/ 7751611321 mamá | AQ55: b.2346atm@gmail.com | AU55: 5.2567844e+15 | AV55: Banamex | AW55: 30 | AX55: 28 | AY55: 26 | AZ55: M | BA55: M | BB55: 608.61 | BC55: FALSE | BD55: 2353384842 | BE55: 1196125583659 | BF55: 7711895526 | BH55: A+ | BI55: 45719 | BJ55: M | BK55: =+Table13[[#This Row],[Nombres]]&" "&Table13[[#This Row],[Ap_paterno]]&" "&Table13[[#This Row],[Ap_materno]] -> Brayan Cortes Roldan
A56: 2345 | B56: Sanchez | C56: Torres | D56: Arleth | E56: 0 | F56: 35617 | G56: Edo de México | H56: SATA970706Q69 | I56: Fray Martin de Valencia | J56: Los Frailes | K56: Cd Sahagun | L56: Hidalgo | M56: 43977 | N56: Mexico | O56: Superior | P56: Ing Industrial | Q56: Terminado | R56: Administrativo | S56: Administrativo | T56: 3323604334 | V56: Normal | W56: 45701 | X56: 1315974451-8 | Y56: Mexicana | Z56: SATA970706MMCNRR07 | AA56: 2 | AB56: TRUE | AC56: 45701 | AD56: 45701 | AF56: 45728 | AG56: F | AH56: S | AI56: FALSE | AK56: TRUE | AL56: TRUE | AM56: papa/ 7712205582 mama | AN56: Office y Logistica | AO56: Logistica Ing industrial | AP56: Logistica Trafico | AQ56: a.2345tusa@gmail.com | AR56: 45728 | AU56: 5.2567843e+15 | AV56: Banamex | AW56: XG | AX56: 42 | AY56: 25 | AZ56: XG | BA56: XG | BB56: 571.36 | BC56: FALSE | BD56: 1876731920 | BE56: 1224103719647 | BI56: 45738 | BJ56: M | BK56: =+Table13[[#This Row],[Nombres]]&" "&Table13[[#This Row],[Ap_paterno]]&" "&Table13[[#This Row],[Ap_materno]] -> Arleth Sanchez Torres
A57: 2344 | B57: Perez | C57: Rendon | D57: Luis Alberto | E57: 0 | F57: 32591 | G57: Tlaxcala | H57: PERL890324M5A | I57: Campesinos | J57: San Felipe Hidalgo | K57: Tlaxcala | L57: Tlaxcala | M57: 90281 | N57: Mexico | O57: Secundaria | Q57: Terminado | R57: Operativo | S57: Operativo | T57: 7491083116 | V57: Normal | X57: 6107890655-1 | Y57: Mexicana | Z57: PERL890324HTLRNS02 | AA57: 1 | AB57: TRUE | AC57: 45699 | AD57: 45699 | AG57: M | AH57: C | AI57: FALSE | AK57: TRUE | AL57: TRUE | AM57: esposa/ 7481068165 mamá | AQ57: l.2344atm@gmail.com | AU57: 5.2567843e+15 | AV57: Banamex | AW57: 38 | AX57: 32 | AY57: 27 | AZ57: M | BA57: M | BB57: 700.93 | BC57: FALSE | BD57: 2282457271 | BE57: 308077978924 | BF57: 8115535329 | BH57: O+ | BI57: 45719 | BJ57: M | BK57: =+Table13[[#This Row],[Nombres]]&" "&Table13[[#This Row],[Ap_paterno]]&" "&Table13[[#This Row],[Ap_materno]] -> Luis Alberto Perez Rendon
A58: 2343 | B58: Reyes | C58: Arena | D58: Miguel Alfredo | E58: 0 | F58: 34159 | G58: Tamaulipas | H58: REAM930709AI0 | I58: 6 de Enero 239 | J58: El Roble | K58: San Nicolas de los Garza | L58: Nuevo León | M58: 66450 | N58: Mexico | O58: Superior | P58: Ing Gestion Empresarial | Q58: Terminado | R58: Administrativo | S58: Administrativo | T58: 8135906225 | V58: Normal | W58: 45698 | X58: 0517935458-3 | Y58: Mexicana | Z58: REAM930709HTSYRG00 | AA58: 2 | AB58: TRUE | AC58: 45698 | AD58: 45698 | AG58: M | AH58: S | AI58: FALSE | AK58: TRUE | AL58: TRUE | AM58: Madre/ 8331860535 Papa | AN58: Informatica, Servicio al cliente | AO58: Atencion al cliente | AP58: Administracion | AQ58: m.2343atm@gmail.com | AU58: 5.5791005e+15 | AV58: Banamex | AW58: 38 | AX58: 34 | AY58: 29 | AZ58: G | BA58: G | BB58: 642.58 | BC58: FALSE | BD58: 2653394750 | BE58: 1830090474070 | BF58: 8115388295 | BI58: 45728 | BJ58: M | BK58: =+Table13[[#This Row],[Nombres]]&" "&Table13[[#This Row],[Ap_paterno]]&" "&Table13[[#This Row],[Ap_materno]] -> Miguel Alfredo Reyes Arena
A59: 2342 | B59: Hernandez | C59: Flores | D59: Jose Santiago | E59: 0 | F59: 26431 | G59: Nuevo León | H59: HEFS720512142 | I59: Cerrada de Baobab #903 | J59: Cerradas de Anahuac | K59: Escobedo | L59: Nuevo León | M59: 66059 | N59: Mesico | O59: Medio Superior | P59: Analista Rpogramador | Q59: Terminado | R59: Operativo | S59: Operativo | T59: 8130963434 | V59: Normal | X59: 4390725562-4 | Y59: Mexicana | Z59: HEFS720512HNLRLN08 | AA59: 1 | AB59: TRUE | AC59: 45698 | AD59: 45698 | AF59: 45699 | AG59: M | AH59: C | AI59: FALSE | AK59: TRUE | AL59: FALSE | AM59: Esposa/ 8111595807 casa | AQ59: j.2342atm@gmail.com | AR59: 45699 | AW59: 36 | AX59: 32 | AY59: 28 | AZ59: G | BA59: G | BB59: 296.37 | BC59: FALSE | BD59: 2626908456 | BE59: 2543016791977 | BI59: 45740 | BJ59: M | BK59: =+Table13[[#This Row],[Nombres]]&" "&Table13[[#This Row],[Ap_paterno]]&" "&Table13[[#This Row],[Ap_materno]] -> Jose Santiago Hernandez Flores
A60: 2341 | B60: Maya | C60: Gomez | D60: Cesar | E60: 1 | F60: 33701 | G60: Edo de México | H60: MAGC920407GV5 | I60: Av. 5 de mayo ote | J60: Centro | K60: Santa Cruz Atizapan | L60: Edo de México | M60: 52500 | N60: Mexico | O60: Secundaria | Q60: Truncado | R60: Operativo | S60: Operativo | T60: 7224998744 | V60: Normal | X60: 1610925872-9 | Y60: Mexicana | Z60: MAGC920407HMCYMS07 | AA60: 1 | AB60: TRUE | AC60: 45695 | AD60: 45695 | AF60: 45736 | AG60: M | AH60: D | AI60: FALSE | AK60: TRUE | AL60: TRUE | AM60: hermana Juana/ 7131045558 hermano Alberto | AQ60: c.2341atm@gmail.com | AR60: 45736 | AU60: 5.5791004e+15 | AV60: Banamex | AW60: 32 | AX60: 30 | AY60: 27 | AZ60: M | BA60: CH | BB60: 494.23 | BC60: FALSE | BD60: 1814175326 | BE60: 248086334549 | BH60: O+ | BI60: 45741 | BJ60: M | BK60: =+Table13[[#This Row],[Nombres]]&" "&Table13[[#This Row],[Ap_paterno]]&" "&Table13[[#This Row],[Ap_materno]] -> Cesar Maya Gomez
A61: 2340 | B61: Ochoa | C61: Ramirez | D61: Isaac Yair | E61: 0 | F61: 34117 | G61: Hidalgo | H61: OORI9305289S0 | I61: Alvaro Obregón | J61: Santiago de la Peña | K61: Tuxpan | L61: Veracruz | M61: 92770 | N61: Mexico | O61: Medio Superior | Q61: Terminado | R61: Operativo | S61: Operativo | T61: 5576649241 | V61: Normal | X61: 1313932199-9 | Y61: Mexicana | Z61: OORI930528HHGCMS09 | AA61: 1 | AB61: TRUE | AC61: 45692 | AD61: 45692 | AF61: 45723 | AG61: M | AH61: U | AI61: FALSE | AK61: TRUE | AL61: TRUE | AM61: Luis Isaac Ochoa Herrera/5529133197 Jacqueline Vergara Urdapilleta | AQ61: i.2340atm@gmail.com | AR61: 45723 | AU61: 5.2567844e+15 | AV61: Banamex | AW61: 42 | AX61: 36 | AY61: 28 | AZ61: XG | BA61: XG | BB61: 359.24 | BC61: FALSE | BD61: 2446474375 | BE61: 4144090094397 | BH61: A+ | BI61: 45736 | BJ61: M | BK61: =+Table13[[#This Row],[Nombres]]&" "&Table13[[#This Row],[Ap_paterno]]&" "&Table13[[#This Row],[Ap_materno]] -> Isaac Yair Ochoa Ramirez
A62: 2339 | B62: Lopez | C62: Gonzalez | D62: Antonio de Jesus | E62: 0 | F62: 32135 | G62: Hidalgo | H62: LOGA871224IV4 | I62: Valle de Tulancingo 22 | J62: Hidalguense | K62: Apan | L62: Hidalgo | M62: 43917 | N62: Mexico | O62: Superior | P62: Ing sistemas com´putacionales | Q62: Terminado | R62: Administrativo | S62: Administrativo | T62: 7751338068 | V62: Normal | W62: 45686 | X62: 13128709444 | Y62: Mexicana | Z62: LOGA871224HHGPNN06 | AA62: 2 | AB62: TRUE | AC62: 45686 | AD62: 45686 | AF62: 45804 | AG62: M | AH62: C | AI62: FALSE | AK62: TRUE | AL62: TRUE | AM62: Esposa/7716994638 Hermano | AN62: Toma de decisiones,Liderazgo | AO62: Manufactura Finanzas Sistemas | AP62: Finanzas Sistemas | AQ62: a.2339atm@gmail.com | AR62: 45804 | AS62: 1320088369 | AU62: 5.5791004e+15 | AV62: Banamex | AW62: 34 | AX62: 34 | AY62: 27 | AZ62: M | BA62: G | BB62: 550.58 | BC62: FALSE | BD62: 2224887090 | BE62: 127073995110 | BI62: 45824 | BJ62: M | BK62: =+Table13[[#This Row],[Nombres]]&" "&Table13[[#This Row],[Ap_paterno]]&" "&Table13[[#This Row],[Ap_materno]] -> Antonio de Jesus Lopez Gonzalez
A63: 2338 | B63: Valdez | C63: Almaguer | D63: Abraham Alexander | E63: 0 | F63: 33118 | G63: Nuevo León | H63: VAAA900902IS0 | I63: Santa Ana 643 | J63: Res California | K63: Escobedo | L63: Nuevo León | M63: 66055 | N63: Mexico | O63: Superior | P63: Administracion de Empresas | Q63: Terminado | R63: Administrativo | S63: Administrativo | T63: 1956865029 | V63: Normal | W63: 45680 | X63: 4112900923-3 | Y63: Mexicana | Z63: VAAA900902HNLLLB06 | AA63: 2 | AB63: TRUE | AC63: 45680 | AD63: 45680 | AF63: 45887 | AG63: M | AH63: S | AI63: FALSE | AK63: TRUE | AL63: TRUE | AM63: Personal/ 8118888007 Hermano/ 8125718998 Papa | AN63: Organizacion | AO63: Logistica | AP63: Administrativo | AQ63: a.2338atm@gmail.com | AR63: 45887 | AS63: 1918107957 | AU63: 5.2567843e+15 | AV63: Banamex | AW63: 46 | AX63: 34 | AY63: 28 | AZ63: M | BA63: G | BB63: 642.58 | BC63: FALSE | BD63: 1526925446 | BE63: 491082903778 | BI63: 45890 | BJ63: M | BK63: =+Table13[[#This Row],[Nombres]]&" "&Table13[[#This Row],[Ap_paterno]]&" "&Table13[[#This Row],[Ap_materno]] -> Abraham Alexander Valdez Almaguer
A64: 2337 | B64: Gomez | C64: Valencia | D64: Giovanni Alfredo | E64: 0 | F64: 36519 | G64: Hidalgo | H64: GOVG9912256N1 | I64: Niño Heroes Sur 14 | J64: Centro | K64: Tlanalapa | L64: Hidalgo | M64: 43930 | N64: Mexico | O64: Superior | P64: Ing Logistica | Q64: Truncado | R64: Administrativo | S64: Administrativo | T64: 7757518673 | V64: Normal | W64: 45678 | X64: 13159989303 | Y64: Mexicana | Z64: GOVG991225HHGMLV02 | AA64: 2 | AB64: TRUE | AC64: 45678 | AD64: 45678 | AG64: M | AH64: U | AI64: FALSE | AK64: TRUE | AL64: TRUE | AM64: Mama/ 7751134685 Hermana | AN64: Atencion a clientes ERP | AO64: Trafico y Rastreo,Operacion | AP64: Rastreo | AQ64: g.2337atm@gmail.com | AU64: 5.5791003e+15 | AV64: Banamex | AW64: 42 | AX64: 36 | AY64: 27 | AZ64: G | BA64: G | BB64: 571.36 | BC64: FALSE | BD64: 1681504508 | BE64: 1398120047155 | BF64: 7711895504 | BI64: 45680 | BJ64: M | BK64: =+Table13[[#This Row],[Nombres]]&" "&Table13[[#This Row],[Ap_paterno]]&" "&Table13[[#This Row],[Ap_materno]] -> Giovanni Alfredo Gomez Valencia
A65: 2336 | B65: Sosa | C65: Nava | D65: Nallely Berenice | E65: 0 | F65: 32273 | G65: Edo de México | H65: SONN880510EM2 | I65: Mariano Matamoros 52 | J65: Miguel Hidalgo | K65: CD Sahagun | L65: Hidalgo | M65: 43998 | N65: Mexico | O65: Superior | P65: Ing Desarrolo e INnovacion Empresarial | Q65: Terminado | R65: Administrativo | S65: Administrativo | T65: 5519668067 | V65: Normal | W65: 45677 | X65: 9611882906-6 | Y65: Mexicana | Z65: SONN880510MMCSVL01 | AA65: 2 | AB65: TRUE | AC65: 45677 | AD65: 45677 | AG65: F | AH65: S | AI65: FALSE | AK65: TRUE | AL65: TRUE | AM65: Hermano/ 7751384461 Mama | AN65: Ofimatica | AO65: Administrativo trafico y logistica | AP65: Logistica | AQ65: n.2336atm@gmail.com | AU65: 5.579087e+15 | AV65: Banamex | AW65: G | AX65: 30 | AY65: 24 | AZ65: G | BA65: M | BB65: 571.36 | BC65: FALSE | BD65: 1275713156 | BE65: 1246077467477 | BF65: 7711895513 | BI65: 45769 | BJ65: M | BK65: =+Table13[[#This Row],[Nombres]]&" "&Table13[[#This Row],[Ap_paterno]]&" "&Table13[[#This Row],[Ap_materno]] -> Nallely Berenice Sosa Nava
A66: 2335 | B66: Garza | C66: Mendoza | D66: Roberto | E66: 0 | F66: 23518 | G66: Nuevo León | H66: GAMR640521CU0 | I66: Calle Oporto #440 | J66: Privadas de Anahuac | K66: Escobedo | L66: Nuevo León | M66: 66059 | N66: Mexico | O66: Medio Superior | Q66: Truncado | R66: Operativo | S66: Operativo | T66: 8111175144 | V66: Normal | X66: 7681640083-2 | Y66: Mexicana | Z66: GAMR640521HNLRNB02 | AA66: 1 | AB66: TRUE | AC66: 45677 | AD66: 45677 | AF66: 45678 | AG66: M | AH66: C | AI66: FALSE | AK66: TRUE | AL66: TRUE | AM66: esposa/ 8122843181 hijo | AQ66: r.2335atm@gmail.com | AW66: 36 | AX66: 34 | AY66: 27 | AZ66: G | BA66: G | BB66: 296.37 | BC66: FALSE | BD66: 1812485160 | BE66: 2535040269043 | BI66: 45740 | BJ66: M | BK66: =+Table13[[#This Row],[Nombres]]&" "&Table13[[#This Row],[Ap_paterno]]&" "&Table13[[#This Row],[Ap_materno]] -> Roberto Garza Mendoza
A67: 2334 | B67: Ordoñez | C67: Cruz | D67: Brenda Lizeth | E67: 0 | F67: 36109 | G67: Hidalgo | H67: OOCB981110DF1 | I67: Sor Juana Ines De la Cruz 102 | J67: San Miguel del Arco | K67: Apan | L67: Hidalgo | M67: 43904 | N67: Mexico | O67: Superior | P67: Ingenrria en Gestion Empresarial | Q67: Terminado | R67: Administrativo | S67: Administrativo | T67: 7751535207 | V67: Normal | W67: 45672 | X67: 2213989404-6 | Y67: Mexicana | Z67: OOCB981110MHGRRR08 | AA67: 2 | AB67: TRUE | AC67: 45672 | AD67: 45672 | AF67: 45681 | AG67: F | AH67: S | AI67: FALSE | AK67: FALSE | AL67: FALSE | AM67: Mama/ 7752059814 Papa | AN67: Analisis | AO67: Manufactura | AP67: Economico administrativo | AQ67: b.2334tusa@gmail.com | AR67: 45681 | AU67: 5.2567836e+15 | AV67: Banamex | AW67: M | AX67: 28 | AY67: 25 | AZ67: M | BA67: M | BB67: 519.48 | BC67: FALSE | BD67: 1540672935 | BE67: 129116854373 | BI67: 45737 | BJ67: M | BK67: =+Table13[[#This Row],[Nombres]]&" "&Table13[[#This Row],[Ap_paterno]]&" "&Table13[[#This Row],[Ap_materno]] -> Brenda Lizeth Ordoñez Cruz
A68: 2333 | B68: Cortes | C68: Rugerio | D68: David | E68: 0 | F68: 25749 | G68: Distrito Federal | H68: CORD700630VC5 | I68: Jose Maria Morelos Mza 97 seccion Corrales | J68: San Miguel Teotongo | K68: Iztapalapa | L68: Distrito Federal | M68: 9630 | N68: Mexico | O68: Secundaria | Q68: Terminado | R68: Operativo | S68: Operativo | T68: 5611721519 | V68: Normal | X68: 4288701130-4 | Y68: Mexicana | Z68: CORD700630HDFRGV05 | AA68: 1 | AB68: TRUE | AC68: 45671 | AD68: 45671 | AG68: M | AH68: V | AI68: FALSE | AK68: TRUE | AL68: TRUE | AM68: Claudia Alvarez, prima/ Silveria hermana 5533889131 | AQ68: d.2333atm@gmail.com | AU68: 5.2567843e+15 | AV68: Banamex | AW68: 40 | AX68: 34 | AY68: 25 | AZ68: XG | BA68: G | BB68: 776.56 | BC68: FALSE | BD68: 2322356795 | BE68: 2808036943100 | BF68: 7712168071 | BH68: O+ | BI68: 45719 | BJ68: M | BK68: =+Table13[[#This Row],[Nombres]]&" "&Table13[[#This Row],[Ap_paterno]]&" "&Table13[[#This Row],[Ap_materno]] -> David Cortes Rugerio
A69: 2332 | B69: Pacheco | C69: Cano | D69: Arturo | E69: 0 | F69: 28582 | G69: Tlaxcala | H69: PACA7804022J9 | I69: Lazaro Cardenas #10 | J69: Alfonso Espejel | K69: Calpulalpan | L69: Tlaxcala | M69: 90208 | N69: Mexico | O69: Secundaria | Q69: Terminado | R69: Operativo | S69: Operativo | T69: 7491065431 | V69: Normal | X69: 6195780773-0 | Y69: Mexicana | Z69: PACA780402HTLCNR08 | AA69: 1 | AB69: TRUE | AC69: 45671 | AD69: 45671 | AF69: 45678 | AG69: M | AH69: U | AI69: FALSE | AK69: TRUE | AL69: FALSE | AM69: esposa/ 4642067954 hija | AQ69: a.2332tusa@gmail.com | AR69: 45678 | AU69: 5.2567844e+15 | AV69: Banamex | AW69: 34 | AX69: 34 | AY69: 27 | AZ69: M | BA69: M | BB69: 296.37 | BC69: FALSE | BD69: 2306611643 | BE69: 78009761132 | BI69: 45740 | BJ69: M | BK69: =+Table13[[#This Row],[Nombres]]&" "&Table13[[#This Row],[Ap_paterno]]&" "&Table13[[#This Row],[Ap_materno]] -> Arturo Pacheco Cano
A70: 2331 | B70: Eguia | C70: Herrera | D70: Esteban David | E70: 0 | F70: 35245 | G70: Edo de México | H70: EUHE9606296B1 | I70: Oriente 245-D #211 | J70: Agricola Oriental | K70: Iztacalco | L70: Distrito Federal | M70: 8500 | N70: Mexico | O70: Secundaria | Q70: Terminado | R70: Operativo | S70: Operativo | T70: 5647622889 | U70: 53603-01 | V70: Normal | X70: 3915960151-5 | Y70: Mexicana | Z70: EUHE960629HMCGRS07 | AA70: 1 | AB70: TRUE | AC70: 45656 | AD70: 45656 | AF70: 45720 | AG70: M | AH70: U | AI70: FALSE | AK70: TRUE | AL70: TRUE | AM70: Rosalbina mama/ 5560968220 valeria Esposa | AQ70: e.2331tusa@gmail.com | AR70: 45720 | AU70: 5.5791004e+15 | AV70: Banamex | AW70: 40 | AX70: 34 | AY70: 29 | AZ70: G | BA70: G | BB70: 316.5 | BC70: FALSE | BD70: 2539808131 | BE70: 1857104890696 | BH70: A+ | BI70: 45740 | BJ70: M | BK70: =+Table13[[#This Row],[Nombres]]&" "&Table13[[#This Row],[Ap_paterno]]&" "&Table13[[#This Row],[Ap_materno]] -> Esteban David Eguia Herrera
A71: 2330 | B71: Ramirez | C71: Garcia | D71: Edgar Oswaldo | E71: 0 | F71: 31029 | G71: Veracruz | H71: RAGE841213JV6 | I71: Francisco I Madero Edificio S departamento 202 | J71: Fraccionamiento Lomas de Ecatepec | K71: Ecatepec de Morelos | L71: Edo de México | M71: 55080 | N71: Mexico | O71: Medio Superior | Q71: Truncado | R71: Operativo | S71: Operativo | T71: 5512018056 | V71: Normal | X71: 2104842529-8 | Y71: Mexicana | Z71: RAGE841213HVZMRD08 | AA71: 1 | AB71: TRUE | AC71: 45649 | AD71: 45649 | AF71: 45650 | AG71: M | AH71: U | AI71: FALSE | AK71: TRUE | AL71: FALSE | AM71: Conyugue/ Eliseo 7828886256 Padre/ Cesar 5527586926 familiar | AQ71: e.2330tusa@gmail.com | AR71: 45650 | AW71: 40 | AX71: 38 | AY71: 26 | AZ71: G | BA71: G | BB71: 265 | BC71: FALSE | BD71: 2310703811 | BE71: 1347010212109 | BI71: 45673 | BJ71: M | BK71: =+Table13[[#This Row],[Nombres]]&" "&Table13[[#This Row],[Ap_paterno]]&" "&Table13[[#This Row],[Ap_materno]] -> Edgar Oswaldo Ramirez Garcia
A72: 2329 | B72: Garcia | C72: Mar | D72: Roberto | E72: 0 | F72: 32890 | G72: Morelos | H72: GAMR900117467 | I72: Deshoras #408B | J72: Portales de Lincoln | K72: Garcia | L72: Nuevo León | M72: 66013 | N72: Mexico | O72: Medio Superior | Q72: Truncado | R72: Operativo | S72: Operativo | T72: 8184670325 | U72: 53603-01 | V72: Normal | X72: 9607902416-0 | Y72: Mexicana | Z72: GAMR900117HMSRRB01 | AA72: 1 | AB72: TRUE | AC72: 45649 | AD72: 45649 | AF72: 45667 | AG72: M | AH72: S | AI72: FALSE | AK72: TRUE | AL72: TRUE | AM72: 5530600939 abuela/ 9984005076 amigo | AQ72: r.2329tusa@gmail.com | AR72: 45667 | AU72: 5.2567843e+15 | AV72: Banamex | AW72: 40 | AX72: 38 | AY72: 27 | AZ72: XG | BA72: XG | BB72: 0 | BC72: FALSE | BD72: 2492194283 | BE72: 2823081289415 | BI72: 45740 | BJ72: M | BK72: =+Table13[[#This Row],[Nombres]]&" "&Table13[[#This Row],[Ap_paterno]]&" "&Table13[[#This Row],[Ap_materno]] -> Roberto Garcia Mar
A73: 2328 | B73: Morales | C73: Reyes | D73: Pedro Alberto | E73: 0 | F73: 36817 | G73: Nuevo León | H73: MORP001018RN3 | I73: Simon Bolivar | J73: Privada Los Olivos | K73: General Escobedo | L73: Nuevo León | M73: 66052 | N73: Mexico | O73: Medio Superior | Q73: Truncado | R73: Administrativo | S73: Administrativo | T73: 8118952686 | U73: 53603-01 | V73: Normal | W73: 45646 | X73: 0417001733-1 | Y73: Mexicana | Z73: MORP001018HNLRYDA5 | AA73: 2 | AB73: TRUE | AC73: 45646 | AD73: 45646 | AF73: 45674 | AG73: M | AH73: S | AI73: FALSE | AK73: TRUE | AL73: FALSE | AM73: Madre/ 8118514487 Padre | AN73: Conducir | AQ73: p.2328tusa@gmail.com | AR73: 45674 | AU73: 5.579087e+15 | AV73: Banamex | AW73: 34 | AX73: 32 | AY73: 27 | AZ73: M | BA73: M | BB73: 462.48 | BC73: FALSE | BD73: 1798163553 | BE73: 449122232968 | BI73: 45738 | BJ73: M | BK73: =+Table13[[#This Row],[Nombres]]&" "&Table13[[#This Row],[Ap_paterno]]&" "&Table13[[#This Row],[Ap_materno]] -> Pedro Alberto Morales Reyes
A74: 2327 | B74: Carrillo | C74: Torres | D74: Jose Valente | E74: 0 | F74: 25877 | G74: Edo de México | H74: CATV701105Q40 | I74: Calle Sauco | J74: Santa María Tecajete | K74: Zempoala | L74: Hidalgo | M74: 43851 | N74: Mexico | O74: Superior | P74: Medico Veterinario Zootecnista | Q74: Terminado | R74: Operativo | S74: Operativo | T74: 5612311220 | U74: 53603-01 | V74: Normal | X74: 0223705170-7 | Y74: Mexicana | Z74: CATV701105HMCRRL01 | AA74: 1 | AB74: TRUE | AC74: 45639 | AD74: 45639 | AF74: 45719 | AG74: M | AH74: S | AI74: FALSE | AK74: TRUE | AL74: FALSE | AM74: harmana/ 8115027165 hermano | AQ74: j.2327tusa@gmail.com | AR74: 45719 | AU74: 5.5791004e+15 | AV74: Banamex | AW74: 46 | AX74: 40 | AY74: 28 | AZ74: XXXG | BA74: XXXG | BB74: 296.37 | BC74: FALSE | BD74: 1461943912 | BE74: 1010048699916 | BH74: O+ | BI74: 45840 | BJ74: M | BK74: =+Table13[[#This Row],[Nombres]]&" "&Table13[[#This Row],[Ap_paterno]]&" "&Table13[[#This Row],[Ap_materno]] -> Jose Valente Carrillo Torres
A75: 2326 | B75: Juarez | C75: Cortes | D75: Fausto | E75: 0 | F75: 26182 | G75: Edo de México | H75: JUCF710906FF8 | I75: Calle Cedros Mza 7 L15 | J75: Carlos Hank González | K75: Los Reyes La Paz | L75: Edo de México | M75: 56510 | N75: Mexico | O75: Primaria | Q75: Terminado | R75: Operativo | S75: Operativo | T75: 7775684495 | V75: Normal | X75: 0216711389-9 | Y75: Mexicana | Z75: JUCF710906HMCRRS09 | AA75: 1 | AB75: TRUE | AC75: 45639 | AD75: 45639 | AF75: 45640 | AG75: M | AH75: S | AI75: FALSE | AK75: TRUE | AL75: FALSE | AM75: hermano/5530255129 hermana | AQ75: f.2326tusa@gmail.com | AR75: 45640 | AW75: 40 | AX75: 34 | AY75: 27 | AZ75: 0 | BA75: XG | BB75: 265 | BC75: FALSE | BD75: 1329147052 | BE75: 3946044816157 | BI75: 45673 | BJ75: M | BK75: =+Table13[[#This Row],[Nombres]]&" "&Table13[[#This Row],[Ap_paterno]]&" "&Table13[[#This Row],[Ap_materno]] -> Fausto Juarez Cortes
A76: 2325 | B76: Peralta | C76: Alvarado | D76: Javier | E76: 0 | F76: 31500 | G76: Tlaxcala | H76: PEAJ8603299H5 | I76: Francisco Villa | J76: Ampl Pino Suarez | K76: Tepeapulco | L76: Hidalgo | M76: 43974 | N76: Mexico | O76: Medio Superior | Q76: Terminado | R76: Administrativo | S76: Administrativo | T76: 7751092383 | V76: Normal | X76: 0215867096-4 | Y76: Mexicana | Z76: PEAJ860329HTLRLV03 | AA76: 2 | AB76: TRUE | AC76: 45619 | AD76: 45619 | AG76: M | AH76: U | AI76: FALSE | AK76: FALSE | AL76: FALSE | AM76: Hermana, 7919149071 Madre | AP76: Jardineria | AQ76: j.2325tusa@gmail.com | AU76: 5.2567843e+15 | AV76: Banamex | AW76: 34 | AX76: 32 | AY76: 27 | AZ76: G | BA76: M | BB76: 463.26 | BC76: FALSE | BD76: 1468207279 | BE76: 1192075215638 | BF76: 7711278210 | BI76: 45660 | BJ76: M | BK76: =+Table13[[#This Row],[Nombres]]&" "&Table13[[#This Row],[Ap_paterno]]&" "&Table13[[#This Row],[Ap_materno]] -> Javier Peralta Alvarado
A77: 2324 | B77: Galicia | C77: Rivera | D77: Isaac | E77: 0 | F77: 38365 | G77: Distrito Federal | H77: GARI0501134N9 | I77: Tarascos L.25 Mza44 | J77: Pedregal de Santa Ursula Xitla | K77: Tlalpan | L77: Distrito Federal | M77: 14438 | N77: Mexico | O77: Medio Superior | Q77: Truncado | R77: Operativo | S77: Operativo | T77: 5576124158 | U77: 53603-01 | V77: Normal | X77: 0220053480-4 | Y77: Mexicana | Z77: GARI050113HDFLVSA4 | AA77: 1 | AB77: TRUE | AC77: 45636 | AD77: 45636 | AF77: 45677 | AG77: M | AH77: S | AI77: FALSE | AK77: TRUE | AL77: TRUE | AM77: abuelo/ 5533643479 papá | AQ77: i.2324tusa@gmail.com | AR77: 45677 | AU77: 5.579087e+15 | AV77: Banamex | AW77: 36 | AX77: 36 | AY77: 26 | AZ77: G | BA77: CH | BB77: 265 | BC77: FALSE | BD77: 2423970106 | BE77: 3904133864931 | BI77: 45740 | BJ77: M | BK77: =+Table13[[#This Row],[Nombres]]&" "&Table13[[#This Row],[Ap_paterno]]&" "&Table13[[#This Row],[Ap_materno]] -> Isaac Galicia Rivera
A78: 2323 | B78: Jimenez | C78: Rosenberg | D78: Hector Enrico | E78: 0 | F78: 23575 | G78: Hidalgo | H78: JIRH640717S26 | I78: Metzquititlan | J78: Parque de poblamiento | K78: Pachuca de Soto | L78: Hidalgo | M78: 32042 | N78: Mexico | O78: Maestria | P78: Administracion de tecnologia de la informaion | Q78: Terminado | R78: Administrativo | S78: Administrativo | T78: 7716785839 | U78: 53603-01 | V78: Normal | W78: 45635 | X78: 2285640232-0 | Y78: Mexicana | Z78: JIRH640717HNEMSC00 | AA78: 2 | AB78: TRUE | AC78: 45635 | AD78: 45635 | AF78: 45665 | AG78: M | AH78: U | AI78: FALSE | AK78: TRUE | AL78: TRUE | AM78: Esposa/ 5534687903 | AN78: Administracion de proyectos, planeacion tecnologica | AO78: Analisis de datos | AP78: Tecnologia | AQ78: h.2323tusa@gmail.com | AR78: 45665 | AU78: 5.5791004e+15 | AV78: Banamex | AW78: 34 | AX78: 32 | AY78: 28 | AZ78: G | BA78: M | BB78: 519.48 | BC78: FALSE | BD78: 1906763978 | BE78: 880058996509 | BI78: 45668 | BJ78: M | BK78: =+Table13[[#This Row],[Nombres]]&" "&Table13[[#This Row],[Ap_paterno]]&" "&Table13[[#This Row],[Ap_materno]] -> Hector Enrico Jimenez Rosenberg
A79: 2322 | B79: Flores | C79: Garcia | D79: Gilberto Francisco | E79: 1 | F79: 29132 | G79: Tamaulipas | H79: FOGG791004I53 | I79: Calle Cerro Prieto | J79: Rodriguez | K79: Matamoros | L79: Tamaulipas | M79: 87395 | N79: Mexico | O79: Primaria | Q79: Terminado | R79: Operativo | S79: Operativo | T79: 8683538032 | U79: 53603-01 | V79: Normal | X79: 2187932922 | Y79: Mexicana | Z79: FOGG791004HTSLRL06 | AA79: 1 | AB79: TRUE | AC79: 45623 | AD79: 45623 | AF79: 45724 | AG79: M | AH79: C | AI79: FALSE | AK79: TRUE | AL79: FALSE | AM79: esposa/8681908748 papás | AQ79: g.2322tusa@gmail.com | AR79: 45724 | AU79: 5.5791004e+15 | AV79: Banamex | AW79: 42 | AX79: 34 | AY79: 27 | AZ79: CH | BA79: XG | BB79: 383.39 | BC79: FALSE | BD79: 2463961911 | BE79: 670070710116 | BH79: O+ | BI79: 45740 | BJ79: M | BK79: =+Table13[[#This Row],[Nombres]]&" "&Table13[[#This Row],[Ap_paterno]]&" "&Table13[[#This Row],[Ap_materno]] -> Gilberto Francisco Flores Garcia
A80: 2321 | B80: Quintos | C80: Mellado | D80: Geronimo | E80: 0 | F80: 34616 | G80: Hidalgo | H80: QUMG941009LJ4 | I80: Victoria Sur | J80: Centro | K80: Apan | L80: Hidalgo | M80: 43200 | N80: Mexico | O80: Medio Superior | P80: Técnico Agropecuario | Q80: Terminado | R80: Operativo | S80: Operativo | T80: 7752022500 | U80: 53603-01 | V80: Normal | X80: 1312943359-8 | Y80: Mexicana | Z80: QUMG941009HHGNLR00 | AA80: 1 | AB80: TRUE | AC80: 45618 | AD80: 45618 | AF80: 45753 | AG80: M | AH80: C | AI80: FALSE | AK80: TRUE | AL80: TRUE | AM80: esposa/ 7751880972 papá | AQ80: g.2321tusa@gmail.com | AR80: 45753 | AU80: 5.2567843e+15 | AV80: Banamex | AW80: 44 | AX80: 38 | AY80: 28 | AZ80: XG | BA80: XG | BB80: 478.63 | BC80: FALSE | BD80: 2585571322 | BE80: 130093278535 | BH80: B+ | BI80: 45842 | BJ80: M | BK80: =+Table13[[#This Row],[Nombres]]&" "&Table13[[#This Row],[Ap_paterno]]&" "&Table13[[#This Row],[Ap_materno]] -> Geronimo Quintos Mellado
A81: 2320 | B81: Sanchez | C81: Torres | D81: Arleth BAJA | E81: 0 | F81: 35617 | G81: Edo de México | H81: SATA970706Q69 | I81: Pico de Orizaba | J81: Fraccionamiento Valle de Guadalupe | K81: CD Sahagun | L81: Hidalgo | M81: 43996 | N81: Mexico | O81: Superior | P81: Ingenieria Industrial | Q81: Terminado | R81: Administrativo | S81: Administrativo | T81: 3323604334 | V81: Normal | W81: 45608 | X81: 1315974451-8 | Y81: Mexicana | Z81: SATA970706MMCNRR07 | AA81: 2 | AB81: TRUE | AC81: 45608 | AD81: 45608 | AF81: 45624 | AG81: F | AH81: S | AI81: FALSE | AK81: TRUE | AL81: TRUE | AM81: papa/ 7712205582 mama | AO81: Logistica | AQ81: a.2320tusa@gmail.com | AR81: 45624 | AW81: G | AX81: 36 | AY81: 25 | AZ81: G | BA81: G | BB81: 519.48 | BC81: FALSE | BD81: 1876731920 | BE81: 1224103719647 | BI81: 45701 | BJ81: M | BK81: =+Table13[[#This Row],[Nombres]]&" "&Table13[[#This Row],[Ap_paterno]]&" "&Table13[[#This Row],[Ap_materno]] -> Arleth BAJA Sanchez Torres
